{
  "page": 63,
  "content": "```json\n[\n  {\n    \"page_context\": {\n      \"title\": \"Приложение №3. Изображения графиков ЯМР участков исследуемых...\"\n    },\n    \"graph_id\": 1,\n    \"header_data\": {\n      \"full_text\": \"Образец № 3 к Заключению № 11366; Индекс кристалличности = 0.77994; Протонная плотность = 2.30121\",\n      \"structured_metrics\": {\n        \"sample_reference\": \"Образец № 3 к Заключению № 11366\",\n        \"crystallinity_index\": 0.77994,\n        \"proton_density\": 2.30121\n      }\n    },\n    \"graph_statistics\": {\n      \"axes\": {\n        \"y_axis\": {\n          \"label\": \"Амплитуда\",\n          \"visible_min\": null,\n          \"visible_max\": null,\n          \"step_interval\": null\n        },\n        \"x_axis\": {\n          \"label\": \"Время, мкс\",\n          \"visible_min\": null,\n          \"visible_max\": null,\n          \"step_interval\": null\n        }\n      },\n      \"y_metrics_max\": {\n        \"red\": null,\n        \"blue\": null,\n        \"green\": null\n      },\n      \"visible_tabs\": [\"NMR Signal\", \"Results Graph\", \"Code\"]\n    },\n    \"log_panel_data\": {\n      \"timestamp\": \"10:32:16\",\n      \"raw_lines\": [\n        \"Дата исследования - 19.07.2023\",\n        \"Время релаксации короткой компоненты - 296.31590 мкс\",\n        \"Время релаксации длинной компоненты - 3127.56525 мкс\",\n        \"Амплитуда короткой компоненты - 1.24691 a.u.\",\n        \"Амплитуда длинной компоненты - 9.34851 a.u.\",\n        \"Полученный индекс кристалличности = 0.77994\",\n        \"Протонная плотность = 2.30121\"\n      ],\n      \"structured_log_metrics\": {\n        \"research_date\": \"19.07.2023\",\n        \"relaxation_time_short_component_mks\": 296.31590,\n        \"relaxation_time_long_component_mks\": 3127.56525,\n        \"amplitude_short_component_au\": 1.24691,\n        \"amplitude_long_component_au\": 9.34851,\n        \"calculated_crystallinity_index\": 0.77994,\n        \"calculated_proton_density\": 2.30121\n      }\n    },\n    \"status_bar_data\": {\n      \"urtb\": \"3%\",\n      \"adc\": \"0%\",\n      \"base_offset\": \"100% 100%\",\n      \"operation\": \"Чтение буфера A\",\n      \"numeric_values\": \"135.0 0.7823 2032 2094\"\n    },\n    \"caption_data\": {\n      \"illustration_number\": \"124\",\n      \"full_text\": \"Иллюстрация №124. Изображение одного из ЯМР участков исследуемых штрихов рукописной подписи от имени Шмульт Т.А. в предоставленном на исследование Объекте №10 при третьем проколе.\",\n      \"structured_details\": {\n        \"object_type\": \"штрихов рукописной подписи\",\n        \"source_item\": \"Шмульт Т.А.\",\n        \"investigation_object\": \"Объект №10\",\n        \"condition\": \"при третьем проколе\"\n      }\n    }\n  },\n  {\n    \"graph_id\": 2,\n    \"header_data\": {\n      \"full_text\": \"Образец № 3 к Заключению № 11366; Индекс кристалличности = 0.80121; Протонная плотность = 4.45428\",\n      \"structured_metrics\": {\n        \"sample_reference\": \"Образец № 3 к Заключению № 11366\",\n        \"crystallinity_index\": 0.80121,\n        \"proton_density\": 4.45428\n      }\n    },\n    \"graph_statistics\": {\n      \"axes\": {\n        \"y_axis\": {\n          \"label\": \"Амплитуда\",\n          \"visible_min\": null,\n          \"visible_max\": null,\n          \"step_interval\": null\n        },\n        \"x_axis\": {\n          \"label\": \"Время, мкс\",\n          \"visible_min\": null,\n          \"visible_max\": null,\n          \"step_interval\": null\n        }\n      },\n      \"y_metrics_max\": {\n        \"red\": null,\n        \"blue\": null,\n        \"green\": null\n      },\n      \"visible_tabs\": [\"NMR Signal\", \"Results Graph\", \"Code\"]\n    },\n    \"log_panel_data\": {\n      \"timestamp\": \"10:37:34\",\n      \"raw_lines\": [\n        \"Дата исследования - 19.07.2023\",\n        \"Время релаксации короткой компоненты - 197.56997 мкс\",\n        \"Время релаксации длинной компоненты - 3127.65565 мкс\",\n        \"Амплитуда короткой компоненты - 0.99448 a.u.\",\n        \"Амплитуда длинной компоненты - 12.91563 a.u.\",\n        \"Полученный индекс кристалличности = 0.80121\",\n        \"Протонная плотность = 4.45428\"\n      ],\n      \"structured_log_metrics\": {\n        \"research_date\": \"19.07.2023\",\n        \"relaxation_time_short_component_mks\": 197.56997,\n        \"relaxation_time_long_component_mks\": 3127.65565,\n        \"amplitude_short_component_au\": 0.99448,\n        \"amplitude_long_component_au\": 12.91563,\n        \"calculated_crystallinity_index\": 0.80121,\n        \"calculated_proton_density\": 4.45428\n      }\n    },\n    \"status_bar_data\": {\n      \"urtb\": \"3%\",\n      \"adc\": \"0%\",\n      \"base_offset\": \"100% 100%\",\n      \"operation\": \"Чтение буфера A\",\n      \"numeric_values\": \"135.0 0.7823 2032 2094\"\n    },\n    \"caption_data\": {\n      \"illustration_number\": \"125\",\n      \"full_text\": \"Иллюстрация №125. Изображение одного из ЯМР участков исследуемых штрихов рукописной подписи от имени Губашева С.С. в предоставленном на исследование Объекте №11 при третьем проколе.\",\n      \"structured_details\": {\n        \"object_type\": \"штрихов рукописной подписи\",\n        \"source_item\": \"Губашева С.С.\",\n        \"investigation_object\": \"Объект №11\",\n        \"condition\": \"при третьем проколе\"\n      }\n    }\n  }\n]\n```",
  "graphs": [
    {
      "page_context": {
        "title": "Приложение №3. Изображения графиков ЯМР участков исследуемых..."
      },
      "graph_id": 1,
      "header_data": {
        "full_text": "Образец № 3 к Заключению № 11366; Индекс кристалличности = 0.77994; Протонная плотность = 2.30121",
        "structured_metrics": {
          "sample_reference": "Образец № 3 к Заключению № 11366",
          "crystallinity_index": 0.77994,
          "proton_density": 2.30121
        }
      },
      "graph_statistics": {
        "axes": {
          "y_axis": {
            "label": "Амплитуда",
            "visible_min": null,
            "visible_max": null,
            "step_interval": null
          },
          "x_axis": {
            "label": "Время, мкс",
            "visible_min": null,
            "visible_max": null,
            "step_interval": null
          }
        },
        "y_metrics_max": {
          "red": null,
          "blue": null,
          "green": null
        },
        "visible_tabs": [
          "NMR Signal",
          "Results Graph",
          "Code"
        ]
      },
      "log_panel_data": {
        "timestamp": "10:32:16",
        "raw_lines": [
          "Дата исследования - 19.07.2023",
          "Время релаксации короткой компоненты - 296.31590 мкс",
          "Время релаксации длинной компоненты - 3127.56525 мкс",
          "Амплитуда короткой компоненты - 1.24691 a.u.",
          "Амплитуда длинной компоненты - 9.34851 a.u.",
          "Полученный индекс кристалличности = 0.77994",
          "Протонная плотность = 2.30121"
        ],
        "structured_log_metrics": {
          "research_date": "19.07.2023",
          "relaxation_time_short_component_mks": 296.3159,
          "relaxation_time_long_component_mks": 3127.56525,
          "amplitude_short_component_au": 1.24691,
          "amplitude_long_component_au": 9.34851,
          "calculated_crystallinity_index": 0.77994,
          "calculated_proton_density": 2.30121
        }
      },
      "status_bar_data": {
        "urtb": "3%",
        "adc": "0%",
        "base_offset": "100% 100%",
        "operation": "Чтение буфера A",
        "numeric_values": "135.0 0.7823 2032 2094"
      },
      "caption_data": {
        "illustration_number": "124",
        "full_text": "Иллюстрация №124. Изображение одного из ЯМР участков исследуемых штрихов рукописной подписи от имени Шмульт Т.А. в предоставленном на исследование Объекте №10 при третьем проколе.",
        "structured_details": {
          "object_type": "штрихов рукописной подписи",
          "source_item": "Шмульт Т.А.",
          "investigation_object": "Объект №10",
          "condition": "при третьем проколе"
        }
      }
    },
    {
      "graph_id": 2,
      "header_data": {
        "full_text": "Образец № 3 к Заключению № 11366; Индекс кристалличности = 0.80121; Протонная плотность = 4.45428",
        "structured_metrics": {
          "sample_reference": "Образец № 3 к Заключению № 11366",
          "crystallinity_index": 0.80121,
          "proton_density": 4.45428
        }
      },
      "graph_statistics": {
        "axes": {
          "y_axis": {
            "label": "Амплитуда",
            "visible_min": null,
            "visible_max": null,
            "step_interval": null
          },
          "x_axis": {
            "label": "Время, мкс",
            "visible_min": null,
            "visible_max": null,
            "step_interval": null
          }
        },
        "y_metrics_max": {
          "red": null,
          "blue": null,
          "green": null
        },
        "visible_tabs": [
          "NMR Signal",
          "Results Graph",
          "Code"
        ]
      },
      "log_panel_data": {
        "timestamp": "10:37:34",
        "raw_lines": [
          "Дата исследования - 19.07.2023",
          "Время релаксации короткой компоненты - 197.56997 мкс",
          "Время релаксации длинной компоненты - 3127.65565 мкс",
          "Амплитуда короткой компоненты - 0.99448 a.u.",
          "Амплитуда длинной компоненты - 12.91563 a.u.",
          "Полученный индекс кристалличности = 0.80121",
          "Протонная плотность = 4.45428"
        ],
        "structured_log_metrics": {
          "research_date": "19.07.2023",
          "relaxation_time_short_component_mks": 197.56997,
          "relaxation_time_long_component_mks": 3127.65565,
          "amplitude_short_component_au": 0.99448,
          "amplitude_long_component_au": 12.91563,
          "calculated_crystallinity_index": 0.80121,
          "calculated_proton_density": 4.45428
        }
      },
      "status_bar_data": {
        "urtb": "3%",
        "adc": "0%",
        "base_offset": "100% 100%",
        "operation": "Чтение буфера A",
        "numeric_values": "135.0 0.7823 2032 2094"
      },
      "caption_data": {
        "illustration_number": "125",
        "full_text": "Иллюстрация №125. Изображение одного из ЯМР участков исследуемых штрихов рукописной подписи от имени Губашева С.С. в предоставленном на исследование Объекте №11 при третьем проколе.",
        "structured_details": {
          "object_type": "штрихов рукописной подписи",
          "source_item": "Губашева С.С.",
          "investigation_object": "Объект №11",
          "condition": "при третьем проколе"
        }
      }
    }
  ],
  "model": "gpt-4o-2024-08-06",
  "usage": {
    "prompt_tokens": 2025,
    "completion_tokens": 1516,
    "total_tokens": 3541,
    "prompt_tokens_details": {
      "cached_tokens": 0,
      "audio_tokens": 0
    },
    "completion_tokens_details": {
      "reasoning_tokens": 0,
      "audio_tokens": 0,
      "accepted_prediction_tokens": 0,
      "rejected_prediction_tokens": 0
    }
  }
}