{
  "page": 37,
  "content": "```json\n[\n  {\n    \"page_context\": {\n      \"title\": \"Приложение №7. Изображение участков ЯМР участков исследуемых штрихов отпечатка круглой мастичной печати ООО «Агро-Индустриальная Корпорация «Волго-Дон» и исследование Объекте №9 при первом проколе.\"\n    },\n    \"graph_id\": 1,\n    \"header_data\": {\n      \"full_text\": \"Образец № 1 к Заключению № 11366; Индекс кристалличности = 0.78381; Протонная плотность = 4.71697\",\n      \"structured_metrics\": {\n        \"sample_reference\": \"Образец № 1 к Заключению № 11366\",\n        \"crystallinity_index\": 0.78381,\n        \"proton_density\": 4.71697\n      }\n    },\n    \"graph_statistics\": {\n      \"axes\": {\n        \"y_axis\": {\n          \"label\": \"Интенсивность, а. е.\",\n          \"visible_min\": 0,\n          \"visible_max\": 50,\n          \"step_interval\": 10\n        },\n        \"x_axis\": {\n          \"label\": \"Время, мкс\",\n          \"visible_min\": 0,\n          \"visible_max\": 250,\n          \"step_interval\": 50\n        }\n      },\n      \"y_metrics_max\": {\n        \"red\": null,\n        \"blue\": null,\n        \"green\": null\n      },\n      \"visible_tabs\": []\n    },\n    \"log_panel_data\": {\n      \"timestamp\": \"12:37:12\",\n      \"raw_lines\": [\n        \"Дата исследования - 24.06.2023\",\n        \"Время релаксации короткой компоненты - 188.84218 мкс\",\n        \"Время релаксации длинной компоненты - 1282.14761 мкс\",\n        \"Амплитуда короткой компоненты - 11.14671 а.е.\",\n        \"Амплитуда длинной компоненты - 3.73447 а.е.\",\n        \"Протонная плотность - 4.71697\"\n      ],\n      \"structured_log_metrics\": {\n        \"research_date\": \"24.06.2023\",\n        \"relaxation_time_short_component_mks\": 188.84218,\n        \"relaxation_time_long_component_mks\": 1282.14761,\n        \"amplitude_short_component_au\": 11.14671,\n        \"amplitude_long_component_au\": 3.73447,\n        \"calculated_crystallinity_index\": 0.78381,\n        \"calculated_proton_density\": 4.71697\n      }\n    },\n    \"status_bar_data\": {\n      \"urtb\": \"3%\",\n      \"adc\": \"0%\",\n      \"base_offset\": \"100% 100%\",\n      \"operation\": \"Чтение буфера A\",\n      \"numeric_values\": \"130.5 0.7823 2032 2094\"\n    },\n    \"caption_data\": {\n      \"illustration_number\": \"72\",\n      \"full_text\": \"Иллюстрация №72. Изображение одного из ЯМР участков исследуемых штрихов отпечатка круглой мастичной печати ООО «Агро-Индустриальная Корпорация «Волго-Дон» в предоставленном на исследование Объекте №9 при первом проколе.\",\n      \"structured_details\": {\n        \"object_type\": \"ЯМР участок\",\n        \"source_item\": \"ООО «Агро-Индустриальная Корпорация «Волго-Дон»\",\n        \"investigation_object\": \"Объекте №9\",\n        \"condition\": \"первый прокол\"\n      }\n    }\n  },\n  {\n    \"page_context\": {\n      \"title\": \"Приложение №7. Изображение участков ЯМР участков исследуемых штрихов отпечатка круглой мастичной печати ООО «Агро-Индустриальная Корпорация «Волго-Дон» и исследование Объекте №9 при первом проколе.\"\n    },\n    \"graph_id\": 2,\n    \"header_data\": {\n      \"full_text\": \"Образец № 1 к Заключению № 11366; Индекс кристалличности = 0.82851; Протонная плотность = 3.39068\",\n      \"structured_metrics\": {\n        \"sample_reference\": \"Образец № 1 к Заключению № 11366\",\n        \"crystallinity_index\": 0.82851,\n        \"proton_density\": 3.39068\n      }\n    },\n    \"graph_statistics\": {\n      \"axes\": {\n        \"y_axis\": {\n          \"label\": \"Интенсивность, а.е.\",\n          \"visible_min\": 0,\n          \"visible_max\": 50,\n          \"step_interval\": 10\n        },\n        \"x_axis\": {\n          \"label\": \"Время, мкс\",\n          \"visible_min\": 0,\n          \"visible_max\": 250,\n          \"step_interval\": 50\n        }\n      },\n      \"y_metrics_max\": {\n        \"red\": null,\n        \"blue\": null,\n        \"green\": null\n      },\n      \"visible_tabs\": []\n    },\n    \"log_panel_data\": {\n      \"timestamp\": \"12:22:58\",\n      \"raw_lines\": [\n        \"Дата исследования - 24.06.2023\",\n        \"Время релаксации короткой компоненты - 90.12004 мкс\",\n        \"Время релаксации длинной компоненты - 630.25020 мкс\",\n        \"Амплитуда короткой компоненты - 6.64821 а.е.\",\n        \"Амплитуда длинной компоненты - 2.04831 а.е.\",\n        \"Протонная плотность - 3.39068\"\n      ],\n      \"structured_log_metrics\": {\n        \"research_date\": \"24.06.2023\",\n        \"relaxation_time_short_component_mks\": 90.12004,\n        \"relaxation_time_long_component_mks\": 630.25020,\n        \"amplitude_short_component_au\": 6.64821,\n        \"amplitude_long_component_au\": 2.04831,\n        \"calculated_crystallinity_index\": 0.82851,\n        \"calculated_proton_density\": 3.39068\n      }\n    },\n    \"status_bar_data\": {\n      \"urtb\": \"3%\",\n      \"adc\": \"0%\",\n      \"base_offset\": \"100% 100%\",\n      \"operation\": \"Чтение буфера A\",\n      \"numeric_values\": \"130.5 0.7823 2032 2094\"\n    },\n    \"caption_data\": {\n      \"illustration_number\": \"73\",\n      \"full_text\": \"Иллюстрация №73. Изображение одного из ЯМР участков исследуемых штрихов отпечатка круглой мастичной печати ПАО «Московский Индустриальный банк» в предоставленном на исследование Объекте №10 при первом проколе.\",\n      \"structured_details\": {\n        \"object_type\": \"ЯМР участок\",\n        \"source_item\": \"ПАО «Московский Индустриальный банк»\",\n        \"investigation_object\": \"Объекте №10\",\n        \"condition\": \"первый прокол\"\n      }\n    }\n  }\n]\n```",
  "graphs": [
    {
      "page_context": {
        "title": "Приложение №7. Изображение участков ЯМР участков исследуемых штрихов отпечатка круглой мастичной печати ООО «Агро-Индустриальная Корпорация «Волго-Дон» и исследование Объекте №9 при первом проколе."
      },
      "graph_id": 1,
      "header_data": {
        "full_text": "Образец № 1 к Заключению № 11366; Индекс кристалличности = 0.78381; Протонная плотность = 4.71697",
        "structured_metrics": {
          "sample_reference": "Образец № 1 к Заключению № 11366",
          "crystallinity_index": 0.78381,
          "proton_density": 4.71697
        }
      },
      "graph_statistics": {
        "axes": {
          "y_axis": {
            "label": "Интенсивность, а. е.",
            "visible_min": 0,
            "visible_max": 50,
            "step_interval": 10
          },
          "x_axis": {
            "label": "Время, мкс",
            "visible_min": 0,
            "visible_max": 250,
            "step_interval": 50
          }
        },
        "y_metrics_max": {
          "red": null,
          "blue": null,
          "green": null
        },
        "visible_tabs": []
      },
      "log_panel_data": {
        "timestamp": "12:37:12",
        "raw_lines": [
          "Дата исследования - 24.06.2023",
          "Время релаксации короткой компоненты - 188.84218 мкс",
          "Время релаксации длинной компоненты - 1282.14761 мкс",
          "Амплитуда короткой компоненты - 11.14671 а.е.",
          "Амплитуда длинной компоненты - 3.73447 а.е.",
          "Протонная плотность - 4.71697"
        ],
        "structured_log_metrics": {
          "research_date": "24.06.2023",
          "relaxation_time_short_component_mks": 188.84218,
          "relaxation_time_long_component_mks": 1282.14761,
          "amplitude_short_component_au": 11.14671,
          "amplitude_long_component_au": 3.73447,
          "calculated_crystallinity_index": 0.78381,
          "calculated_proton_density": 4.71697
        }
      },
      "status_bar_data": {
        "urtb": "3%",
        "adc": "0%",
        "base_offset": "100% 100%",
        "operation": "Чтение буфера A",
        "numeric_values": "130.5 0.7823 2032 2094"
      },
      "caption_data": {
        "illustration_number": "72",
        "full_text": "Иллюстрация №72. Изображение одного из ЯМР участков исследуемых штрихов отпечатка круглой мастичной печати ООО «Агро-Индустриальная Корпорация «Волго-Дон» в предоставленном на исследование Объекте №9 при первом проколе.",
        "structured_details": {
          "object_type": "ЯМР участок",
          "source_item": "ООО «Агро-Индустриальная Корпорация «Волго-Дон»",
          "investigation_object": "Объекте №9",
          "condition": "первый прокол"
        }
      }
    },
    {
      "page_context": {
        "title": "Приложение №7. Изображение участков ЯМР участков исследуемых штрихов отпечатка круглой мастичной печати ООО «Агро-Индустриальная Корпорация «Волго-Дон» и исследование Объекте №9 при первом проколе."
      },
      "graph_id": 2,
      "header_data": {
        "full_text": "Образец № 1 к Заключению № 11366; Индекс кристалличности = 0.82851; Протонная плотность = 3.39068",
        "structured_metrics": {
          "sample_reference": "Образец № 1 к Заключению № 11366",
          "crystallinity_index": 0.82851,
          "proton_density": 3.39068
        }
      },
      "graph_statistics": {
        "axes": {
          "y_axis": {
            "label": "Интенсивность, а.е.",
            "visible_min": 0,
            "visible_max": 50,
            "step_interval": 10
          },
          "x_axis": {
            "label": "Время, мкс",
            "visible_min": 0,
            "visible_max": 250,
            "step_interval": 50
          }
        },
        "y_metrics_max": {
          "red": null,
          "blue": null,
          "green": null
        },
        "visible_tabs": []
      },
      "log_panel_data": {
        "timestamp": "12:22:58",
        "raw_lines": [
          "Дата исследования - 24.06.2023",
          "Время релаксации короткой компоненты - 90.12004 мкс",
          "Время релаксации длинной компоненты - 630.25020 мкс",
          "Амплитуда короткой компоненты - 6.64821 а.е.",
          "Амплитуда длинной компоненты - 2.04831 а.е.",
          "Протонная плотность - 3.39068"
        ],
        "structured_log_metrics": {
          "research_date": "24.06.2023",
          "relaxation_time_short_component_mks": 90.12004,
          "relaxation_time_long_component_mks": 630.2502,
          "amplitude_short_component_au": 6.64821,
          "amplitude_long_component_au": 2.04831,
          "calculated_crystallinity_index": 0.82851,
          "calculated_proton_density": 3.39068
        }
      },
      "status_bar_data": {
        "urtb": "3%",
        "adc": "0%",
        "base_offset": "100% 100%",
        "operation": "Чтение буфера A",
        "numeric_values": "130.5 0.7823 2032 2094"
      },
      "caption_data": {
        "illustration_number": "73",
        "full_text": "Иллюстрация №73. Изображение одного из ЯМР участков исследуемых штрихов отпечатка круглой мастичной печати ПАО «Московский Индустриальный банк» в предоставленном на исследование Объекте №10 при первом проколе.",
        "structured_details": {
          "object_type": "ЯМР участок",
          "source_item": "ПАО «Московский Индустриальный банк»",
          "investigation_object": "Объекте №10",
          "condition": "первый прокол"
        }
      }
    }
  ],
  "model": "gpt-4o-2024-08-06",
  "usage": {
    "prompt_tokens": 2025,
    "completion_tokens": 1628,
    "total_tokens": 3653,
    "prompt_tokens_details": {
      "cached_tokens": 0,
      "audio_tokens": 0
    },
    "completion_tokens_details": {
      "reasoning_tokens": 0,
      "audio_tokens": 0,
      "accepted_prediction_tokens": 0,
      "rejected_prediction_tokens": 0
    }
  }
}