{
  "page": 7,
  "content": "```json\n[\n  {\n    \"page_context\": {\n      \"title\": \"Приложение №6. Изображения графиков ЯМР участков…\"\n    },\n    \"graph_id\": 1,\n    \"header_data\": {\n      \"full_text\": \"Образец № 1 к Заключению № 11366; Индекс кристалличности = 0.82548; Протонная плотность = 4.74334\",\n      \"structured_metrics\": {\n        \"sample_reference\": \"Образец № 1 к Заключению № 11366\",\n        \"crystallinity_index\": 0.82548,\n        \"proton_density\": 4.74334\n      }\n    },\n    \"graph_statistics\": {\n      \"axes\": {\n        \"y_axis\": {\n          \"label\": \"Интенсивность\",\n          \"visible_min\": null,\n          \"visible_max\": null,\n          \"step_interval\": null\n        },\n        \"x_axis\": {\n          \"label\": \"Время, мкс\",\n          \"visible_min\": null,\n          \"visible_max\": null,\n          \"step_interval\": null\n        }\n      },\n      \"y_metrics_max\": {\n        \"red\": null,\n        \"blue\": null,\n        \"green\": null\n      },\n      \"visible_tabs\": []\n    },\n    \"log_panel_data\": {\n      \"timestamp\": \"08:07:24\",\n      \"raw_lines\": [\n        \"Дата исследования - 24.06.2025\",\n        \"Время релаксации короткой компоненты - 279.15117 мкс\",\n        \"Время релаксации длинной компоненты - 911.89201 мкс\",\n        \"Амплитуда короткой компоненты - 10.59124 a.u.\",\n        \"Амплитуда длинной компоненты - 4.19664 a.u.\",\n        \"Индекс кристалличности = 7.80354\",\n        \"Протонная плотность = 4.74334\"\n      ],\n      \"structured_log_metrics\": {\n        \"research_date\": \"24.06.2025\",\n        \"relaxation_time_short_component_mks\": 279.15117,\n        \"relaxation_time_long_component_mks\": 911.89201,\n        \"amplitude_short_component_au\": 10.59124,\n        \"amplitude_long_component_au\": 4.19664,\n        \"calculated_crystallinity_index\": 7.80354,\n        \"calculated_proton_density\": 4.74334\n      }\n    },\n    \"status_bar_data\": {\n      \"urtb\": \"3%\",\n      \"adc\": \"100%\",\n      \"base_offset\": \"100% 100%\",\n      \"operation\": \"Чтение буфера A\",\n      \"numeric_values\": \"135.0 0.7823 2032 2094\"\n    },\n    \"caption_data\": {\n      \"illustration_number\": \"№12\",\n      \"full_text\": \"Изображение одного из ЯМР участков исследуемых штрихов рукописной подписи от имени Шмульт Т.А. в предоставленном на исследование Объекте №3 при первом проколе.\",\n      \"structured_details\": {\n        \"object_type\": \"ЯМР\",\n        \"source_item\": \"рукописной подписи\",\n        \"investigation_object\": \"Объект №3\",\n        \"condition\": \"первом проколе\"\n      }\n    }\n  },\n  {\n    \"page_context\": {\n      \"title\": \"Приложение №6. Изображения графиков ЯМР участков…\"\n    },\n    \"graph_id\": 2,\n    \"header_data\": {\n      \"full_text\": \"Образец № 1 к Заключению № 11366; Индекс кристалличности = 0.82911; Протонная плотность = 2.69566\",\n      \"structured_metrics\": {\n        \"sample_reference\": \"Образец № 1 к Заключению № 11366\",\n        \"crystallinity_index\": 0.82911,\n        \"proton_density\": 2.69566\n      }\n    },\n    \"graph_statistics\": {\n      \"axes\": {\n        \"y_axis\": {\n          \"label\": \"Интенсивность\",\n          \"visible_min\": null,\n          \"visible_max\": null,\n          \"step_interval\": null\n        },\n        \"x_axis\": {\n          \"label\": \"Время, мкс\",\n          \"visible_min\": null,\n          \"visible_max\": null,\n          \"step_interval\": null\n        }\n      },\n      \"y_metrics_max\": {\n        \"red\": null,\n        \"blue\": null,\n        \"green\": null\n      },\n      \"visible_tabs\": []\n    },\n    \"log_panel_data\": {\n      \"timestamp\": \"08:11:53\",\n      \"raw_lines\": [\n        \"Дата исследования - 24.06.2025\",\n        \"Время релаксации короткой компоненты - 334.53589 мкс\",\n        \"Время релаксации длинной компоненты - 892.44168 мкс\",\n        \"Амплитуда короткой компоненты - 12.91935 a.u.\",\n        \"Амплитуда длинной компоненты - 3.62729 a.u.\",\n        \"Индекс кристалличности = 8.22458\",\n        \"Протонная плотность = 2.69566\"\n      ],\n      \"structured_log_metrics\": {\n        \"research_date\": \"24.06.2025\",\n        \"relaxation_time_short_component_mks\": 334.53589,\n        \"relaxation_time_long_component_mks\": 892.44168,\n        \"amplitude_short_component_au\": 12.91935,\n        \"amplitude_long_component_au\": 3.62729,\n        \"calculated_crystallinity_index\": 8.22458,\n        \"calculated_proton_density\": 2.69566\n      }\n    },\n    \"status_bar_data\": {\n      \"urtb\": \"3%\",\n      \"adc\": \"100%\",\n      \"base_offset\": \"100% 100%\",\n      \"operation\": \"Чтение буфера A\",\n      \"numeric_values\": \"135.0 0.7823 2032 2094\"\n    },\n    \"caption_data\": {\n      \"illustration_number\": \"№13\",\n      \"full_text\": \"Изображение одного из ЯМР участков исследуемых штрихов рукописной подписи нераспознанного лица №1 в предоставленном на исследование Объекте №3 при первом проколе.\",\n      \"structured_details\": {\n        \"object_type\": \"ЯМР\",\n        \"source_item\": \"рукописной подписи\",\n        \"investigation_object\": \"Объект №3\",\n        \"condition\": \"первом проколе\"\n      }\n    }\n  }\n]\n```",
  "graphs": [
    {
      "page_context": {
        "title": "Приложение №6. Изображения графиков ЯМР участков…"
      },
      "graph_id": 1,
      "header_data": {
        "full_text": "Образец № 1 к Заключению № 11366; Индекс кристалличности = 0.82548; Протонная плотность = 4.74334",
        "structured_metrics": {
          "sample_reference": "Образец № 1 к Заключению № 11366",
          "crystallinity_index": 0.82548,
          "proton_density": 4.74334
        }
      },
      "graph_statistics": {
        "axes": {
          "y_axis": {
            "label": "Интенсивность",
            "visible_min": null,
            "visible_max": null,
            "step_interval": null
          },
          "x_axis": {
            "label": "Время, мкс",
            "visible_min": null,
            "visible_max": null,
            "step_interval": null
          }
        },
        "y_metrics_max": {
          "red": null,
          "blue": null,
          "green": null
        },
        "visible_tabs": []
      },
      "log_panel_data": {
        "timestamp": "08:07:24",
        "raw_lines": [
          "Дата исследования - 24.06.2025",
          "Время релаксации короткой компоненты - 279.15117 мкс",
          "Время релаксации длинной компоненты - 911.89201 мкс",
          "Амплитуда короткой компоненты - 10.59124 a.u.",
          "Амплитуда длинной компоненты - 4.19664 a.u.",
          "Индекс кристалличности = 7.80354",
          "Протонная плотность = 4.74334"
        ],
        "structured_log_metrics": {
          "research_date": "24.06.2025",
          "relaxation_time_short_component_mks": 279.15117,
          "relaxation_time_long_component_mks": 911.89201,
          "amplitude_short_component_au": 10.59124,
          "amplitude_long_component_au": 4.19664,
          "calculated_crystallinity_index": 7.80354,
          "calculated_proton_density": 4.74334
        }
      },
      "status_bar_data": {
        "urtb": "3%",
        "adc": "100%",
        "base_offset": "100% 100%",
        "operation": "Чтение буфера A",
        "numeric_values": "135.0 0.7823 2032 2094"
      },
      "caption_data": {
        "illustration_number": "№12",
        "full_text": "Изображение одного из ЯМР участков исследуемых штрихов рукописной подписи от имени Шмульт Т.А. в предоставленном на исследование Объекте №3 при первом проколе.",
        "structured_details": {
          "object_type": "ЯМР",
          "source_item": "рукописной подписи",
          "investigation_object": "Объект №3",
          "condition": "первом проколе"
        }
      }
    },
    {
      "page_context": {
        "title": "Приложение №6. Изображения графиков ЯМР участков…"
      },
      "graph_id": 2,
      "header_data": {
        "full_text": "Образец № 1 к Заключению № 11366; Индекс кристалличности = 0.82911; Протонная плотность = 2.69566",
        "structured_metrics": {
          "sample_reference": "Образец № 1 к Заключению № 11366",
          "crystallinity_index": 0.82911,
          "proton_density": 2.69566
        }
      },
      "graph_statistics": {
        "axes": {
          "y_axis": {
            "label": "Интенсивность",
            "visible_min": null,
            "visible_max": null,
            "step_interval": null
          },
          "x_axis": {
            "label": "Время, мкс",
            "visible_min": null,
            "visible_max": null,
            "step_interval": null
          }
        },
        "y_metrics_max": {
          "red": null,
          "blue": null,
          "green": null
        },
        "visible_tabs": []
      },
      "log_panel_data": {
        "timestamp": "08:11:53",
        "raw_lines": [
          "Дата исследования - 24.06.2025",
          "Время релаксации короткой компоненты - 334.53589 мкс",
          "Время релаксации длинной компоненты - 892.44168 мкс",
          "Амплитуда короткой компоненты - 12.91935 a.u.",
          "Амплитуда длинной компоненты - 3.62729 a.u.",
          "Индекс кристалличности = 8.22458",
          "Протонная плотность = 2.69566"
        ],
        "structured_log_metrics": {
          "research_date": "24.06.2025",
          "relaxation_time_short_component_mks": 334.53589,
          "relaxation_time_long_component_mks": 892.44168,
          "amplitude_short_component_au": 12.91935,
          "amplitude_long_component_au": 3.62729,
          "calculated_crystallinity_index": 8.22458,
          "calculated_proton_density": 2.69566
        }
      },
      "status_bar_data": {
        "urtb": "3%",
        "adc": "100%",
        "base_offset": "100% 100%",
        "operation": "Чтение буфера A",
        "numeric_values": "135.0 0.7823 2032 2094"
      },
      "caption_data": {
        "illustration_number": "№13",
        "full_text": "Изображение одного из ЯМР участков исследуемых штрихов рукописной подписи нераспознанного лица №1 в предоставленном на исследование Объекте №3 при первом проколе.",
        "structured_details": {
          "object_type": "ЯМР",
          "source_item": "рукописной подписи",
          "investigation_object": "Объект №3",
          "condition": "первом проколе"
        }
      }
    }
  ],
  "model": "gpt-4o-2024-08-06",
  "usage": {
    "prompt_tokens": 2025,
    "completion_tokens": 1489,
    "total_tokens": 3514,
    "prompt_tokens_details": {
      "cached_tokens": 0,
      "audio_tokens": 0
    },
    "completion_tokens_details": {
      "reasoning_tokens": 0,
      "audio_tokens": 0,
      "accepted_prediction_tokens": 0,
      "rejected_prediction_tokens": 0
    }
  }
}