{
  "page": 54,
  "content": "```json\n[\n  {\n    \"page_context\": {\n      \"title\": \"Приложение №6. Изображения графиков ЯМР участков...\"\n    },\n    \"graph_id\": 1,\n    \"header_data\": {\n      \"full_text\": \"Образец № 3 к Заключению № 11366; Индекс кристалличности = 0.75336; Протонная плотность = 3.35176\",\n      \"structured_metrics\": {\n        \"sample_reference\": \"Образец № 3 к Заключению № 11366\",\n        \"crystallinity_index\": 0.75336,\n        \"proton_density\": 3.35176\n      }\n    },\n    \"graph_statistics\": {\n      \"axes\": {\n        \"y_axis\": { \"label\": \"Интенсивность\", \"visible_min\": null, \"visible_max\": null, \"step_interval\": null },\n        \"x_axis\": { \"label\": \"Время, мкс\", \"visible_min\": null, \"visible_max\": null, \"step_interval\": null }\n      },\n      \"y_metrics_max\": { \"red\": null, \"blue\": null, \"green\": null },\n      \"visible_tabs\": [\"NMR Signal\", \"Results Graph\", \"Code\"]\n    },\n    \"log_panel_data\": {\n      \"timestamp\": \"09:00:00\",\n      \"raw_lines\": [\n        \"Дата исследования - 19.07.2023\",\n        \"Время релаксации короткой компоненты - 347.90248 мкс\",\n        \"Время релаксации длинной компоненты - 5.75124 мкс\",\n        \"Амплитуда короткой компоненты - 234.1795 а.у.\",\n        \"Амплитуда длинной компоненты - 1698.3157 а.у.\",\n        \"Индекс кристалличности - 0.75336\",\n        \"Протонная плотность - 3.35176\"\n      ],\n      \"structured_log_metrics\": {\n        \"research_date\": \"19.07.2023\",\n        \"relaxation_time_short_component_mks\": 347.90248,\n        \"relaxation_time_long_component_mks\": 5.75124,\n        \"amplitude_short_component_au\": 234.1795,\n        \"amplitude_long_component_au\": 1698.3157,\n        \"calculated_crystallinity_index\": 0.75336,\n        \"calculated_proton_density\": 3.35176\n      }\n    },\n    \"status_bar_data\": {\n      \"urtb\": \"3%\",\n      \"adc\": \"0%\",\n      \"base_offset\": \"100% 100%\",\n      \"operation\": \"Чтение буфера A\",\n      \"numeric_values\": \"135.0 0.7823 2032 2094\"\n    },\n    \"caption_data\": {\n      \"illustration_number\": \"№106\",\n      \"full_text\": \"Изображение одного из ЯМР участков исследуемых штрихов рукописной подписи от имени Володько И.А. в предоставленном на исследование Объекте №7 при третьем проколе.\",\n      \"structured_details\": {\n        \"object_type\": \"ЯМР участок\",\n        \"source_item\": \"Володько И.А.\",\n        \"investigation_object\": \"Объект №7\",\n        \"condition\": \"при третьем проколе\"\n      }\n    }\n  },\n  {\n    \"graph_id\": 2,\n    \"header_data\": {\n      \"full_text\": \"Образец № 3 к Заключению № 11366; Индекс кристалличности = 0.79755; Протонная плотность = 4.31773\",\n      \"structured_metrics\": {\n        \"sample_reference\": \"Образец № 3 к Заключению № 11366\",\n        \"crystallinity_index\": 0.79755,\n        \"proton_density\": 4.31773\n      }\n    },\n    \"graph_statistics\": {\n      \"axes\": {\n        \"y_axis\": { \"label\": \"Интенсивность\", \"visible_min\": null, \"visible_max\": null, \"step_interval\": null },\n        \"x_axis\": { \"label\": \"Время, мкс\", \"visible_min\": null, \"visible_max\": null, \"step_interval\": null }\n      },\n      \"y_metrics_max\": { \"red\": null, \"blue\": null, \"green\": null },\n      \"visible_tabs\": [\"NMR Signal\", \"Results Graph\", \"Code\"]\n    },\n    \"log_panel_data\": {\n      \"timestamp\": \"09:14:46\",\n      \"raw_lines\": [\n        \"Дата исследования - 19.07.2023\",\n        \"Время релаксации короткой компоненты - 242.39068 мкс\",\n        \"Время релаксации длинной компоненты - 9.15436 мкс\",\n        \"Амплитуда короткой компоненты - 213.21 а.у.\",\n        \"Амплитуда длинной компоненты - 1815.655 а.у.\",\n        \"Индекс кристалличности - 0.79755\",\n        \"Протонная плотность - 4.31773\"\n      ],\n      \"structured_log_metrics\": {\n        \"research_date\": \"19.07.2023\",\n        \"relaxation_time_short_component_mks\": 242.39068,\n        \"relaxation_time_long_component_mks\": 9.15436,\n        \"amplitude_short_component_au\": 213.21,\n        \"amplitude_long_component_au\": 1815.655,\n        \"calculated_crystallinity_index\": 0.79755,\n        \"calculated_proton_density\": 4.31773\n      }\n    },\n    \"status_bar_data\": {\n      \"urtb\": \"3%\",\n      \"adc\": \"0%\",\n      \"base_offset\": \"100% 100%\",\n      \"operation\": \"Чтение буфера A\",\n      \"numeric_values\": \"135.0 0.7823 2032 2094\"\n    },\n    \"caption_data\": {\n      \"illustration_number\": \"№107\",\n      \"full_text\": \"Изображение одного из ЯМР участков исследуемых штрихов рукописной подписи от имени Тисленко Т.Б. в предоставленном на исследование Объекте №7 при третьем проколе.\",\n      \"structured_details\": {\n        \"object_type\": \"ЯМР участок\",\n        \"source_item\": \"Тисленко Т.Б.\",\n        \"investigation_object\": \"Объект №7\",\n        \"condition\": \"при третьем проколе\"\n      }\n    }\n  }\n]\n```",
  "graphs": [
    {
      "page_context": {
        "title": "Приложение №6. Изображения графиков ЯМР участков..."
      },
      "graph_id": 1,
      "header_data": {
        "full_text": "Образец № 3 к Заключению № 11366; Индекс кристалличности = 0.75336; Протонная плотность = 3.35176",
        "structured_metrics": {
          "sample_reference": "Образец № 3 к Заключению № 11366",
          "crystallinity_index": 0.75336,
          "proton_density": 3.35176
        }
      },
      "graph_statistics": {
        "axes": {
          "y_axis": {
            "label": "Интенсивность",
            "visible_min": null,
            "visible_max": null,
            "step_interval": null
          },
          "x_axis": {
            "label": "Время, мкс",
            "visible_min": null,
            "visible_max": null,
            "step_interval": null
          }
        },
        "y_metrics_max": {
          "red": null,
          "blue": null,
          "green": null
        },
        "visible_tabs": [
          "NMR Signal",
          "Results Graph",
          "Code"
        ]
      },
      "log_panel_data": {
        "timestamp": "09:00:00",
        "raw_lines": [
          "Дата исследования - 19.07.2023",
          "Время релаксации короткой компоненты - 347.90248 мкс",
          "Время релаксации длинной компоненты - 5.75124 мкс",
          "Амплитуда короткой компоненты - 234.1795 а.у.",
          "Амплитуда длинной компоненты - 1698.3157 а.у.",
          "Индекс кристалличности - 0.75336",
          "Протонная плотность - 3.35176"
        ],
        "structured_log_metrics": {
          "research_date": "19.07.2023",
          "relaxation_time_short_component_mks": 347.90248,
          "relaxation_time_long_component_mks": 5.75124,
          "amplitude_short_component_au": 234.1795,
          "amplitude_long_component_au": 1698.3157,
          "calculated_crystallinity_index": 0.75336,
          "calculated_proton_density": 3.35176
        }
      },
      "status_bar_data": {
        "urtb": "3%",
        "adc": "0%",
        "base_offset": "100% 100%",
        "operation": "Чтение буфера A",
        "numeric_values": "135.0 0.7823 2032 2094"
      },
      "caption_data": {
        "illustration_number": "№106",
        "full_text": "Изображение одного из ЯМР участков исследуемых штрихов рукописной подписи от имени Володько И.А. в предоставленном на исследование Объекте №7 при третьем проколе.",
        "structured_details": {
          "object_type": "ЯМР участок",
          "source_item": "Володько И.А.",
          "investigation_object": "Объект №7",
          "condition": "при третьем проколе"
        }
      }
    },
    {
      "graph_id": 2,
      "header_data": {
        "full_text": "Образец № 3 к Заключению № 11366; Индекс кристалличности = 0.79755; Протонная плотность = 4.31773",
        "structured_metrics": {
          "sample_reference": "Образец № 3 к Заключению № 11366",
          "crystallinity_index": 0.79755,
          "proton_density": 4.31773
        }
      },
      "graph_statistics": {
        "axes": {
          "y_axis": {
            "label": "Интенсивность",
            "visible_min": null,
            "visible_max": null,
            "step_interval": null
          },
          "x_axis": {
            "label": "Время, мкс",
            "visible_min": null,
            "visible_max": null,
            "step_interval": null
          }
        },
        "y_metrics_max": {
          "red": null,
          "blue": null,
          "green": null
        },
        "visible_tabs": [
          "NMR Signal",
          "Results Graph",
          "Code"
        ]
      },
      "log_panel_data": {
        "timestamp": "09:14:46",
        "raw_lines": [
          "Дата исследования - 19.07.2023",
          "Время релаксации короткой компоненты - 242.39068 мкс",
          "Время релаксации длинной компоненты - 9.15436 мкс",
          "Амплитуда короткой компоненты - 213.21 а.у.",
          "Амплитуда длинной компоненты - 1815.655 а.у.",
          "Индекс кристалличности - 0.79755",
          "Протонная плотность - 4.31773"
        ],
        "structured_log_metrics": {
          "research_date": "19.07.2023",
          "relaxation_time_short_component_mks": 242.39068,
          "relaxation_time_long_component_mks": 9.15436,
          "amplitude_short_component_au": 213.21,
          "amplitude_long_component_au": 1815.655,
          "calculated_crystallinity_index": 0.79755,
          "calculated_proton_density": 4.31773
        }
      },
      "status_bar_data": {
        "urtb": "3%",
        "adc": "0%",
        "base_offset": "100% 100%",
        "operation": "Чтение буфера A",
        "numeric_values": "135.0 0.7823 2032 2094"
      },
      "caption_data": {
        "illustration_number": "№107",
        "full_text": "Изображение одного из ЯМР участков исследуемых штрихов рукописной подписи от имени Тисленко Т.Б. в предоставленном на исследование Объекте №7 при третьем проколе.",
        "structured_details": {
          "object_type": "ЯМР участок",
          "source_item": "Тисленко Т.Б.",
          "investigation_object": "Объект №7",
          "condition": "при третьем проколе"
        }
      }
    }
  ],
  "model": "gpt-4o-2024-08-06",
  "usage": {
    "prompt_tokens": 2025,
    "completion_tokens": 1453,
    "total_tokens": 3478,
    "prompt_tokens_details": {
      "cached_tokens": 0,
      "audio_tokens": 0
    },
    "completion_tokens_details": {
      "reasoning_tokens": 0,
      "audio_tokens": 0,
      "accepted_prediction_tokens": 0,
      "rejected_prediction_tokens": 0
    }
  }
}