{
  "page": 76,
  "content": "```json\n[\n  {\n    \"page_context\": {\n      \"title\": \"Приложение №6. Изображения графиков ЯМР участков…\"\n    },\n    \"graph_id\": 1,\n    \"header_data\": {\n      \"full_text\": \"Образец № 3 к Заключению № 11366; Индекс кристалличности = 0.76030; Протонная плотность = 4.57546\",\n      \"structured_metrics\": {\n        \"sample_reference\": \"№ 3 к Заключению № 11366\",\n        \"crystallinity_index\": 0.76030,\n        \"proton_density\": 4.57546\n      }\n    },\n    \"graph_statistics\": {\n      \"axes\": {\n        \"y_axis\": {\n          \"label\": \"a.u.\",\n          \"visible_min\": null,\n          \"visible_max\": null,\n          \"step_interval\": null\n        },\n        \"x_axis\": {\n          \"label\": \"Время, мкс\",\n          \"visible_min\": null,\n          \"visible_max\": null,\n          \"step_interval\": null\n        }\n      },\n      \"y_metrics_max\": {\n        \"red\": null,\n        \"blue\": null,\n        \"green\": null\n      },\n      \"visible_tabs\": [\"NMR Signal\", \"Results Graph\", \"Code\"]\n    },\n    \"log_panel_data\": {\n      \"timestamp\": \"12:06:26\",\n      \"raw_lines\": [\n        \"Дата исследования - 19.07.2023\",\n        \"Время релаксации короткой компоненты - 330.96126 мкс\",\n        \"Время релаксации длинной компоненты - 1525.53 мкс\",\n        \"Амплитуда короткой компоненты - 45.1334 a.u.\",\n        \"Амплитуда длинной компоненты - 76.48219 a.u.\",\n        \"Протонная плотность - 4.57546\"\n      ],\n      \"structured_log_metrics\": {\n        \"research_date\": \"19.07.2023\",\n        \"relaxation_time_short_component_mks\": 330.96126,\n        \"relaxation_time_long_component_mks\": 1525.53,\n        \"amplitude_short_component_au\": 45.1334,\n        \"amplitude_long_component_au\": 76.48219,\n        \"calculated_crystallinity_index\": 0.76030,\n        \"calculated_proton_density\": 4.57546\n      }\n    },\n    \"status_bar_data\": {\n      \"urtb\": \"3%\",\n      \"adc\": \"0%\",\n      \"base_offset\": \"100% 100%\",\n      \"operation\": \"Чтение буфера А\",\n      \"numeric_values\": \"130.5 0.7823 2032 2094\"\n    },\n    \"caption_data\": {\n      \"illustration_number\": \"№150\",\n      \"full_text\": \"Иллюстрация №150. Изображение одного из ЯМР участков исследуемых штрихов оттиска круглой мастичной печати ООО «Агро-Индустриальная Корпорация «Волго-Дон» в предоставленном на исследование Объекте №9 при третьем проколе.\",\n      \"structured_details\": {\n        \"object_type\": \"ЯМР участок\",\n        \"source_item\": \"штрих оттиска круглой мастичной печати\",\n        \"investigation_object\": \"Объект №9\",\n        \"condition\": \"при третьем проколе\"\n      }\n    }\n  },\n  {\n    \"graph_id\": 2,\n    \"header_data\": {\n      \"full_text\": \"Образец № 3 к Заключению № 11366; Индекс кристалличности = 0.80365; Протонная плотность = 3.28896\",\n      \"structured_metrics\": {\n        \"sample_reference\": \"№ 3 к Заключению № 11366\",\n        \"crystallinity_index\": 0.80365,\n        \"proton_density\": 3.28896\n      }\n    },\n    \"graph_statistics\": {\n      \"axes\": {\n        \"y_axis\": {\n          \"label\": \"a.u.\",\n          \"visible_min\": null,\n          \"visible_max\": null,\n          \"step_interval\": null\n        },\n        \"x_axis\": {\n          \"label\": \"Время, мкс\",\n          \"visible_min\": null,\n          \"visible_max\": null,\n          \"step_interval\": null\n        }\n      },\n      \"y_metrics_max\": {\n        \"red\": null,\n        \"blue\": null,\n        \"green\": null\n      },\n      \"visible_tabs\": [\"NMR Signal\", \"Results Graph\", \"Code\"]\n    },\n    \"log_panel_data\": {\n      \"timestamp\": \"12:11:22\",\n      \"raw_lines\": [\n        \"Дата исследования - 19.07.2025\",\n        \"Время релаксации короткой компоненты - 132.15447 мкс\",\n        \"Время релаксации длинной компоненты - 1337.7356 мкс\",\n        \"Амплитуда короткой компоненты - 22.39699 a.u.\",\n        \"Амплитуда длинной компоненты - 47.10211 a.u.\",\n        \"Протонная плотность - 3.28896\"\n      ],\n      \"structured_log_metrics\": {\n        \"research_date\": \"19.07.2025\",\n        \"relaxation_time_short_component_mks\": 132.15447,\n        \"relaxation_time_long_component_mks\": 1337.7356,\n        \"amplitude_short_component_au\": 22.39699,\n        \"amplitude_long_component_au\": 47.10211,\n        \"calculated_crystallinity_index\": 0.80365,\n        \"calculated_proton_density\": 3.28896\n      }\n    },\n    \"status_bar_data\": {\n      \"urtb\": \"3%\",\n      \"adc\": \"0%\",\n      \"base_offset\": \"100% 100%\",\n      \"operation\": \"Чтение буфера А\",\n      \"numeric_values\": \"130.5 0.7823 2032 2094\"\n    },\n    \"caption_data\": {\n      \"illustration_number\": \"№151\",\n      \"full_text\": \"Иллюстрация №151. Изображение одного из ЯМР участков исследуемых штрихов оттиска круглой мастичной печати ПАО «Московский Индустриальный банк» в предоставленном на исследование Объекте №10 при третьем проколе.\",\n      \"structured_details\": {\n        \"object_type\": \"ЯМР участок\",\n        \"source_item\": \"штрих оттиска круглой мастичной печати\",\n        \"investigation_object\": \"Объект №10\",\n        \"condition\": \"при третьем проколе\"\n      }\n    }\n  }\n]\n```",
  "graphs": [
    {
      "page_context": {
        "title": "Приложение №6. Изображения графиков ЯМР участков…"
      },
      "graph_id": 1,
      "header_data": {
        "full_text": "Образец № 3 к Заключению № 11366; Индекс кристалличности = 0.76030; Протонная плотность = 4.57546",
        "structured_metrics": {
          "sample_reference": "№ 3 к Заключению № 11366",
          "crystallinity_index": 0.7603,
          "proton_density": 4.57546
        }
      },
      "graph_statistics": {
        "axes": {
          "y_axis": {
            "label": "a.u.",
            "visible_min": null,
            "visible_max": null,
            "step_interval": null
          },
          "x_axis": {
            "label": "Время, мкс",
            "visible_min": null,
            "visible_max": null,
            "step_interval": null
          }
        },
        "y_metrics_max": {
          "red": null,
          "blue": null,
          "green": null
        },
        "visible_tabs": [
          "NMR Signal",
          "Results Graph",
          "Code"
        ]
      },
      "log_panel_data": {
        "timestamp": "12:06:26",
        "raw_lines": [
          "Дата исследования - 19.07.2023",
          "Время релаксации короткой компоненты - 330.96126 мкс",
          "Время релаксации длинной компоненты - 1525.53 мкс",
          "Амплитуда короткой компоненты - 45.1334 a.u.",
          "Амплитуда длинной компоненты - 76.48219 a.u.",
          "Протонная плотность - 4.57546"
        ],
        "structured_log_metrics": {
          "research_date": "19.07.2023",
          "relaxation_time_short_component_mks": 330.96126,
          "relaxation_time_long_component_mks": 1525.53,
          "amplitude_short_component_au": 45.1334,
          "amplitude_long_component_au": 76.48219,
          "calculated_crystallinity_index": 0.7603,
          "calculated_proton_density": 4.57546
        }
      },
      "status_bar_data": {
        "urtb": "3%",
        "adc": "0%",
        "base_offset": "100% 100%",
        "operation": "Чтение буфера А",
        "numeric_values": "130.5 0.7823 2032 2094"
      },
      "caption_data": {
        "illustration_number": "№150",
        "full_text": "Иллюстрация №150. Изображение одного из ЯМР участков исследуемых штрихов оттиска круглой мастичной печати ООО «Агро-Индустриальная Корпорация «Волго-Дон» в предоставленном на исследование Объекте №9 при третьем проколе.",
        "structured_details": {
          "object_type": "ЯМР участок",
          "source_item": "штрих оттиска круглой мастичной печати",
          "investigation_object": "Объект №9",
          "condition": "при третьем проколе"
        }
      }
    },
    {
      "graph_id": 2,
      "header_data": {
        "full_text": "Образец № 3 к Заключению № 11366; Индекс кристалличности = 0.80365; Протонная плотность = 3.28896",
        "structured_metrics": {
          "sample_reference": "№ 3 к Заключению № 11366",
          "crystallinity_index": 0.80365,
          "proton_density": 3.28896
        }
      },
      "graph_statistics": {
        "axes": {
          "y_axis": {
            "label": "a.u.",
            "visible_min": null,
            "visible_max": null,
            "step_interval": null
          },
          "x_axis": {
            "label": "Время, мкс",
            "visible_min": null,
            "visible_max": null,
            "step_interval": null
          }
        },
        "y_metrics_max": {
          "red": null,
          "blue": null,
          "green": null
        },
        "visible_tabs": [
          "NMR Signal",
          "Results Graph",
          "Code"
        ]
      },
      "log_panel_data": {
        "timestamp": "12:11:22",
        "raw_lines": [
          "Дата исследования - 19.07.2025",
          "Время релаксации короткой компоненты - 132.15447 мкс",
          "Время релаксации длинной компоненты - 1337.7356 мкс",
          "Амплитуда короткой компоненты - 22.39699 a.u.",
          "Амплитуда длинной компоненты - 47.10211 a.u.",
          "Протонная плотность - 3.28896"
        ],
        "structured_log_metrics": {
          "research_date": "19.07.2025",
          "relaxation_time_short_component_mks": 132.15447,
          "relaxation_time_long_component_mks": 1337.7356,
          "amplitude_short_component_au": 22.39699,
          "amplitude_long_component_au": 47.10211,
          "calculated_crystallinity_index": 0.80365,
          "calculated_proton_density": 3.28896
        }
      },
      "status_bar_data": {
        "urtb": "3%",
        "adc": "0%",
        "base_offset": "100% 100%",
        "operation": "Чтение буфера А",
        "numeric_values": "130.5 0.7823 2032 2094"
      },
      "caption_data": {
        "illustration_number": "№151",
        "full_text": "Иллюстрация №151. Изображение одного из ЯМР участков исследуемых штрихов оттиска круглой мастичной печати ПАО «Московский Индустриальный банк» в предоставленном на исследование Объекте №10 при третьем проколе.",
        "structured_details": {
          "object_type": "ЯМР участок",
          "source_item": "штрих оттиска круглой мастичной печати",
          "investigation_object": "Объект №10",
          "condition": "при третьем проколе"
        }
      }
    }
  ],
  "model": "gpt-4o-2024-08-06",
  "usage": {
    "prompt_tokens": 2025,
    "completion_tokens": 1492,
    "total_tokens": 3517,
    "prompt_tokens_details": {
      "cached_tokens": 0,
      "audio_tokens": 0
    },
    "completion_tokens_details": {
      "reasoning_tokens": 0,
      "audio_tokens": 0,
      "accepted_prediction_tokens": 0,
      "rejected_prediction_tokens": 0
    }
  }
}