{
  "page": 70,
  "content": "```json\n[\n  {\n    \"page_context\": {\n      \"title\": \"Приложение №6. Изображения графиков ЯМР участков\"\n    },\n    \"graph_id\": 1,\n    \"header_data\": {\n      \"full_text\": \"Образец № 3 к Заключению № 11366; Индекс кристалличности = 0.78540; Протонная плотность = 3.18516\",\n      \"structured_metrics\": {\n        \"sample_reference\": \"Образец № 3 к Заключению № 11366\",\n        \"crystallinity_index\": 0.78540,\n        \"proton_density\": 3.18516\n      }\n    },\n    \"graph_statistics\": {\n      \"axes\": {\n        \"y_axis\": {\n          \"label\": \"Интенсивность, %\",\n          \"visible_min\": null,\n          \"visible_max\": null,\n          \"step_interval\": null\n        },\n        \"x_axis\": {\n          \"label\": \"Время, мкс\",\n          \"visible_min\": null,\n          \"visible_max\": null,\n          \"step_interval\": null\n        }\n      },\n      \"y_metrics_max\": {\n        \"red\": null,\n        \"blue\": null,\n        \"green\": null\n      },\n      \"visible_tabs\": []\n    },\n    \"log_panel_data\": {\n      \"timestamp\": \"11:18:55\",\n      \"raw_lines\": [\n        \"Дата исследования - 19.07.2025\",\n        \"Время релаксации короткой компоненты - 297.77908 mks\",\n        \"Время релаксации длинной компоненты - 18.92702 mks\",\n        \"Амплитуда короткой компоненты - 12.1728 a.u.\",\n        \"Амплитуда длинной компоненты - 1 a.u.\",\n        \"Индекс кристалличности - 0.78540\",\n        \"Протонная плотность - 3.18516\"\n      ],\n      \"structured_log_metrics\": {\n        \"research_date\": \"19.07.2025\",\n        \"relaxation_time_short_component_mks\": 297.77908,\n        \"relaxation_time_long_component_mks\": 18.92702,\n        \"amplitude_short_component_au\": 12.1728,\n        \"amplitude_long_component_au\": 1.0,\n        \"calculated_crystallinity_index\": 0.78540,\n        \"calculated_proton_density\": 3.18516\n      }\n    },\n    \"status_bar_data\": {\n      \"urtb\": \"3%\",\n      \"adc\": \"0%\",\n      \"base_offset\": \"100% 100%\",\n      \"operation\": \"Чтение буфера A\",\n      \"numeric_values\": \"135.0 0.7823 2032 2094\"\n    },\n    \"caption_data\": {\n      \"illustration_number\": \"№138\",\n      \"full_text\": \"Иллюстрация №138. Изображение одного из ЯМР участков исследуемых штрихов оттиска круглой мастичной печати ООО «Ростовская нива» в предоставленном на исследование Объекте №3 при третьем проколе.\",\n      \"structured_details\": {\n        \"object_type\": \"оттиск круглой мастичной печати\",\n        \"source_item\": \"ООО «Ростовская нива»\",\n        \"investigation_object\": \"Объект №3\",\n        \"condition\": \"при третьем проколе\"\n      }\n    }\n  },\n  {\n    \"graph_id\": 2,\n    \"header_data\": {\n      \"full_text\": \"Образец № 3 к Заключению № 11366; Индекс кристалличности = 0.80209; Протонная плотность = 4.01404\",\n      \"structured_metrics\": {\n        \"sample_reference\": \"Образец № 3 к Заключению № 11366\",\n        \"crystallinity_index\": 0.80209,\n        \"proton_density\": 4.01404\n      }\n    },\n    \"graph_statistics\": {\n      \"axes\": {\n        \"y_axis\": {\n          \"label\": \"Интенсивность, %\",\n          \"visible_min\": null,\n          \"visible_max\": null,\n          \"step_interval\": null\n        },\n        \"x_axis\": {\n          \"label\": \"Время, мкс\",\n          \"visible_min\": null,\n          \"visible_max\": null,\n          \"step_interval\": null\n        }\n      },\n      \"y_metrics_max\": {\n        \"red\": null,\n        \"blue\": null,\n        \"green\": null\n      },\n      \"visible_tabs\": []\n    },\n    \"log_panel_data\": {\n      \"timestamp\": \"11:23:07\",\n      \"raw_lines\": [\n        \"Дата исследования - 19.07.2025\",\n        \"Время релаксации короткой компоненты - 186.11526 mks\",\n        \"Время релаксации длинной компоненты - 36.96068 mks\",\n        \"Амплитуда короткой компоненты - 8.945 a.u.\",\n        \"Амплитуда длинной компоненты - 1.105 a.u.\",\n        \"Индекс кристалличности - 0.80209\",\n        \"Протонная плотность - 4.01404\"\n      ],\n      \"structured_log_metrics\": {\n        \"research_date\": \"19.07.2025\",\n        \"relaxation_time_short_component_mks\": 186.11526,\n        \"relaxation_time_long_component_mks\": 36.96068,\n        \"amplitude_short_component_au\": 8.945,\n        \"amplitude_long_component_au\": 1.105,\n        \"calculated_crystallinity_index\": 0.80209,\n        \"calculated_proton_density\": 4.01404\n      }\n    },\n    \"status_bar_data\": {\n      \"urtb\": \"3%\",\n      \"adc\": \"0%\",\n      \"base_offset\": \"100% 100%\",\n      \"operation\": \"Чтение буфера A\",\n      \"numeric_values\": \"135.0 0.7823 2032 2094\"\n    },\n    \"caption_data\": {\n      \"illustration_number\": \"№139\",\n      \"full_text\": \"Иллюстрация №139. Изображение одного из ЯМР участков исследуемых штрихов оттиска круглой мастичной печати ПАО «Московский Индустриальный банк» в предоставленном на исследование Объекте №4 при третьем проколе.\",\n      \"structured_details\": {\n        \"object_type\": \"оттиск круглой мастичной печати\",\n        \"source_item\": \"ПАО «Московский Индустриальный банк»\",\n        \"investigation_object\": \"Объект №4\",\n        \"condition\": \"при третьем проколе\"\n      }\n    }\n  }\n]\n```",
  "graphs": [
    {
      "page_context": {
        "title": "Приложение №6. Изображения графиков ЯМР участков"
      },
      "graph_id": 1,
      "header_data": {
        "full_text": "Образец № 3 к Заключению № 11366; Индекс кристалличности = 0.78540; Протонная плотность = 3.18516",
        "structured_metrics": {
          "sample_reference": "Образец № 3 к Заключению № 11366",
          "crystallinity_index": 0.7854,
          "proton_density": 3.18516
        }
      },
      "graph_statistics": {
        "axes": {
          "y_axis": {
            "label": "Интенсивность, %",
            "visible_min": null,
            "visible_max": null,
            "step_interval": null
          },
          "x_axis": {
            "label": "Время, мкс",
            "visible_min": null,
            "visible_max": null,
            "step_interval": null
          }
        },
        "y_metrics_max": {
          "red": null,
          "blue": null,
          "green": null
        },
        "visible_tabs": []
      },
      "log_panel_data": {
        "timestamp": "11:18:55",
        "raw_lines": [
          "Дата исследования - 19.07.2025",
          "Время релаксации короткой компоненты - 297.77908 mks",
          "Время релаксации длинной компоненты - 18.92702 mks",
          "Амплитуда короткой компоненты - 12.1728 a.u.",
          "Амплитуда длинной компоненты - 1 a.u.",
          "Индекс кристалличности - 0.78540",
          "Протонная плотность - 3.18516"
        ],
        "structured_log_metrics": {
          "research_date": "19.07.2025",
          "relaxation_time_short_component_mks": 297.77908,
          "relaxation_time_long_component_mks": 18.92702,
          "amplitude_short_component_au": 12.1728,
          "amplitude_long_component_au": 1.0,
          "calculated_crystallinity_index": 0.7854,
          "calculated_proton_density": 3.18516
        }
      },
      "status_bar_data": {
        "urtb": "3%",
        "adc": "0%",
        "base_offset": "100% 100%",
        "operation": "Чтение буфера A",
        "numeric_values": "135.0 0.7823 2032 2094"
      },
      "caption_data": {
        "illustration_number": "№138",
        "full_text": "Иллюстрация №138. Изображение одного из ЯМР участков исследуемых штрихов оттиска круглой мастичной печати ООО «Ростовская нива» в предоставленном на исследование Объекте №3 при третьем проколе.",
        "structured_details": {
          "object_type": "оттиск круглой мастичной печати",
          "source_item": "ООО «Ростовская нива»",
          "investigation_object": "Объект №3",
          "condition": "при третьем проколе"
        }
      }
    },
    {
      "graph_id": 2,
      "header_data": {
        "full_text": "Образец № 3 к Заключению № 11366; Индекс кристалличности = 0.80209; Протонная плотность = 4.01404",
        "structured_metrics": {
          "sample_reference": "Образец № 3 к Заключению № 11366",
          "crystallinity_index": 0.80209,
          "proton_density": 4.01404
        }
      },
      "graph_statistics": {
        "axes": {
          "y_axis": {
            "label": "Интенсивность, %",
            "visible_min": null,
            "visible_max": null,
            "step_interval": null
          },
          "x_axis": {
            "label": "Время, мкс",
            "visible_min": null,
            "visible_max": null,
            "step_interval": null
          }
        },
        "y_metrics_max": {
          "red": null,
          "blue": null,
          "green": null
        },
        "visible_tabs": []
      },
      "log_panel_data": {
        "timestamp": "11:23:07",
        "raw_lines": [
          "Дата исследования - 19.07.2025",
          "Время релаксации короткой компоненты - 186.11526 mks",
          "Время релаксации длинной компоненты - 36.96068 mks",
          "Амплитуда короткой компоненты - 8.945 a.u.",
          "Амплитуда длинной компоненты - 1.105 a.u.",
          "Индекс кристалличности - 0.80209",
          "Протонная плотность - 4.01404"
        ],
        "structured_log_metrics": {
          "research_date": "19.07.2025",
          "relaxation_time_short_component_mks": 186.11526,
          "relaxation_time_long_component_mks": 36.96068,
          "amplitude_short_component_au": 8.945,
          "amplitude_long_component_au": 1.105,
          "calculated_crystallinity_index": 0.80209,
          "calculated_proton_density": 4.01404
        }
      },
      "status_bar_data": {
        "urtb": "3%",
        "adc": "0%",
        "base_offset": "100% 100%",
        "operation": "Чтение буфера A",
        "numeric_values": "135.0 0.7823 2032 2094"
      },
      "caption_data": {
        "illustration_number": "№139",
        "full_text": "Иллюстрация №139. Изображение одного из ЯМР участков исследуемых штрихов оттиска круглой мастичной печати ПАО «Московский Индустриальный банк» в предоставленном на исследование Объекте №4 при третьем проколе.",
        "structured_details": {
          "object_type": "оттиск круглой мастичной печати",
          "source_item": "ПАО «Московский Индустриальный банк»",
          "investigation_object": "Объект №4",
          "condition": "при третьем проколе"
        }
      }
    }
  ],
  "model": "gpt-4o-2024-08-06",
  "usage": {
    "prompt_tokens": 2025,
    "completion_tokens": 1498,
    "total_tokens": 3523,
    "prompt_tokens_details": {
      "cached_tokens": 0,
      "audio_tokens": 0
    },
    "completion_tokens_details": {
      "reasoning_tokens": 0,
      "audio_tokens": 0,
      "accepted_prediction_tokens": 0,
      "rejected_prediction_tokens": 0
    }
  }
}