{
  "page": 11,
  "content": "```json\n[\n  {\n    \"page_context\": {\n      \"title\": \"Приложение №6. Изображения графиков ЯМР участков…\"\n    },\n    \"graph_id\": 1,\n    \"header_data\": {\n      \"full_text\": \"Образец № 1 к Заключению № 11366; Индекс кристалличности = 0.80947. Протонная плотность = 4.46319\",\n      \"structured_metrics\": {\n        \"sample_reference\": \"Образец № 1 к Заключению № 11366\",\n        \"crystallinity_index\": 0.80947,\n        \"proton_density\": 4.46319\n      }\n    },\n    \"graph_statistics\": {\n      \"axes\": {\n        \"y_axis\": {\n          \"label\": \" \",\n          \"visible_min\": 0,\n          \"visible_max\": 100,\n          \"step_interval\": 10\n        },\n        \"x_axis\": {\n          \"label\": \"Время, мкс\",\n          \"visible_min\": 0,\n          \"visible_max\": 115,\n          \"step_interval\": 5\n        }\n      },\n      \"y_metrics_max\": {\n        \"red\": null,\n        \"blue\": null,\n        \"green\": null\n      },\n      \"visible_tabs\": [\n        \"NMR Signal\",\n        \"Results Graph\",\n        \"Code\"\n      ]\n    },\n    \"log_panel_data\": {\n      \"timestamp\": \"09:45:37\",\n      \"raw_lines\": [\n        \"Дата исследования - 24.06.2023\",\n        \"Время релаксации короткой компоненты = 343.91897 мкс\",\n        \"Время релаксации длинной компоненты = 1964.5515 мкс\",\n        \"Амплитуда короткой компоненты = 1.19983 а.е.\",\n        \"Амплитуда длинной компоненты = 4.46319 а.е.\",\n        \"Индекс кристалличности = 0.80947\",\n        \"Протонная плотность = 4.46319\"\n      ],\n      \"structured_log_metrics\": {\n        \"research_date\": \"24.06.2023\",\n        \"relaxation_time_short_component_mks\": 343.91897,\n        \"relaxation_time_long_component_mks\": 1964.5515,\n        \"amplitude_short_component_au\": 1.19983,\n        \"amplitude_long_component_au\": 4.46319,\n        \"calculated_crystallinity_index\": 0.80947,\n        \"calculated_proton_density\": 4.46319\n      }\n    },\n    \"status_bar_data\": {\n      \"urtb\": \"3%\",\n      \"adc\": \"0%\",\n      \"base_offset\": \"100% 100%\",\n      \"operation\": \"Чтение буфера A\",\n      \"numeric_values\": \"135.0 07823 2032 2094\"\n    },\n    \"caption_data\": {\n      \"illustration_number\": \"№20\",\n      \"full_text\": \"Иллюстрация №20. Изображение одного из ЯМР участков исследуемых штрихов рукописной подписи от имени Губашева С.С. в предоставленном на исследование Объекте №5 при первом проколе.\",\n      \"structured_details\": {\n        \"object_type\": \"ЯМР участок\",\n        \"source_item\": \"рукописной подписи\",\n        \"investigation_object\": \"Объект №5\",\n        \"condition\": \"при первом проколе\"\n      }\n    }\n  },\n  {\n    \"graph_id\": 2,\n    \"header_data\": {\n      \"full_text\": \"Образец № 1 к Заключению № 11366; Индекс кристалличности = 0.79663. Протонная плотность = 2.95562\",\n      \"structured_metrics\": {\n        \"sample_reference\": \"Образец № 1 к Заключению № 11366\",\n        \"crystallinity_index\": 0.79663,\n        \"proton_density\": 2.95562\n      }\n    },\n    \"graph_statistics\": {\n      \"axes\": {\n        \"y_axis\": {\n          \"label\": \" \",\n          \"visible_min\": 0,\n          \"visible_max\": 100,\n          \"step_interval\": 10\n        },\n        \"x_axis\": {\n          \"label\": \"Время, мкс\",\n          \"visible_min\": 0,\n          \"visible_max\": 115,\n          \"step_interval\": 5\n        }\n      },\n      \"y_metrics_max\": {\n        \"red\": null,\n        \"blue\": null,\n        \"green\": null\n      },\n      \"visible_tabs\": [\n        \"NMR Signal\",\n        \"Results Graph\",\n        \"Code\"\n      ]\n    },\n    \"log_panel_data\": {\n      \"timestamp\": \"09:41:05\",\n      \"raw_lines\": [\n        \"Дата исследования - 24.06.2023\",\n        \"Время релаксации короткой компоненты = 200.52531 мкс\",\n        \"Время релаксации длинной компоненты = 2060.9709 мкс\",\n        \"Амплитуда короткой компоненты = 0.91372 а.е.\",\n        \"Амплитуда длинной компоненты = 2.95562 а.е.\",\n        \"Индекс кристалличности = 0.79663\",\n        \"Протонная плотность = 2.95562\"\n      ],\n      \"structured_log_metrics\": {\n        \"research_date\": \"24.06.2023\",\n        \"relaxation_time_short_component_mks\": 200.52531,\n        \"relaxation_time_long_component_mks\": 2060.9709,\n        \"amplitude_short_component_au\": 0.91372,\n        \"amplitude_long_component_au\": 2.95562,\n        \"calculated_crystallinity_index\": 0.79663,\n        \"calculated_proton_density\": 2.95562\n      }\n    },\n    \"status_bar_data\": {\n      \"urtb\": \"3%\",\n      \"adc\": \"0%\",\n      \"base_offset\": \"100% 100%\",\n      \"operation\": \"Чтение буфера A\",\n      \"numeric_values\": \"135.0 07823 2032 2094\"\n    },\n    \"caption_data\": {\n      \"illustration_number\": \"№21\",\n      \"full_text\": \"Иллюстрация №21. Изображение одного из ЯМР участков исследуемых штрихов рукописной подписи от имени Тисленко Т.Б. в предоставленном на исследование Объекте №5 при первом проколе.\",\n      \"structured_details\": {\n        \"object_type\": \"ЯМР участок\",\n        \"source_item\": \"рукописной подписи\",\n        \"investigation_object\": \"Объект №5\",\n        \"condition\": \"при первом проколе\"\n      }\n    }\n  }\n]\n```",
  "graphs": [
    {
      "page_context": {
        "title": "Приложение №6. Изображения графиков ЯМР участков…"
      },
      "graph_id": 1,
      "header_data": {
        "full_text": "Образец № 1 к Заключению № 11366; Индекс кристалличности = 0.80947. Протонная плотность = 4.46319",
        "structured_metrics": {
          "sample_reference": "Образец № 1 к Заключению № 11366",
          "crystallinity_index": 0.80947,
          "proton_density": 4.46319
        }
      },
      "graph_statistics": {
        "axes": {
          "y_axis": {
            "label": " ",
            "visible_min": 0,
            "visible_max": 100,
            "step_interval": 10
          },
          "x_axis": {
            "label": "Время, мкс",
            "visible_min": 0,
            "visible_max": 115,
            "step_interval": 5
          }
        },
        "y_metrics_max": {
          "red": null,
          "blue": null,
          "green": null
        },
        "visible_tabs": [
          "NMR Signal",
          "Results Graph",
          "Code"
        ]
      },
      "log_panel_data": {
        "timestamp": "09:45:37",
        "raw_lines": [
          "Дата исследования - 24.06.2023",
          "Время релаксации короткой компоненты = 343.91897 мкс",
          "Время релаксации длинной компоненты = 1964.5515 мкс",
          "Амплитуда короткой компоненты = 1.19983 а.е.",
          "Амплитуда длинной компоненты = 4.46319 а.е.",
          "Индекс кристалличности = 0.80947",
          "Протонная плотность = 4.46319"
        ],
        "structured_log_metrics": {
          "research_date": "24.06.2023",
          "relaxation_time_short_component_mks": 343.91897,
          "relaxation_time_long_component_mks": 1964.5515,
          "amplitude_short_component_au": 1.19983,
          "amplitude_long_component_au": 4.46319,
          "calculated_crystallinity_index": 0.80947,
          "calculated_proton_density": 4.46319
        }
      },
      "status_bar_data": {
        "urtb": "3%",
        "adc": "0%",
        "base_offset": "100% 100%",
        "operation": "Чтение буфера A",
        "numeric_values": "135.0 07823 2032 2094"
      },
      "caption_data": {
        "illustration_number": "№20",
        "full_text": "Иллюстрация №20. Изображение одного из ЯМР участков исследуемых штрихов рукописной подписи от имени Губашева С.С. в предоставленном на исследование Объекте №5 при первом проколе.",
        "structured_details": {
          "object_type": "ЯМР участок",
          "source_item": "рукописной подписи",
          "investigation_object": "Объект №5",
          "condition": "при первом проколе"
        }
      }
    },
    {
      "graph_id": 2,
      "header_data": {
        "full_text": "Образец № 1 к Заключению № 11366; Индекс кристалличности = 0.79663. Протонная плотность = 2.95562",
        "structured_metrics": {
          "sample_reference": "Образец № 1 к Заключению № 11366",
          "crystallinity_index": 0.79663,
          "proton_density": 2.95562
        }
      },
      "graph_statistics": {
        "axes": {
          "y_axis": {
            "label": " ",
            "visible_min": 0,
            "visible_max": 100,
            "step_interval": 10
          },
          "x_axis": {
            "label": "Время, мкс",
            "visible_min": 0,
            "visible_max": 115,
            "step_interval": 5
          }
        },
        "y_metrics_max": {
          "red": null,
          "blue": null,
          "green": null
        },
        "visible_tabs": [
          "NMR Signal",
          "Results Graph",
          "Code"
        ]
      },
      "log_panel_data": {
        "timestamp": "09:41:05",
        "raw_lines": [
          "Дата исследования - 24.06.2023",
          "Время релаксации короткой компоненты = 200.52531 мкс",
          "Время релаксации длинной компоненты = 2060.9709 мкс",
          "Амплитуда короткой компоненты = 0.91372 а.е.",
          "Амплитуда длинной компоненты = 2.95562 а.е.",
          "Индекс кристалличности = 0.79663",
          "Протонная плотность = 2.95562"
        ],
        "structured_log_metrics": {
          "research_date": "24.06.2023",
          "relaxation_time_short_component_mks": 200.52531,
          "relaxation_time_long_component_mks": 2060.9709,
          "amplitude_short_component_au": 0.91372,
          "amplitude_long_component_au": 2.95562,
          "calculated_crystallinity_index": 0.79663,
          "calculated_proton_density": 2.95562
        }
      },
      "status_bar_data": {
        "urtb": "3%",
        "adc": "0%",
        "base_offset": "100% 100%",
        "operation": "Чтение буфера A",
        "numeric_values": "135.0 07823 2032 2094"
      },
      "caption_data": {
        "illustration_number": "№21",
        "full_text": "Иллюстрация №21. Изображение одного из ЯМР участков исследуемых штрихов рукописной подписи от имени Тисленко Т.Б. в предоставленном на исследование Объекте №5 при первом проколе.",
        "structured_details": {
          "object_type": "ЯМР участок",
          "source_item": "рукописной подписи",
          "investigation_object": "Объект №5",
          "condition": "при первом проколе"
        }
      }
    }
  ],
  "model": "gpt-4o-2024-08-06",
  "usage": {
    "prompt_tokens": 2025,
    "completion_tokens": 1514,
    "total_tokens": 3539,
    "prompt_tokens_details": {
      "cached_tokens": 0,
      "audio_tokens": 0
    },
    "completion_tokens_details": {
      "reasoning_tokens": 0,
      "audio_tokens": 0,
      "accepted_prediction_tokens": 0,
      "rejected_prediction_tokens": 0
    }
  }
}