{
  "page": 20,
  "content": "```json\n[\n  {\n    \"page_context\": {\n      \"title\": \"Приложение №6. Изображения графиков ЯМР участков…\"\n    },\n    \"graph_id\": 1,\n    \"header_data\": {\n      \"full_text\": \"Образец № 1 к Заключению № 11366; Индекс кристалличности = 0.79650; Протонная плотность = 2.06219\",\n      \"structured_metrics\": {\n        \"sample_reference\": \"Образец № 1 к Заключению № 11366\",\n        \"crystallinity_index\": 0.79650,\n        \"proton_density\": 2.06219\n      }\n    },\n    \"graph_statistics\": {\n      \"axes\": {\n        \"y_axis\": { \"label\": \"Интенсивность, а.е.\", \"visible_min\": null, \"visible_max\": null, \"step_interval\": null },\n        \"x_axis\": { \"label\": \"Время, мкс\", \"visible_min\": null, \"visible_max\": null, \"step_interval\": null }\n      },\n      \"y_metrics_max\": { \"red\": null, \"blue\": null, \"green\": null },\n      \"visible_tabs\": []\n    },\n    \"log_panel_data\": {\n      \"timestamp\": \"10:05:46\",\n      \"raw_lines\": [\n        \"Дата исследования - 24.06.2023\",\n        \"Время релаксации короткой компоненты - 243.04629 мкс\",\n        \"Время релаксации длинной компоненты - 30.82663 мкс\",\n        \"Амплитуда короткой компоненты - 19.77665 а.е.\",\n        \"Амплитуда длинной компоненты - 3.26117 а.е.\",\n        \"Индекс кристалличности - 0.79850\",\n        \"Протонная плотность - 2.06196\"\n      ],\n      \"structured_log_metrics\": {\n        \"research_date\": \"24.06.2023\",\n        \"relaxation_time_short_component_mks\": 243.04629,\n        \"relaxation_time_long_component_mks\": 30.82663,\n        \"amplitude_short_component_au\": 19.77665,\n        \"amplitude_long_component_au\": 3.26117,\n        \"calculated_crystallinity_index\": 0.79850,\n        \"calculated_proton_density\": 2.06196\n      }\n    },\n    \"status_bar_data\": {\n      \"urtb\": \"3%\",\n      \"adc\": \"\",\n      \"base_offset\": \"100% 100%\",\n      \"operation\": \"Чтение буфера A\",\n      \"numeric_values\": \"135.0 7823 2032 2094\"\n    },\n    \"caption_data\": {\n      \"illustration_number\": \"№38\",\n      \"full_text\": \"Иллюстрация №38. Изображение одного из ЯМР участков исследуемых штрихов рукописной подписи от имени Филиппенко И.Н. в предоставленном на исследование Объекте №9 при первом проколе.\",\n      \"structured_details\": {\n        \"object_type\": \"\",\n        \"source_item\": \"\",\n        \"investigation_object\": \"Объекта №9\",\n        \"condition\": \"при первом проколе\"\n      }\n    }\n  },\n  {\n    \"page_context\": {\n      \"title\": \"Приложение №6. Изображения графиков ЯМР участков…\"\n    },\n    \"graph_id\": 2,\n    \"header_data\": {\n      \"full_text\": \"Образец № 1 к Заключению № 11366; Индекс кристалличности = 0.78503; Протонная плотность = 3.84540\",\n      \"structured_metrics\": {\n        \"sample_reference\": \"Образец № 1 к Заключению № 11366\",\n        \"crystallinity_index\": 0.78503,\n        \"proton_density\": 3.84540\n      }\n    },\n    \"graph_statistics\": {\n      \"axes\": {\n        \"y_axis\": { \"label\": \"Интенсивность, а.е.\", \"visible_min\": null, \"visible_max\": null, \"step_interval\": null },\n        \"x_axis\": { \"label\": \"Время, мкс\", \"visible_min\": null, \"visible_max\": null, \"step_interval\": null }\n      },\n      \"y_metrics_max\": { \"red\": null, \"blue\": null, \"green\": null },\n      \"visible_tabs\": []\n    },\n    \"log_panel_data\": {\n      \"timestamp\": \"10:10:37\",\n      \"raw_lines\": [\n        \"Дата исследования - 24.06.2023\",\n        \"Время релаксации короткой компоненты - 371.95153 мкс\",\n        \"Время релаксации длинной компоненты - 283.92648 мкс\",\n        \"Амплитуда короткой компоненты - 1.57216 а.е.\",\n        \"Амплитуда длинной компоненты - 7.14795 а.е.\",\n        \"Индекс кристалличности - 1.27189\",\n        \"Протонная плотность - 3.84455\"\n      ],\n      \"structured_log_metrics\": {\n        \"research_date\": \"24.06.2023\",\n        \"relaxation_time_short_component_mks\": 371.95153,\n        \"relaxation_time_long_component_mks\": 283.92648,\n        \"amplitude_short_component_au\": 1.57216,\n        \"amplitude_long_component_au\": 7.14795,\n        \"calculated_crystallinity_index\": 1.27189,\n        \"calculated_proton_density\": 3.84455\n      }\n    },\n    \"status_bar_data\": {\n      \"urtb\": \"3%\",\n      \"adc\": \"\",\n      \"base_offset\": \"100% 100%\",\n      \"operation\": \"Чтение буфера A\",\n      \"numeric_values\": \"135.0 7823 2032 2094\"\n    },\n    \"caption_data\": {\n      \"illustration_number\": \"№39\",\n      \"full_text\": \"Иллюстрация №39. Изображение одного из ЯМР участков исследуемых штрихов рукописной подписи от имени Шмульт Т.А. в предоставленном на исследование Объекте №9 при первом проколе.\",\n      \"structured_details\": {\n        \"object_type\": \"\",\n        \"source_item\": \"\",\n        \"investigation_object\": \"Объекта №9\",\n        \"condition\": \"при первом проколе\"\n      }\n    }\n  }\n]\n```",
  "graphs": [
    {
      "page_context": {
        "title": "Приложение №6. Изображения графиков ЯМР участков…"
      },
      "graph_id": 1,
      "header_data": {
        "full_text": "Образец № 1 к Заключению № 11366; Индекс кристалличности = 0.79650; Протонная плотность = 2.06219",
        "structured_metrics": {
          "sample_reference": "Образец № 1 к Заключению № 11366",
          "crystallinity_index": 0.7965,
          "proton_density": 2.06219
        }
      },
      "graph_statistics": {
        "axes": {
          "y_axis": {
            "label": "Интенсивность, а.е.",
            "visible_min": null,
            "visible_max": null,
            "step_interval": null
          },
          "x_axis": {
            "label": "Время, мкс",
            "visible_min": null,
            "visible_max": null,
            "step_interval": null
          }
        },
        "y_metrics_max": {
          "red": null,
          "blue": null,
          "green": null
        },
        "visible_tabs": []
      },
      "log_panel_data": {
        "timestamp": "10:05:46",
        "raw_lines": [
          "Дата исследования - 24.06.2023",
          "Время релаксации короткой компоненты - 243.04629 мкс",
          "Время релаксации длинной компоненты - 30.82663 мкс",
          "Амплитуда короткой компоненты - 19.77665 а.е.",
          "Амплитуда длинной компоненты - 3.26117 а.е.",
          "Индекс кристалличности - 0.79850",
          "Протонная плотность - 2.06196"
        ],
        "structured_log_metrics": {
          "research_date": "24.06.2023",
          "relaxation_time_short_component_mks": 243.03629,
          "relaxation_time_long_component_mks": 30.80404,
          "amplitude_short_component_au": 18.76633,
          "amplitude_long_component_au": 14.07165,
          "calculated_crystallinity_index": 0.7985,
          "calculated_proton_density": 2.06196
        }
      },
      "status_bar_data": {
        "urtb": "3%",
        "adc": "",
        "base_offset": "100% 100%",
        "operation": "Чтение буфера A",
        "numeric_values": "135.0 7823 2032 2094"
      },
      "caption_data": {
        "illustration_number": "№38",
        "full_text": "Иллюстрация №38. Изображение одного из ЯМР участков исследуемых штрихов рукописной подписи от имени Филиппенко И.Н. в предоставленном на исследование Объекте №9 при первом проколе.",
        "structured_details": {
          "object_type": "",
          "source_item": "",
          "investigation_object": "Объекта №9",
          "condition": "при первом проколе"
        }
      }
    },
    {
      "page_context": {
        "title": "Приложение №6. Изображения графиков ЯМР участков…"
      },
      "graph_id": 2,
      "header_data": {
        "full_text": "Образец № 1 к Заключению № 11366; Индекс кристалличности = 0.78503; Протонная плотность = 3.84540",
        "structured_metrics": {
          "sample_reference": "Образец № 1 к Заключению № 11366",
          "crystallinity_index": 0.78503,
          "proton_density": 3.8454
        }
      },
      "graph_statistics": {
        "axes": {
          "y_axis": {
            "label": "Интенсивность, а.е.",
            "visible_min": null,
            "visible_max": null,
            "step_interval": null
          },
          "x_axis": {
            "label": "Время, мкс",
            "visible_min": null,
            "visible_max": null,
            "step_interval": null
          }
        },
        "y_metrics_max": {
          "red": null,
          "blue": null,
          "green": null
        },
        "visible_tabs": []
      },
      "log_panel_data": {
        "timestamp": "10:10:37",
        "raw_lines": [
          "Дата исследования - 24.06.2023",
          "Время релаксации короткой компоненты - 371.95153 мкс",
          "Время релаксации длинной компоненты - 283.92648 мкс",
          "Амплитуда короткой компоненты - 1.57216 а.е.",
          "Амплитуда длинной компоненты - 7.14795 а.е.",
          "Индекс кристалличности - 1.27189",
          "Протонная плотность - 3.84455"
        ],
        "structured_log_metrics": {
          "research_date": "24.06.2023",
          "relaxation_time_short_component_mks": 371.65153,
          "relaxation_time_long_component_mks": 288.94784,
          "amplitude_short_component_au": 7.82206,
          "amplitude_long_component_au": 5.13716,
          "calculated_crystallinity_index": 1.27189,
          "calculated_proton_density": 3.84455
        }
      },
      "status_bar_data": {
        "urtb": "3%",
        "adc": "",
        "base_offset": "100% 100%",
        "operation": "Чтение буфера A",
        "numeric_values": "135.0 7823 2032 2094"
      },
      "caption_data": {
        "illustration_number": "№39",
        "full_text": "Иллюстрация №39. Изображение одного из ЯМР участков исследуемых штрихов рукописной подписи от имени Шмульт Т.А. в предоставленном на исследование Объекте №9 при первом проколе.",
        "structured_details": {
          "object_type": "",
          "source_item": "",
          "investigation_object": "Объекта №9",
          "condition": "при первом проколе"
        }
      }
    }
  ],
  "model": "gpt-4o-2024-08-06",
  "usage": {
    "prompt_tokens": 2025,
    "completion_tokens": 1446,
    "total_tokens": 3471,
    "prompt_tokens_details": {
      "cached_tokens": 0,
      "audio_tokens": 0
    },
    "completion_tokens_details": {
      "reasoning_tokens": 0,
      "audio_tokens": 0,
      "accepted_prediction_tokens": 0,
      "rejected_prediction_tokens": 0
    }
  }
}