{
  "page": 75,
  "content": "```json\n[\n  {\n    \"page_context\": {\n      \"title\": \"Приложение №6. Изображения графиков ЯМР участков…\"\n    },\n    \"graph_id\": 1,\n    \"header_data\": {\n      \"full_text\": \"Образец № 3 к Заключению № 11366; Индекс кристалличности = 0.80789; Протонная плотность = 3.30126\",\n      \"structured_metrics\": {\n        \"sample_reference\": \"Образец № 3 к Заключению № 11366\",\n        \"crystallinity_index\": 0.80789,\n        \"proton_density\": 3.30126\n      }\n    },\n    \"graph_statistics\": {\n      \"axes\": {\n        \"y_axis\": {\n          \"label\": \"Сигнал, мкВ\",\n          \"visible_min\": 0,\n          \"visible_max\": null,\n          \"step_interval\": null\n        },\n        \"x_axis\": {\n          \"label\": \"Время, мкс\",\n          \"visible_min\": 0,\n          \"visible_max\": null,\n          \"step_interval\": null\n        }\n      },\n      \"y_metrics_max\": {\n        \"red\": null,\n        \"blue\": null,\n        \"green\": null\n      },\n      \"visible_tabs\": [\"NMR Signal\", \"Results Graph\", \"Code\"]\n    },\n    \"log_panel_data\": {\n      \"timestamp\": \"11:58:24\",\n      \"raw_lines\": [\n        \"11:58:24  Дата исследования - 10.07.2025\",\n        \"11:58:24  Время релаксации короткой компоненты - 197.13458 мкс\",\n        \"11:58:24  Время релаксации длинной компоненты - 475.23241 мкс\",\n        \"11:58:24  Амплитуда короткой компоненты - 6.4456 a.u.\",\n        \"11:58:24  Амплитуда длинной компоненты - 4.78278 a.u.\",\n        \"11:58:24  Протонная плотность = 3.30126\"\n      ],\n      \"structured_log_metrics\": {\n        \"research_date\": \"10.07.2025\",\n        \"relaxation_time_short_component_mks\": 197.13458,\n        \"relaxation_time_long_component_mks\": 475.23241,\n        \"amplitude_short_component_au\": 6.4456,\n        \"amplitude_long_component_au\": 4.78278,\n        \"calculated_crystallinity_index\": 0.80789,\n        \"calculated_proton_density\": 3.30126\n      }\n    },\n    \"status_bar_data\": {\n      \"urtb\": \"3%\",\n      \"adc\": \"0%\",\n      \"base_offset\": \"100% 100%\",\n      \"operation\": \"Чтение буфера A\",\n      \"numeric_values\": \"1.135 0.7823 2094\"\n    },\n    \"caption_data\": {\n      \"illustration_number\": \"148\",\n      \"full_text\": \"Иллюстрация №148. Изображение одного из ЯМР участков исследуемых штрихов оттиска круглой мастичной печати ООО «Ростовская нива» в предоставленном на исследование Объекте №8 при третьем проколе.\",\n      \"structured_details\": {\n        \"object_type\": \"штрихи оттиска круглой мастичной печати\",\n        \"source_item\": \"ООО «Ростовская нива»\",\n        \"investigation_object\": \"Объект №8\",\n        \"condition\": \"при третьем проколе\"\n      }\n    }\n  },\n  {\n    \"graph_id\": 2,\n    \"header_data\": {\n      \"full_text\": \"Образец № 3 к Заключению № 11366; Индекс кристалличности = 0.79936; Протонная плотность = 3.79005\",\n      \"structured_metrics\": {\n        \"sample_reference\": \"Образец № 3 к Заключению № 11366\",\n        \"crystallinity_index\": 0.79936,\n        \"proton_density\": 3.79005\n      }\n    },\n    \"graph_statistics\": {\n      \"axes\": {\n        \"y_axis\": {\n          \"label\": \"Сигнал, мкВ\",\n          \"visible_min\": 0,\n          \"visible_max\": null,\n          \"step_interval\": null\n        },\n        \"x_axis\": {\n          \"label\": \"время, мкс\",\n          \"visible_min\": 0,\n          \"visible_max\": null,\n          \"step_interval\": null\n        }\n      },\n      \"y_metrics_max\": {\n        \"red\": null,\n        \"blue\": null,\n        \"green\": null\n      },\n      \"visible_tabs\": [\"NMR Signal\", \"Results Graph\", \"Code\"]\n    },\n    \"log_panel_data\": {\n      \"timestamp\": \"12:00:48\",\n      \"raw_lines\": [\n        \"12:00:48  Дата исследования - 10.07.2025\",\n        \"12:00:48  Время релаксации короткой компоненты - 384.79465 мкс\",\n        \"12:00:48  Время релаксации длинной компоненты - 296.73254 мкс\",\n        \"12:00:48  Амплитуда короткой компоненты - 4.27664 a.u.\",\n        \"12:00:48  Амплитуда длинной компоненты - 2.73155 a.u.\",\n        \"12:00:48  Протонная плотность = 3.79005\"\n      ],\n      \"structured_log_metrics\": {\n        \"research_date\": \"10.07.2025\",\n        \"relaxation_time_short_component_mks\": 384.79465,\n        \"relaxation_time_long_component_mks\": 296.73254,\n        \"amplitude_short_component_au\": 4.27664,\n        \"amplitude_long_component_au\": 2.73155,\n        \"calculated_crystallinity_index\": 0.79936,\n        \"calculated_proton_density\": 3.79005\n      }\n    },\n    \"status_bar_data\": {\n      \"urtb\": \"3%\",\n      \"adc\": \"0%\",\n      \"base_offset\": \"100% 100%\",\n      \"operation\": \"Чтение буфера A\",\n      \"numeric_values\": \"1.135 0.7823 2094\"\n    },\n    \"caption_data\": {\n      \"illustration_number\": \"149\",\n      \"full_text\": \"Иллюстрация №149. Изображение одного из ЯМР участков исследуемых штрихов оттиска круглой мастичной печати ПАО «Московский Индустриальный банк» в предоставленном на исследование Объекте №9 при третьем проколе.\",\n      \"structured_details\": {\n        \"object_type\": \"штрихи оттиска круглой мастичной печати\",\n        \"source_item\": \"ПАО «Московский Индустриальный банк»\",\n        \"investigation_object\": \"Объект №9\",\n        \"condition\": \"при третьем проколе\"\n      }\n    }\n  }\n]\n```",
  "graphs": [
    {
      "page_context": {
        "title": "Приложение №6. Изображения графиков ЯМР участков…"
      },
      "graph_id": 1,
      "header_data": {
        "full_text": "Образец № 3 к Заключению № 11366; Индекс кристалличности = 0.80789; Протонная плотность = 3.30126",
        "structured_metrics": {
          "sample_reference": "Образец № 3 к Заключению № 11366",
          "crystallinity_index": 0.80789,
          "proton_density": 3.30126
        }
      },
      "graph_statistics": {
        "axes": {
          "y_axis": {
            "label": "Сигнал, мкВ",
            "visible_min": 0,
            "visible_max": null,
            "step_interval": null
          },
          "x_axis": {
            "label": "Время, мкс",
            "visible_min": 0,
            "visible_max": null,
            "step_interval": null
          }
        },
        "y_metrics_max": {
          "red": null,
          "blue": null,
          "green": null
        },
        "visible_tabs": [
          "NMR Signal",
          "Results Graph",
          "Code"
        ]
      },
      "log_panel_data": {
        "timestamp": "11:58:24",
        "raw_lines": [
          "11:58:24  Дата исследования - 10.07.2025",
          "11:58:24  Время релаксации короткой компоненты - 197.13458 мкс",
          "11:58:24  Время релаксации длинной компоненты - 475.23241 мкс",
          "11:58:24  Амплитуда короткой компоненты - 6.4456 a.u.",
          "11:58:24  Амплитуда длинной компоненты - 4.78278 a.u.",
          "11:58:24  Протонная плотность = 3.30126"
        ],
        "structured_log_metrics": {
          "research_date": "10.07.2025",
          "relaxation_time_short_component_mks": 197.13458,
          "relaxation_time_long_component_mks": 475.23241,
          "amplitude_short_component_au": 6.4456,
          "amplitude_long_component_au": 4.78278,
          "calculated_crystallinity_index": 0.80789,
          "calculated_proton_density": 3.30126
        }
      },
      "status_bar_data": {
        "urtb": "3%",
        "adc": "0%",
        "base_offset": "100% 100%",
        "operation": "Чтение буфера A",
        "numeric_values": "1.135 0.7823 2094"
      },
      "caption_data": {
        "illustration_number": "148",
        "full_text": "Иллюстрация №148. Изображение одного из ЯМР участков исследуемых штрихов оттиска круглой мастичной печати ООО «Ростовская нива» в предоставленном на исследование Объекте №8 при третьем проколе.",
        "structured_details": {
          "object_type": "штрихи оттиска круглой мастичной печати",
          "source_item": "ООО «Ростовская нива»",
          "investigation_object": "Объект №8",
          "condition": "при третьем проколе"
        }
      }
    },
    {
      "graph_id": 2,
      "header_data": {
        "full_text": "Образец № 3 к Заключению № 11366; Индекс кристалличности = 0.79936; Протонная плотность = 3.79005",
        "structured_metrics": {
          "sample_reference": "Образец № 3 к Заключению № 11366",
          "crystallinity_index": 0.79936,
          "proton_density": 3.79005
        }
      },
      "graph_statistics": {
        "axes": {
          "y_axis": {
            "label": "Сигнал, мкВ",
            "visible_min": 0,
            "visible_max": null,
            "step_interval": null
          },
          "x_axis": {
            "label": "время, мкс",
            "visible_min": 0,
            "visible_max": null,
            "step_interval": null
          }
        },
        "y_metrics_max": {
          "red": null,
          "blue": null,
          "green": null
        },
        "visible_tabs": [
          "NMR Signal",
          "Results Graph",
          "Code"
        ]
      },
      "log_panel_data": {
        "timestamp": "12:00:48",
        "raw_lines": [
          "12:00:48  Дата исследования - 10.07.2025",
          "12:00:48  Время релаксации короткой компоненты - 384.79465 мкс",
          "12:00:48  Время релаксации длинной компоненты - 296.73254 мкс",
          "12:00:48  Амплитуда короткой компоненты - 4.27664 a.u.",
          "12:00:48  Амплитуда длинной компоненты - 2.73155 a.u.",
          "12:00:48  Протонная плотность = 3.79005"
        ],
        "structured_log_metrics": {
          "research_date": "10.07.2025",
          "relaxation_time_short_component_mks": 384.79465,
          "relaxation_time_long_component_mks": 296.73254,
          "amplitude_short_component_au": 4.27664,
          "amplitude_long_component_au": 2.73155,
          "calculated_crystallinity_index": 0.79936,
          "calculated_proton_density": 3.79005
        }
      },
      "status_bar_data": {
        "urtb": "3%",
        "adc": "0%",
        "base_offset": "100% 100%",
        "operation": "Чтение буфера A",
        "numeric_values": "1.135 0.7823 2094"
      },
      "caption_data": {
        "illustration_number": "149",
        "full_text": "Иллюстрация №149. Изображение одного из ЯМР участков исследуемых штрихов оттиска круглой мастичной печати ПАО «Московский Индустриальный банк» в предоставленном на исследование Объекте №9 при третьем проколе.",
        "structured_details": {
          "object_type": "штрихи оттиска круглой мастичной печати",
          "source_item": "ПАО «Московский Индустриальный банк»",
          "investigation_object": "Объект №9",
          "condition": "при третьем проколе"
        }
      }
    }
  ],
  "model": "gpt-4o-2024-08-06",
  "usage": {
    "prompt_tokens": 2025,
    "completion_tokens": 1579,
    "total_tokens": 3604,
    "prompt_tokens_details": {
      "cached_tokens": 0,
      "audio_tokens": 0
    },
    "completion_tokens_details": {
      "reasoning_tokens": 0,
      "audio_tokens": 0,
      "accepted_prediction_tokens": 0,
      "rejected_prediction_tokens": 0
    }
  }
}