{
  "page": 55,
  "content": "```json\n[\n  {\n    \"page_context\": {\n      \"title\": \"Приложение №3. Изображение графиков ЯМР участков исследуемых штрихов\"\n    },\n    \"graph_id\": 1,\n    \"header_data\": {\n      \"full_text\": \"Образец № 3 к Заключению № 11366; Индекс кристалличности = 0.75821; Протонная плотность = 3.94963\",\n      \"structured_metrics\": {\n        \"sample_reference\": \"Образец № 3 к Заключению № 11366\",\n        \"crystallinity_index\": 0.75821,\n        \"proton_density\": 3.94963\n      }\n    },\n    \"graph_statistics\": {\n      \"axes\": {\n        \"y_axis\": { \"label\": \"Амплитуда\", \"visible_min\": 0, \"visible_max\": 30, \"step_interval\": 3 },\n        \"x_axis\": { \"label\": \"Время, мкс\", \"visible_min\": 0, \"visible_max\": 250, \"step_interval\": 25 }\n      },\n      \"y_metrics_max\": { \"red\": 19, \"blue\": 17, \"green\": 14 },\n      \"visible_tabs\": [\"NMR Signal\", \"Results Graph\", \"Code\"]\n    },\n    \"log_panel_data\": {\n      \"timestamp\": \"09:02:30\",\n      \"raw_lines\": [\n        \"Дата исследования - 19.07.2023\",\n        \"Время релаксации короткой компоненты - 196.12931 мкс\",\n        \"Время релаксации длинной компоненты - 5.92525 мкс\",\n        \"Амплитуда короткой компоненты - 3.9703 a.u.\",\n        \"Амплитуда длинной компоненты - 2.51454 a.u.\",\n        \"Индекс кристалличности - 5.4125 %\",\n        \"Протонная плотность - 3.2344\"\n      ],\n      \"structured_log_metrics\": {\n        \"research_date\": \"19.07.2023\",\n        \"relaxation_time_short_component_mks\": 196.12931,\n        \"relaxation_time_long_component_mks\": 5.92525,\n        \"amplitude_short_component_au\": 3.9703,\n        \"amplitude_long_component_au\": 2.51454,\n        \"calculated_crystallinity_index\": 5.4125,\n        \"calculated_proton_density\": 3.2344\n      }\n    },\n    \"status_bar_data\": {\n      \"urtb\": \"3%\",\n      \"adc\": \"0%\",\n      \"base_offset\": \"100% 100%\",\n      \"operation\": \"Чтение буфера A\",\n      \"numeric_values\": \"1.135 0.7823 2032 2094\"\n    },\n    \"caption_data\": {\n      \"illustration_number\": \"№108\",\n      \"full_text\": \"Изображение одного из ЯМР участков исследуемых штрихов рукописной подписи от имени Филиппенко И.Н. в предоставленном на исследование Объекте №7 при третьем проколе.\",\n      \"structured_details\": {\n        \"object_type\": \"рукописная подпись\",\n        \"source_item\": \"Филиппенко И.Н.\",\n        \"investigation_object\": \"Объект №7\",\n        \"condition\": \"третий прокол\"\n      }\n    }\n  },\n  {\n    \"graph_id\": 2,\n    \"header_data\": {\n      \"full_text\": \"Образец № 3 к Заключению № 11366; Индекс кристалличности = 0.78943; Протонная плотность = 2.78103\",\n      \"structured_metrics\": {\n        \"sample_reference\": \"Образец № 3 к Заключению № 11366\",\n        \"crystallinity_index\": 0.78943,\n        \"proton_density\": 2.78103\n      }\n    },\n    \"graph_statistics\": {\n      \"axes\": {\n        \"y_axis\": { \"label\": \"Амплитуда\", \"visible_min\": 0, \"visible_max\": 30, \"step_interval\": 3 },\n        \"x_axis\": { \"label\": \"Время, мкс\", \"visible_min\": 0, \"visible_max\": 250, \"step_interval\": 25 }\n      },\n      \"y_metrics_max\": { \"red\": 20, \"blue\": 18, \"green\": 15 },\n      \"visible_tabs\": [\"NMR Signal\", \"Results Graph\", \"Code\"]\n    },\n    \"log_panel_data\": {\n      \"timestamp\": \"09:21:42\",\n      \"raw_lines\": [\n        \"Дата исследования - 19.07.2023\",\n        \"Время релаксации короткой компоненты - 198.25942 мкс\",\n        \"Время релаксации длинной компоненты - 4.72651 мкс\",\n        \"Амплитуда короткой компоненты - 3.05843 a.u.\",\n        \"Амплитуда длинной компоненты - 2.3756 a.u.\",\n        \"Индекс кристалличности - 6.5476 %\",\n        \"Протонная плотность - 2.78103\"\n      ],\n      \"structured_log_metrics\": {\n        \"research_date\": \"19.07.2023\",\n        \"relaxation_time_short_component_mks\": 198.25942,\n        \"relaxation_time_long_component_mks\": 4.72651,\n        \"amplitude_short_component_au\": 3.05843,\n        \"amplitude_long_component_au\": 2.3756,\n        \"calculated_crystallinity_index\": 6.5476,\n        \"calculated_proton_density\": 2.78103\n      }\n    },\n    \"status_bar_data\": {\n      \"urtb\": \"3%\",\n      \"adc\": \"0%\",\n      \"base_offset\": \"100% 100%\",\n      \"operation\": \"Чтение буфера A\",\n      \"numeric_values\": \"1.135 0.7823 2032 2094\"\n    },\n    \"caption_data\": {\n      \"illustration_number\": \"№109\",\n      \"full_text\": \"Изображение одного из ЯМР участков исследуемых штрихов рукописной подписи от имени Шмульт Т.А. в предоставленном на исследование Объекте №7 при третьем проколе.\",\n      \"structured_details\": {\n        \"object_type\": \"рукописная подпись\",\n        \"source_item\": \"Шмульт Т.А.\",\n        \"investigation_object\": \"Объект №7\",\n        \"condition\": \"третий прокол\"\n      }\n    }\n  }\n]\n```",
  "graphs": [
    {
      "page_context": {
        "title": "Приложение №3. Изображение графиков ЯМР участков исследуемых штрихов"
      },
      "graph_id": 1,
      "header_data": {
        "full_text": "Образец № 3 к Заключению № 11366; Индекс кристалличности = 0.75821; Протонная плотность = 3.94963",
        "structured_metrics": {
          "sample_reference": "Образец № 3 к Заключению № 11366",
          "crystallinity_index": 0.75821,
          "proton_density": 3.94963
        }
      },
      "graph_statistics": {
        "axes": {
          "y_axis": {
            "label": "Амплитуда",
            "visible_min": 0,
            "visible_max": 30,
            "step_interval": 3
          },
          "x_axis": {
            "label": "Время, мкс",
            "visible_min": 0,
            "visible_max": 250,
            "step_interval": 25
          }
        },
        "y_metrics_max": {
          "red": 19,
          "blue": 17,
          "green": 14
        },
        "visible_tabs": [
          "NMR Signal",
          "Results Graph",
          "Code"
        ]
      },
      "log_panel_data": {
        "timestamp": "09:02:30",
        "raw_lines": [
          "Дата исследования - 19.07.2023",
          "Время релаксации короткой компоненты - 196.12931 мкс",
          "Время релаксации длинной компоненты - 5.92525 мкс",
          "Амплитуда короткой компоненты - 3.9703 a.u.",
          "Амплитуда длинной компоненты - 2.51454 a.u.",
          "Индекс кристалличности - 5.4125 %",
          "Протонная плотность - 3.2344"
        ],
        "structured_log_metrics": {
          "research_date": "19.07.2023",
          "relaxation_time_short_component_mks": 196.12931,
          "relaxation_time_long_component_mks": 5.92525,
          "amplitude_short_component_au": 3.9703,
          "amplitude_long_component_au": 2.51454,
          "calculated_crystallinity_index": 5.4125,
          "calculated_proton_density": 3.2344
        }
      },
      "status_bar_data": {
        "urtb": "3%",
        "adc": "0%",
        "base_offset": "100% 100%",
        "operation": "Чтение буфера A",
        "numeric_values": "1.135 0.7823 2032 2094"
      },
      "caption_data": {
        "illustration_number": "№108",
        "full_text": "Изображение одного из ЯМР участков исследуемых штрихов рукописной подписи от имени Филиппенко И.Н. в предоставленном на исследование Объекте №7 при третьем проколе.",
        "structured_details": {
          "object_type": "рукописная подпись",
          "source_item": "Филиппенко И.Н.",
          "investigation_object": "Объект №7",
          "condition": "третий прокол"
        }
      }
    },
    {
      "graph_id": 2,
      "header_data": {
        "full_text": "Образец № 3 к Заключению № 11366; Индекс кристалличности = 0.78943; Протонная плотность = 2.78103",
        "structured_metrics": {
          "sample_reference": "Образец № 3 к Заключению № 11366",
          "crystallinity_index": 0.78943,
          "proton_density": 2.78103
        }
      },
      "graph_statistics": {
        "axes": {
          "y_axis": {
            "label": "Амплитуда",
            "visible_min": 0,
            "visible_max": 30,
            "step_interval": 3
          },
          "x_axis": {
            "label": "Время, мкс",
            "visible_min": 0,
            "visible_max": 250,
            "step_interval": 25
          }
        },
        "y_metrics_max": {
          "red": 20,
          "blue": 18,
          "green": 15
        },
        "visible_tabs": [
          "NMR Signal",
          "Results Graph",
          "Code"
        ]
      },
      "log_panel_data": {
        "timestamp": "09:21:42",
        "raw_lines": [
          "Дата исследования - 19.07.2023",
          "Время релаксации короткой компоненты - 198.25942 мкс",
          "Время релаксации длинной компоненты - 4.72651 мкс",
          "Амплитуда короткой компоненты - 3.05843 a.u.",
          "Амплитуда длинной компоненты - 2.3756 a.u.",
          "Индекс кристалличности - 6.5476 %",
          "Протонная плотность - 2.78103"
        ],
        "structured_log_metrics": {
          "research_date": "19.07.2023",
          "relaxation_time_short_component_mks": 198.25942,
          "relaxation_time_long_component_mks": 4.72651,
          "amplitude_short_component_au": 3.05843,
          "amplitude_long_component_au": 2.3756,
          "calculated_crystallinity_index": 6.5476,
          "calculated_proton_density": 2.78103
        }
      },
      "status_bar_data": {
        "urtb": "3%",
        "adc": "0%",
        "base_offset": "100% 100%",
        "operation": "Чтение буфера A",
        "numeric_values": "1.135 0.7823 2032 2094"
      },
      "caption_data": {
        "illustration_number": "№109",
        "full_text": "Изображение одного из ЯМР участков исследуемых штрихов рукописной подписи от имени Шмульт Т.А. в предоставленном на исследование Объекте №7 при третьем проколе.",
        "structured_details": {
          "object_type": "рукописная подпись",
          "source_item": "Шмульт Т.А.",
          "investigation_object": "Объект №7",
          "condition": "третий прокол"
        }
      }
    }
  ],
  "model": "gpt-4o-2024-08-06",
  "usage": {
    "prompt_tokens": 2025,
    "completion_tokens": 1479,
    "total_tokens": 3504,
    "prompt_tokens_details": {
      "cached_tokens": 0,
      "audio_tokens": 0
    },
    "completion_tokens_details": {
      "reasoning_tokens": 0,
      "audio_tokens": 0,
      "accepted_prediction_tokens": 0,
      "rejected_prediction_tokens": 0
    }
  }
}