{
  "page": 39,
  "content": "```json\n[\n  {\n    \"page_context\": {\n      \"title\": \"Приложение №6. Изображения графиков ЯМР участков исследуемых штрихов оттиска круглой мастичной печати ООО «Агро-Индустриальная Корпорация «Волго-Дон» в предоставленном на исследование Объекте №11 при первом проколе.\"\n    },\n    \"graph_id\": 1,\n    \"header_data\": {\n      \"full_text\": \"Образец № 1 к Заключению № 11366; Индекс кристалличности = 0.80630; Протонная плотность = 2.84545\",\n      \"structured_metrics\": {\n        \"sample_reference\": \"Образец № 1 к Заключению № 11366\",\n        \"crystallinity_index\": 0.80630,\n        \"proton_density\": 2.84545\n      }\n    },\n    \"graph_statistics\": {\n      \"axes\": {\n        \"y_axis\": {\n          \"label\": \"Амплитуда\",\n          \"visible_min\": null,\n          \"visible_max\": null,\n          \"step_interval\": null\n        },\n        \"x_axis\": {\n          \"label\": \"Время, мкс\",\n          \"visible_min\": null,\n          \"visible_max\": null,\n          \"step_interval\": null\n        }\n      },\n      \"y_metrics_max\": {\n        \"red\": null,\n        \"blue\": null,\n        \"green\": null\n      },\n      \"visible_tabs\": []\n    },\n    \"log_panel_data\": {\n      \"timestamp\": \"12:17:39\",\n      \"raw_lines\": [\n        \"Дата исследования: 24.06.2023\",\n        \"Время релаксации короткой компоненты = 265.11231 мкс\",\n        \"Время релаксации длинной компоненты = 1324.5680 мкс\",\n        \"Амплитуда короткой компоненты = 1.173565 а.е.\",\n        \"Амплитуда длинной компоненты = 13.63536 а.е.\",\n        \"Индекс кристалличности = 0.80630\",\n        \"Протонная плотность = 2.84545\"\n      ],\n      \"structured_log_metrics\": {\n        \"research_date\": \"24.06.2023\",\n        \"relaxation_time_short_component_mks\": 265.11231,\n        \"relaxation_time_long_component_mks\": 1324.5680,\n        \"amplitude_short_component_au\": 1.173565,\n        \"amplitude_long_component_au\": 13.63536,\n        \"calculated_crystallinity_index\": 0.80630,\n        \"calculated_proton_density\": 2.84545\n      }\n    },\n    \"status_bar_data\": {\n      \"urtb\": \"3%\",\n      \"adc\": \"\",\n      \"base_offset\": \"100% 100%\",\n      \"operation\": \"Чтение буфера A\",\n      \"numeric_values\": \"135.0 7823 2032 2094\"\n    },\n    \"caption_data\": {\n      \"illustration_number\": \"№76\",\n      \"full_text\": \"Иллюстрация №76. Изображение одного из ЯМР участков исследуемых штрихов оттиска круглой мастичной печати ООО «Агро-Индустриальная Корпорация «Волго-Дон» в предоставленном на исследование Объекте №11 при первом проколе.\",\n      \"structured_details\": {\n        \"object_type\": \"ЯМР участков\",\n        \"source_item\": \"ООО «Агро-Индустриальная Корпорация «Волго-Дон»\",\n        \"investigation_object\": \"Объект №11\",\n        \"condition\": \"первом проколе\"\n      }\n    }\n  },\n  {\n    \"graph_id\": 2,\n    \"header_data\": {\n      \"full_text\": \"Образец № 1 к Заключению № 11366; Индекс кристалличности = 0.80307; Протонная плотность = 2.17198\",\n      \"structured_metrics\": {\n        \"sample_reference\": \"Образец № 1 к Заключению № 11366\",\n        \"crystallinity_index\": 0.80307,\n        \"proton_density\": 2.17198\n      }\n    },\n    \"graph_statistics\": {\n      \"axes\": {\n        \"y_axis\": {\n          \"label\": \"Амплитуда\",\n          \"visible_min\": null,\n          \"visible_max\": null,\n          \"step_interval\": null\n        },\n        \"x_axis\": {\n          \"label\": \"Время, мкс\",\n          \"visible_min\": null,\n          \"visible_max\": null,\n          \"step_interval\": null\n        }\n      },\n      \"y_metrics_max\": {\n        \"red\": null,\n        \"blue\": null,\n        \"green\": null\n      },\n      \"visible_tabs\": []\n    },\n    \"log_panel_data\": {\n      \"timestamp\": \"12:04:08\",\n      \"raw_lines\": [\n        \"Дата исследования: 24.06.2023\",\n        \"Время релаксации короткой компоненты = 344.99531 мкс\",\n        \"Время релаксации длинной компоненты = 2036.1289 мкс\",\n        \"Амплитуда короткой компоненты = 1.172593 а.е.\",\n        \"Амплитуда длинной компоненты = 12.93733 а.е.\",\n        \"Индекс кристалличности = 0.80307\",\n        \"Протонная плотность = 2.17198\"\n      ],\n      \"structured_log_metrics\": {\n        \"research_date\": \"24.06.2023\",\n        \"relaxation_time_short_component_mks\": 344.99531,\n        \"relaxation_time_long_component_mks\": 2036.1289,\n        \"amplitude_short_component_au\": 1.172593,\n        \"amplitude_long_component_au\": 12.93733,\n        \"calculated_crystallinity_index\": 0.80307,\n        \"calculated_proton_density\": 2.17198\n      }\n    },\n    \"status_bar_data\": {\n      \"urtb\": \"3%\",\n      \"adc\": \"\",\n      \"base_offset\": \"100% 100%\",\n      \"operation\": \"Чтение буфера A\",\n      \"numeric_values\": \"135.0 7823 2032 2094\"\n    },\n    \"caption_data\": {\n      \"illustration_number\": \"№77\",\n      \"full_text\": \"Иллюстрация №77. Изображение одного из ЯМР участков исследуемых штрихов оттиска круглой мастичной печати ПАО «Московский Индустриальный банк» в предоставленном на исследование Объекте №12 при первом проколе.\",\n      \"structured_details\": {\n        \"object_type\": \"ЯМР участков\",\n        \"source_item\": \"ПАО «Московский Индустриальный банк»\",\n        \"investigation_object\": \"Объект №12\",\n        \"condition\": \"первом проколе\"\n      }\n    }\n  }\n]\n```",
  "graphs": [
    {
      "page_context": {
        "title": "Приложение №6. Изображения графиков ЯМР участков исследуемых штрихов оттиска круглой мастичной печати ООО «Агро-Индустриальная Корпорация «Волго-Дон» в предоставленном на исследование Объекте №11 при первом проколе."
      },
      "graph_id": 1,
      "header_data": {
        "full_text": "Образец № 1 к Заключению № 11366; Индекс кристалличности = 0.80630; Протонная плотность = 2.84545",
        "structured_metrics": {
          "sample_reference": "Образец № 1 к Заключению № 11366",
          "crystallinity_index": 0.8063,
          "proton_density": 2.84545
        }
      },
      "graph_statistics": {
        "axes": {
          "y_axis": {
            "label": "Амплитуда",
            "visible_min": null,
            "visible_max": null,
            "step_interval": null
          },
          "x_axis": {
            "label": "Время, мкс",
            "visible_min": null,
            "visible_max": null,
            "step_interval": null
          }
        },
        "y_metrics_max": {
          "red": null,
          "blue": null,
          "green": null
        },
        "visible_tabs": []
      },
      "log_panel_data": {
        "timestamp": "12:17:39",
        "raw_lines": [
          "Дата исследования: 24.06.2023",
          "Время релаксации короткой компоненты = 265.11231 мкс",
          "Время релаксации длинной компоненты = 1324.5680 мкс",
          "Амплитуда короткой компоненты = 1.173565 а.е.",
          "Амплитуда длинной компоненты = 13.63536 а.е.",
          "Индекс кристалличности = 0.80630",
          "Протонная плотность = 2.84545"
        ],
        "structured_log_metrics": {
          "research_date": "24.06.2023",
          "relaxation_time_short_component_mks": 265.11231,
          "relaxation_time_long_component_mks": 1324.568,
          "amplitude_short_component_au": 1.173565,
          "amplitude_long_component_au": 13.63536,
          "calculated_crystallinity_index": 0.8063,
          "calculated_proton_density": 2.84545
        }
      },
      "status_bar_data": {
        "urtb": "3%",
        "adc": "",
        "base_offset": "100% 100%",
        "operation": "Чтение буфера A",
        "numeric_values": "135.0 7823 2032 2094"
      },
      "caption_data": {
        "illustration_number": "№76",
        "full_text": "Иллюстрация №76. Изображение одного из ЯМР участков исследуемых штрихов оттиска круглой мастичной печати ООО «Агро-Индустриальная Корпорация «Волго-Дон» в предоставленном на исследование Объекте №11 при первом проколе.",
        "structured_details": {
          "object_type": "ЯМР участков",
          "source_item": "ООО «Агро-Индустриальная Корпорация «Волго-Дон»",
          "investigation_object": "Объект №11",
          "condition": "первом проколе"
        }
      }
    },
    {
      "graph_id": 2,
      "header_data": {
        "full_text": "Образец № 1 к Заключению № 11366; Индекс кристалличности = 0.80307; Протонная плотность = 2.17198",
        "structured_metrics": {
          "sample_reference": "Образец № 1 к Заключению № 11366",
          "crystallinity_index": 0.80307,
          "proton_density": 2.17198
        }
      },
      "graph_statistics": {
        "axes": {
          "y_axis": {
            "label": "Амплитуда",
            "visible_min": null,
            "visible_max": null,
            "step_interval": null
          },
          "x_axis": {
            "label": "Время, мкс",
            "visible_min": null,
            "visible_max": null,
            "step_interval": null
          }
        },
        "y_metrics_max": {
          "red": null,
          "blue": null,
          "green": null
        },
        "visible_tabs": []
      },
      "log_panel_data": {
        "timestamp": "12:04:08",
        "raw_lines": [
          "Дата исследования: 24.06.2023",
          "Время релаксации короткой компоненты = 344.99531 мкс",
          "Время релаксации длинной компоненты = 2036.1289 мкс",
          "Амплитуда короткой компоненты = 1.172593 а.е.",
          "Амплитуда длинной компоненты = 12.93733 а.е.",
          "Индекс кристалличности = 0.80307",
          "Протонная плотность = 2.17198"
        ],
        "structured_log_metrics": {
          "research_date": "24.06.2023",
          "relaxation_time_short_component_mks": 344.99531,
          "relaxation_time_long_component_mks": 2036.1289,
          "amplitude_short_component_au": 1.172593,
          "amplitude_long_component_au": 12.93733,
          "calculated_crystallinity_index": 0.80307,
          "calculated_proton_density": 2.17198
        }
      },
      "status_bar_data": {
        "urtb": "3%",
        "adc": "",
        "base_offset": "100% 100%",
        "operation": "Чтение буфера A",
        "numeric_values": "135.0 7823 2032 2094"
      },
      "caption_data": {
        "illustration_number": "№77",
        "full_text": "Иллюстрация №77. Изображение одного из ЯМР участков исследуемых штрихов оттиска круглой мастичной печати ПАО «Московский Индустриальный банк» в предоставленном на исследование Объекте №12 при первом проколе.",
        "structured_details": {
          "object_type": "ЯМР участков",
          "source_item": "ПАО «Московский Индустриальный банк»",
          "investigation_object": "Объект №12",
          "condition": "первом проколе"
        }
      }
    }
  ],
  "model": "gpt-4o-2024-08-06",
  "usage": {
    "prompt_tokens": 2025,
    "completion_tokens": 1570,
    "total_tokens": 3595,
    "prompt_tokens_details": {
      "cached_tokens": 0,
      "audio_tokens": 0
    },
    "completion_tokens_details": {
      "reasoning_tokens": 0,
      "audio_tokens": 0,
      "accepted_prediction_tokens": 0,
      "rejected_prediction_tokens": 0
    }
  }
}