{
  "page": 69,
  "content": "```json\n[\n  {\n    \"page_context\": {\n      \"title\": \"Приложение №6. Изображения графиков ЯМР участков…\"\n    },\n    \"graph_id\": 1,\n    \"header_data\": {\n      \"full_text\": \"Образец № 3 к Заключению № 11366; Индекс кристалличности = 0.78824; Протонная плотность = 4.32330\",\n      \"structured_metrics\": {\n        \"sample_reference\": \"№ 3 к Заключению № 11366\",\n        \"crystallinity_index\": 0.78824,\n        \"proton_density\": 4.32330\n      }\n    },\n    \"graph_statistics\": {\n      \"axes\": {\n        \"y_axis\": {\n          \"label\": \" \",\n          \"visible_min\": null,\n          \"visible_max\": null,\n          \"step_interval\": null\n        },\n        \"x_axis\": {\n          \"label\": \"Время, мкс\",\n          \"visible_min\": null,\n          \"visible_max\": null,\n          \"step_interval\": null\n        }\n      },\n      \"y_metrics_max\": {\n        \"red\": null,\n        \"blue\": null,\n        \"green\": null\n      },\n      \"visible_tabs\": [\"NMR Signal\", \"Results Graph\", \"Code\"]\n    },\n    \"log_panel_data\": {\n      \"timestamp\": \"11:01:53\",\n      \"raw_lines\": [\n        \"Дата исследования = 19.09.2025\",\n        \"Время релаксации короткой компоненты = 790.631711 мкс\",\n        \"Время релаксации длинной компоненты = 72.216151 мкс\",\n        \"Амплитуда короткой компоненты = 3.962203 а.е.\",\n        \"Амплитуда длинной компоненты = 0.032312 а.е.\",\n        \"Индекс кристалличности = 0.78824\",\n        \"Протонная плотность = 4.32330\"\n      ],\n      \"structured_log_metrics\": {\n        \"research_date\": \"19.09.2025\",\n        \"relaxation_time_short_component_mks\": 790.631711,\n        \"relaxation_time_long_component_mks\": 72.216151,\n        \"amplitude_short_component_au\": 3.962203,\n        \"amplitude_long_component_au\": 0.032312,\n        \"calculated_crystallinity_index\": 0.78824,\n        \"calculated_proton_density\": 4.32330\n      }\n    },\n    \"status_bar_data\": {\n      \"urtb\": \"3%\",\n      \"adc\": \"0%\",\n      \"base_offset\": \"100% 100%\",\n      \"operation\": \"Чтение буфера A\",\n      \"numeric_values\": \"139.5 0.7823 2032 2094\"\n    },\n    \"caption_data\": {\n      \"illustration_number\": \"№136\",\n      \"full_text\": \"Иллюстрация №136. Изображение одного из ЯМР участков исследуемых штрихов оттиска круглой мастичной печати ООО «Агро-Индустриальная Корпорация «Волго-Дон» в предоставленном на исследование Объекте №2 при третьем проколе.\",\n      \"structured_details\": {\n        \"object_type\": \"штрихов оттиска круглой мастичной печати\",\n        \"source_item\": \"ООО «Агро-Индустриальная Корпорация «Волго-Дон»\",\n        \"investigation_object\": \"Объекте №2\",\n        \"condition\": \"при третьем проколе\"\n      }\n    }\n  },\n  {\n    \"graph_id\": 2,\n    \"header_data\": {\n      \"full_text\": \"Образец № 3 к Заключению № 11366; Индекс кристалличности = 0.78383; Протонная плотность = 4.31742\",\n      \"structured_metrics\": {\n        \"sample_reference\": \"№ 3 к Заключению № 11366\",\n        \"crystallinity_index\": 0.78383,\n        \"proton_density\": 4.31742\n      }\n    },\n    \"graph_statistics\": {\n      \"axes\": {\n        \"y_axis\": {\n          \"label\": \" \",\n          \"visible_min\": null,\n          \"visible_max\": null,\n          \"step_interval\": null\n        },\n        \"x_axis\": {\n          \"label\": \"Время, мкс\",\n          \"visible_min\": null,\n          \"visible_max\": null,\n          \"step_interval\": null\n        }\n      },\n      \"y_metrics_max\": {\n        \"red\": null,\n        \"blue\": null,\n        \"green\": null\n      },\n      \"visible_tabs\": [\"NMR Signal\", \"Results Graph\", \"Code\"]\n    },\n    \"log_panel_data\": {\n      \"timestamp\": \"11:15:18\",\n      \"raw_lines\": [\n        \"Дата исследования = 19.07.2025\",\n        \"Время релаксации короткой компоненты = 1378.6508 мкс\",\n        \"Время релаксации длинной компоненты = 7.52491 мкс\",\n        \"Амплитуда короткой компоненты = 3.9669 а.е.\",\n        \"Амплитуда длинной компоненты = 0.6325 а.е.\",\n        \"Индекс кристалличности = 0.78383\",\n        \"Протонная плотность = 4.31742\"\n      ],\n      \"structured_log_metrics\": {\n        \"research_date\": \"19.07.2025\",\n        \"relaxation_time_short_component_mks\": 1378.6508,\n        \"relaxation_time_long_component_mks\": 7.52491,\n        \"amplitude_short_component_au\": 3.9669,\n        \"amplitude_long_component_au\": 0.6325,\n        \"calculated_crystallinity_index\": 0.78383,\n        \"calculated_proton_density\": 4.31742\n      }\n    },\n    \"status_bar_data\": {\n      \"urtb\": \"3%\",\n      \"adc\": \"0%\",\n      \"base_offset\": \"100% 100%\",\n      \"operation\": \"Чтение буфера A\",\n      \"numeric_values\": \"139.5 0.7823 2032 2094\"\n    },\n    \"caption_data\": {\n      \"illustration_number\": \"№137\",\n      \"full_text\": \"Иллюстрация №137. Изображение одного из ЯМР участков исследуемых штрихов оттиска круглой мастичной печати ПАО «Московский Индустриальный банк» в предоставленном на исследование Объекте №3 при третьем проколе.\",\n      \"structured_details\": {\n        \"object_type\": \"штрихов оттиска круглой мастичной печати\",\n        \"source_item\": \"ПАО «Московский Индустриальный банк»\",\n        \"investigation_object\": \"Объекте №3\",\n        \"condition\": \"при третьем проколе\"\n      }\n    }\n  }\n]\n```",
  "graphs": [
    {
      "page_context": {
        "title": "Приложение №6. Изображения графиков ЯМР участков…"
      },
      "graph_id": 1,
      "header_data": {
        "full_text": "Образец № 3 к Заключению № 11366; Индекс кристалличности = 0.78824; Протонная плотность = 4.32330",
        "structured_metrics": {
          "sample_reference": "№ 3 к Заключению № 11366",
          "crystallinity_index": 0.78824,
          "proton_density": 4.3233
        }
      },
      "graph_statistics": {
        "axes": {
          "y_axis": {
            "label": " ",
            "visible_min": null,
            "visible_max": null,
            "step_interval": null
          },
          "x_axis": {
            "label": "Время, мкс",
            "visible_min": null,
            "visible_max": null,
            "step_interval": null
          }
        },
        "y_metrics_max": {
          "red": null,
          "blue": null,
          "green": null
        },
        "visible_tabs": [
          "NMR Signal",
          "Results Graph",
          "Code"
        ]
      },
      "log_panel_data": {
        "timestamp": "11:01:53",
        "raw_lines": [
          "Дата исследования = 19.09.2025",
          "Время релаксации короткой компоненты = 790.631711 мкс",
          "Время релаксации длинной компоненты = 72.216151 мкс",
          "Амплитуда короткой компоненты = 3.962203 а.е.",
          "Амплитуда длинной компоненты = 0.032312 а.е.",
          "Индекс кристалличности = 0.78824",
          "Протонная плотность = 4.32330"
        ],
        "structured_log_metrics": {
          "research_date": "19.09.2025",
          "relaxation_time_short_component_mks": 790.631711,
          "relaxation_time_long_component_mks": 72.216151,
          "amplitude_short_component_au": 3.962203,
          "amplitude_long_component_au": 0.032312,
          "calculated_crystallinity_index": 0.78824,
          "calculated_proton_density": 4.3233
        }
      },
      "status_bar_data": {
        "urtb": "3%",
        "adc": "0%",
        "base_offset": "100% 100%",
        "operation": "Чтение буфера A",
        "numeric_values": "139.5 0.7823 2032 2094"
      },
      "caption_data": {
        "illustration_number": "№136",
        "full_text": "Иллюстрация №136. Изображение одного из ЯМР участков исследуемых штрихов оттиска круглой мастичной печати ООО «Агро-Индустриальная Корпорация «Волго-Дон» в предоставленном на исследование Объекте №2 при третьем проколе.",
        "structured_details": {
          "object_type": "штрихов оттиска круглой мастичной печати",
          "source_item": "ООО «Агро-Индустриальная Корпорация «Волго-Дон»",
          "investigation_object": "Объекте №2",
          "condition": "при третьем проколе"
        }
      }
    },
    {
      "graph_id": 2,
      "header_data": {
        "full_text": "Образец № 3 к Заключению № 11366; Индекс кристалличности = 0.78383; Протонная плотность = 4.31742",
        "structured_metrics": {
          "sample_reference": "№ 3 к Заключению № 11366",
          "crystallinity_index": 0.78383,
          "proton_density": 4.31742
        }
      },
      "graph_statistics": {
        "axes": {
          "y_axis": {
            "label": " ",
            "visible_min": null,
            "visible_max": null,
            "step_interval": null
          },
          "x_axis": {
            "label": "Время, мкс",
            "visible_min": null,
            "visible_max": null,
            "step_interval": null
          }
        },
        "y_metrics_max": {
          "red": null,
          "blue": null,
          "green": null
        },
        "visible_tabs": [
          "NMR Signal",
          "Results Graph",
          "Code"
        ]
      },
      "log_panel_data": {
        "timestamp": "11:15:18",
        "raw_lines": [
          "Дата исследования = 19.07.2025",
          "Время релаксации короткой компоненты = 1378.6508 мкс",
          "Время релаксации длинной компоненты = 7.52491 мкс",
          "Амплитуда короткой компоненты = 3.9669 а.е.",
          "Амплитуда длинной компоненты = 0.6325 а.е.",
          "Индекс кристалличности = 0.78383",
          "Протонная плотность = 4.31742"
        ],
        "structured_log_metrics": {
          "research_date": "19.07.2025",
          "relaxation_time_short_component_mks": 1378.6508,
          "relaxation_time_long_component_mks": 7.52491,
          "amplitude_short_component_au": 3.9669,
          "amplitude_long_component_au": 0.6325,
          "calculated_crystallinity_index": 0.78383,
          "calculated_proton_density": 4.31742
        }
      },
      "status_bar_data": {
        "urtb": "3%",
        "adc": "0%",
        "base_offset": "100% 100%",
        "operation": "Чтение буфера A",
        "numeric_values": "139.5 0.7823 2032 2094"
      },
      "caption_data": {
        "illustration_number": "№137",
        "full_text": "Иллюстрация №137. Изображение одного из ЯМР участков исследуемых штрихов оттиска круглой мастичной печати ПАО «Московский Индустриальный банк» в предоставленном на исследование Объекте №3 при третьем проколе.",
        "structured_details": {
          "object_type": "штрихов оттиска круглой мастичной печати",
          "source_item": "ПАО «Московский Индустриальный банк»",
          "investigation_object": "Объекте №3",
          "condition": "при третьем проколе"
        }
      }
    }
  ],
  "model": "gpt-4o-2024-08-06",
  "usage": {
    "prompt_tokens": 2025,
    "completion_tokens": 1547,
    "total_tokens": 3572,
    "prompt_tokens_details": {
      "cached_tokens": 0,
      "audio_tokens": 0
    },
    "completion_tokens_details": {
      "reasoning_tokens": 0,
      "audio_tokens": 0,
      "accepted_prediction_tokens": 0,
      "rejected_prediction_tokens": 0
    }
  }
}