{
  "page": 74,
  "content": "```json\n[\n  {\n    \"page_context\": {\n      \"title\": \"Приложение №6. Изображения графиков ЯМР участков…\"\n    },\n    \"graph_id\": 1,\n    \"header_data\": {\n      \"full_text\": \"Образец № 3 к Заключению № 11366; Индекс кристалличности = 0.77577; Протонная плотность = 2.68516\",\n      \"structured_metrics\": {\n        \"sample_reference\": \"№ 3 к Заключению № 11366\",\n        \"crystallinity_index\": 0.77577,\n        \"proton_density\": 2.68516\n      }\n    },\n    \"graph_statistics\": {\n      \"axes\": {\n        \"y_axis\": { \"label\": \"Амплитуда, а. е.\", \"visible_min\": 0, \"visible_max\": 80, \"step_interval\": 10 },\n        \"x_axis\": { \"label\": \"Время, мкс\", \"visible_min\": 0, \"visible_max\": 360, \"step_interval\": 60 }\n      },\n      \"y_metrics_max\": { \"red\": null, \"blue\": null, \"green\": null },\n      \"visible_tabs\": [\"NMR Signal\", \"Results Graph\", \"Code\"]\n    },\n    \"log_panel_data\": {\n      \"timestamp\": \"11:50:23\",\n      \"raw_lines\": [\n        \"Дата исследования - 19.09.2025\",\n        \"Время релаксации короткой компоненты - 161.91068 мкс\",\n        \"Время релаксации длинной компоненты - 846.57006 мкс\",\n        \"Амплитуда короткой компоненты - 7.65821 а.е.\",\n        \"Амплитуда длинной компоненты - 6.94534 а.е.\",\n        \"Индекс кристалличности - 0.77577\",\n        \"Протонная плотность - 2.68516\"\n      ],\n      \"structured_log_metrics\": {\n        \"research_date\": \"19.09.2025\",\n        \"relaxation_time_short_component_mks\": 161.91068,\n        \"relaxation_time_long_component_mks\": 846.57006,\n        \"amplitude_short_component_au\": 7.65821,\n        \"amplitude_long_component_au\": 6.94534,\n        \"calculated_crystallinity_index\": 0.77577,\n        \"calculated_proton_density\": 2.68516\n      }\n    },\n    \"status_bar_data\": {\n      \"urtb\": \"3%\",\n      \"adc\": \"0%\",\n      \"base_offset\": \"100% 100%\",\n      \"operation\": \"Чтение буфера A\",\n      \"numeric_values\": \"135.0 0.7823 2032 2094\"\n    },\n    \"caption_data\": {\n      \"illustration_number\": \"№146\",\n      \"full_text\": \"Изображение одного из ЯМР участков исследуемых штрихов оттиска круглой мастичной печати ООО «Ростовская нива» в предоставленном на исследование Объекте №7 при третьем проколе.\",\n      \"structured_details\": {\n        \"object_type\": \"штрих\",\n        \"source_item\": \"оттиск круглой мастичной печати ООО «Ростовская нива»\",\n        \"investigation_object\": \"Объект №7\",\n        \"condition\": \"при третьем проколе\"\n      }\n    }\n  },\n  {\n    \"graph_id\": 2,\n    \"header_data\": {\n      \"full_text\": \"Образец № 3 к Заключению № 11366; Индекс кристалличности = 0.78255; Протонная плотность = 3.73208\",\n      \"structured_metrics\": {\n        \"sample_reference\": \"№ 3 к Заключению № 11366\",\n        \"crystallinity_index\": 0.78255,\n        \"proton_density\": 3.73208\n      }\n    },\n    \"graph_statistics\": {\n      \"axes\": {\n        \"y_axis\": { \"label\": \"Амплитуда, а. е.\", \"visible_min\": 0, \"visible_max\": 80, \"step_interval\": 10 },\n        \"x_axis\": { \"label\": \"Время, мкс\", \"visible_min\": 0, \"visible_max\": 360, \"step_interval\": 60 }\n      },\n      \"y_metrics_max\": { \"red\": null, \"blue\": null, \"green\": null },\n      \"visible_tabs\": [\"NMR Signal\", \"Results Graph\", \"Code\"]\n    },\n    \"log_panel_data\": {\n      \"timestamp\": \"11:50:34\",\n      \"raw_lines\": [\n        \"Дата исследования - 19.09.2025\",\n        \"Время релаксации короткой компоненты - 133.97264 мкс\",\n        \"Время релаксации длинной компоненты - 957.33975 мкс\",\n        \"Амплитуда короткой компоненты - 4.73517 а.е.\",\n        \"Амплитуда длинной компоненты - 7.28123 а.е.\",\n        \"Индекс кристалличности - 0.78255\",\n        \"Протонная плотность - 3.73208\"\n      ],\n      \"structured_log_metrics\": {\n        \"research_date\": \"19.09.2025\",\n        \"relaxation_time_short_component_mks\": 133.97264,\n        \"relaxation_time_long_component_mks\": 957.33975,\n        \"amplitude_short_component_au\": 4.73517,\n        \"amplitude_long_component_au\": 7.28123,\n        \"calculated_crystallinity_index\": 0.78255,\n        \"calculated_proton_density\": 3.73208\n      }\n    },\n    \"status_bar_data\": {\n      \"urtb\": \"3%\",\n      \"adc\": \"0%\",\n      \"base_offset\": \"100% 100%\",\n      \"operation\": \"Чтение буфера A\",\n      \"numeric_values\": \"135.0 0.7823 2032 2094\"\n    },\n    \"caption_data\": {\n      \"illustration_number\": \"№147\",\n      \"full_text\": \"Изображение одного из ЯМР участков исследуемых штрихов оттиска круглой мастичной печати ПАО «Московский Индустриальный банк» в предоставленном на исследование Объекте №8 при третьем проколе.\",\n      \"structured_details\": {\n        \"object_type\": \"штрих\",\n        \"source_item\": \"оттиск круглой мастичной печати ПАО «Московский Индустриальный банк»\",\n        \"investigation_object\": \"Объект №8\",\n        \"condition\": \"при третьем проколе\"\n      }\n    }\n  }\n]\n```",
  "graphs": [
    {
      "page_context": {
        "title": "Приложение №6. Изображения графиков ЯМР участков…"
      },
      "graph_id": 1,
      "header_data": {
        "full_text": "Образец № 3 к Заключению № 11366; Индекс кристалличности = 0.77577; Протонная плотность = 2.68516",
        "structured_metrics": {
          "sample_reference": "№ 3 к Заключению № 11366",
          "crystallinity_index": 0.77577,
          "proton_density": 2.68516
        }
      },
      "graph_statistics": {
        "axes": {
          "y_axis": {
            "label": "Амплитуда, а. е.",
            "visible_min": 0,
            "visible_max": 80,
            "step_interval": 10
          },
          "x_axis": {
            "label": "Время, мкс",
            "visible_min": 0,
            "visible_max": 360,
            "step_interval": 60
          }
        },
        "y_metrics_max": {
          "red": null,
          "blue": null,
          "green": null
        },
        "visible_tabs": [
          "NMR Signal",
          "Results Graph",
          "Code"
        ]
      },
      "log_panel_data": {
        "timestamp": "11:50:23",
        "raw_lines": [
          "Дата исследования - 19.09.2025",
          "Время релаксации короткой компоненты - 161.91068 мкс",
          "Время релаксации длинной компоненты - 846.57006 мкс",
          "Амплитуда короткой компоненты - 7.65821 а.е.",
          "Амплитуда длинной компоненты - 6.94534 а.е.",
          "Индекс кристалличности - 0.77577",
          "Протонная плотность - 2.68516"
        ],
        "structured_log_metrics": {
          "research_date": "19.09.2025",
          "relaxation_time_short_component_mks": 161.91068,
          "relaxation_time_long_component_mks": 846.57006,
          "amplitude_short_component_au": 7.65821,
          "amplitude_long_component_au": 6.94534,
          "calculated_crystallinity_index": 0.77577,
          "calculated_proton_density": 2.68516
        }
      },
      "status_bar_data": {
        "urtb": "3%",
        "adc": "0%",
        "base_offset": "100% 100%",
        "operation": "Чтение буфера A",
        "numeric_values": "135.0 0.7823 2032 2094"
      },
      "caption_data": {
        "illustration_number": "№146",
        "full_text": "Изображение одного из ЯМР участков исследуемых штрихов оттиска круглой мастичной печати ООО «Ростовская нива» в предоставленном на исследование Объекте №7 при третьем проколе.",
        "structured_details": {
          "object_type": "штрих",
          "source_item": "оттиск круглой мастичной печати ООО «Ростовская нива»",
          "investigation_object": "Объект №7",
          "condition": "при третьем проколе"
        }
      }
    },
    {
      "graph_id": 2,
      "header_data": {
        "full_text": "Образец № 3 к Заключению № 11366; Индекс кристалличности = 0.78255; Протонная плотность = 3.73208",
        "structured_metrics": {
          "sample_reference": "№ 3 к Заключению № 11366",
          "crystallinity_index": 0.78255,
          "proton_density": 3.73208
        }
      },
      "graph_statistics": {
        "axes": {
          "y_axis": {
            "label": "Амплитуда, а. е.",
            "visible_min": 0,
            "visible_max": 80,
            "step_interval": 10
          },
          "x_axis": {
            "label": "Время, мкс",
            "visible_min": 0,
            "visible_max": 360,
            "step_interval": 60
          }
        },
        "y_metrics_max": {
          "red": null,
          "blue": null,
          "green": null
        },
        "visible_tabs": [
          "NMR Signal",
          "Results Graph",
          "Code"
        ]
      },
      "log_panel_data": {
        "timestamp": "11:50:34",
        "raw_lines": [
          "Дата исследования - 19.09.2025",
          "Время релаксации короткой компоненты - 133.97264 мкс",
          "Время релаксации длинной компоненты - 957.33975 мкс",
          "Амплитуда короткой компоненты - 4.73517 а.е.",
          "Амплитуда длинной компоненты - 7.28123 а.е.",
          "Индекс кристалличности - 0.78255",
          "Протонная плотность - 3.73208"
        ],
        "structured_log_metrics": {
          "research_date": "19.09.2025",
          "relaxation_time_short_component_mks": 133.97264,
          "relaxation_time_long_component_mks": 957.33975,
          "amplitude_short_component_au": 4.73517,
          "amplitude_long_component_au": 7.28123,
          "calculated_crystallinity_index": 0.78255,
          "calculated_proton_density": 3.73208
        }
      },
      "status_bar_data": {
        "urtb": "3%",
        "adc": "0%",
        "base_offset": "100% 100%",
        "operation": "Чтение буфера A",
        "numeric_values": "135.0 0.7823 2032 2094"
      },
      "caption_data": {
        "illustration_number": "№147",
        "full_text": "Изображение одного из ЯМР участков исследуемых штрихов оттиска круглой мастичной печати ПАО «Московский Индустриальный банк» в предоставленном на исследование Объекте №8 при третьем проколе.",
        "structured_details": {
          "object_type": "штрих",
          "source_item": "оттиск круглой мастичной печати ПАО «Московский Индустриальный банк»",
          "investigation_object": "Объект №8",
          "condition": "при третьем проколе"
        }
      }
    }
  ],
  "model": "gpt-4o-2024-08-06",
  "usage": {
    "prompt_tokens": 2025,
    "completion_tokens": 1496,
    "total_tokens": 3521,
    "prompt_tokens_details": {
      "cached_tokens": 0,
      "audio_tokens": 0
    },
    "completion_tokens_details": {
      "reasoning_tokens": 0,
      "audio_tokens": 0,
      "accepted_prediction_tokens": 0,
      "rejected_prediction_tokens": 0
    }
  }
}