{
  "page": 9,
  "content": "```json\n[\n  {\n    \"page_context\": {\n      \"title\": \"Приложение № 5. Изображения графиков ЯМР участков исследуемых штрихов\"\n    },\n    \"graph_id\": 1,\n    \"header_data\": {\n      \"full_text\": \"Образец № 1 к Заключению № 11366; Индекс кристалличности = 0.83165; Протонная плотность = 2.53661\",\n      \"structured_metrics\": {\n        \"sample_reference\": \"Образец № 1 к Заключению № 11366\",\n        \"crystallinity_index\": 0.83165,\n        \"proton_density\": 2.53661\n      }\n    },\n    \"graph_statistics\": {\n      \"axes\": {\n        \"y_axis\": {\n          \"label\": \"А/П, усл. ед.\",\n          \"visible_min\": null,\n          \"visible_max\": null,\n          \"step_interval\": null\n        },\n        \"x_axis\": {\n          \"label\": \"Время, мкс\",\n          \"visible_min\": 0,\n          \"visible_max\": 175,\n          \"step_interval\": null\n        }\n      },\n      \"y_metrics_max\": {\n        \"red\": null,\n        \"blue\": null,\n        \"green\": null\n      },\n      \"visible_tabs\": []\n    },\n    \"log_panel_data\": {\n      \"timestamp\": \"\",\n      \"raw_lines\": [\n        \"Дата исследования - 24.06.2023\",\n        \"Время релаксации короткой компоненты = 229.79197 мкс\",\n        \"Время релаксации длинной компоненты = 1390.7845 мкс\",\n        \"Амплитуда короткой компоненты = 7.19456 а.у.\",\n        \"Амплитуда длинной компоненты = 4.94536 а.у.\",\n        \"Индекс кристалличности - 0.83165\",\n        \"Протонная плотность - 2.53661\"\n      ],\n      \"structured_log_metrics\": {\n        \"research_date\": \"24.06.2023\",\n        \"relaxation_time_short_component_mks\": 229.79197,\n        \"relaxation_time_long_component_mks\": 1390.7845,\n        \"amplitude_short_component_au\": 7.19456,\n        \"amplitude_long_component_au\": 4.94536,\n        \"calculated_crystallinity_index\": 0.83165,\n        \"calculated_proton_density\": 2.53661\n      }\n    },\n    \"status_bar_data\": {\n      \"urtb\": \"3%\",\n      \"adc\": \"\",\n      \"base_offset\": \"100% 100%\",\n      \"operation\": \"Чтение буфера A\",\n      \"numeric_values\": \"135.0 782.3 2032 2094\"\n    },\n    \"caption_data\": {\n      \"illustration_number\": \"16\",\n      \"full_text\": \"Иллюстрация №16. Изображение одного из ЯМР участков исследуемых штрихов рукописной подписи от имени Денис В.Н. в предоставленном на исследование Объекте №4 при первом проколе.\",\n      \"structured_details\": {\n        \"object_type\": \"ЯМР участок\",\n        \"source_item\": \"рукописная подпись от имени Денис В.Н.\",\n        \"investigation_object\": \"Объект №4\",\n        \"condition\": \"первый прокол\"\n      }\n    }\n  },\n  {\n    \"graph_id\": 2,\n    \"header_data\": {\n      \"full_text\": \"Образец № 1 к Заключению № 11366; Индекс кристалличности = 0.77038; Протонная плотность = 4.63248\",\n      \"structured_metrics\": {\n        \"sample_reference\": \"Образец № 1 к Заключению № 11366\",\n        \"crystallinity_index\": 0.77038,\n        \"proton_density\": 4.63248\n      }\n    },\n    \"graph_statistics\": {\n      \"axes\": {\n        \"y_axis\": {\n          \"label\": \"А/П, усл. ед.\",\n          \"visible_min\": null,\n          \"visible_max\": null,\n          \"step_interval\": null\n        },\n        \"x_axis\": {\n          \"label\": \"Время, мкс\",\n          \"visible_min\": 0,\n          \"visible_max\": 175,\n          \"step_interval\": null\n        }\n      },\n      \"y_metrics_max\": {\n        \"red\": null,\n        \"blue\": null,\n        \"green\": null\n      },\n      \"visible_tabs\": []\n    },\n    \"log_panel_data\": {\n      \"timestamp\": \"\",\n      \"raw_lines\": [\n        \"Дата исследования - 24.06.2023\",\n        \"Время релаксации короткой компоненты = 132.98402 мкс\",\n        \"Время релаксации длинной компоненты = 1346.5957 мкс\",\n        \"Амплитуда короткой компоненты = 8.97456 а.у.\",\n        \"Амплитуда длинной компоненты = 3.95456 а.у.\",\n        \"Индекс кристалличности - 0.77038\",\n        \"Протонная плотность - 4.63248\"\n      ],\n      \"structured_log_metrics\": {\n        \"research_date\": \"24.06.2023\",\n        \"relaxation_time_short_component_mks\": 132.98402,\n        \"relaxation_time_long_component_mks\": 1346.5957,\n        \"amplitude_short_component_au\": 8.97456,\n        \"amplitude_long_component_au\": 3.95456,\n        \"calculated_crystallinity_index\": 0.77038,\n        \"calculated_proton_density\": 4.63248\n      }\n    },\n    \"status_bar_data\": {\n      \"urtb\": \"3%\",\n      \"adc\": \"\",\n      \"base_offset\": \"100% 100%\",\n      \"operation\": \"Чтение буфера A\",\n      \"numeric_values\": \"135.0 782.3 2032 2094\"\n    },\n    \"caption_data\": {\n      \"illustration_number\": \"17\",\n      \"full_text\": \"Иллюстрация №17. Изображение одного из ЯМР участков исследуемых штрихов рукописной подписи от имени Тисленко Т.Б. в предоставленном на исследование Объекте №4 при первом проколе.\",\n      \"structured_details\": {\n        \"object_type\": \"ЯМР участок\",\n        \"source_item\": \"рукописная подпись от имени Тисленко Т.Б.\",\n        \"investigation_object\": \"Объект №4\",\n        \"condition\": \"первый прокол\"\n      }\n    }\n  }\n]\n```",
  "graphs": [
    {
      "page_context": {
        "title": "Приложение № 5. Изображения графиков ЯМР участков исследуемых штрихов"
      },
      "graph_id": 1,
      "header_data": {
        "full_text": "Образец № 1 к Заключению № 11366; Индекс кристалличности = 0.83165; Протонная плотность = 2.53661",
        "structured_metrics": {
          "sample_reference": "Образец № 1 к Заключению № 11366",
          "crystallinity_index": 0.83165,
          "proton_density": 2.53661
        }
      },
      "graph_statistics": {
        "axes": {
          "y_axis": {
            "label": "А/П, усл. ед.",
            "visible_min": null,
            "visible_max": null,
            "step_interval": null
          },
          "x_axis": {
            "label": "Время, мкс",
            "visible_min": 0,
            "visible_max": 175,
            "step_interval": null
          }
        },
        "y_metrics_max": {
          "red": null,
          "blue": null,
          "green": null
        },
        "visible_tabs": []
      },
      "log_panel_data": {
        "timestamp": "",
        "raw_lines": [
          "Дата исследования - 24.06.2023",
          "Время релаксации короткой компоненты = 229.79197 мкс",
          "Время релаксации длинной компоненты = 1390.7845 мкс",
          "Амплитуда короткой компоненты = 7.19456 а.у.",
          "Амплитуда длинной компоненты = 4.94536 а.у.",
          "Индекс кристалличности - 0.83165",
          "Протонная плотность - 2.53661"
        ],
        "structured_log_metrics": {
          "research_date": "24.06.2023",
          "relaxation_time_short_component_mks": 229.79197,
          "relaxation_time_long_component_mks": 1390.7845,
          "amplitude_short_component_au": 7.19456,
          "amplitude_long_component_au": 4.94536,
          "calculated_crystallinity_index": 0.83165,
          "calculated_proton_density": 2.53661
        }
      },
      "status_bar_data": {
        "urtb": "3%",
        "adc": "",
        "base_offset": "100% 100%",
        "operation": "Чтение буфера A",
        "numeric_values": "135.0 782.3 2032 2094"
      },
      "caption_data": {
        "illustration_number": "16",
        "full_text": "Иллюстрация №16. Изображение одного из ЯМР участков исследуемых штрихов рукописной подписи от имени Денис В.Н. в предоставленном на исследование Объекте №4 при первом проколе.",
        "structured_details": {
          "object_type": "ЯМР участок",
          "source_item": "рукописная подпись от имени Денис В.Н.",
          "investigation_object": "Объект №4",
          "condition": "первый прокол"
        }
      }
    },
    {
      "graph_id": 2,
      "header_data": {
        "full_text": "Образец № 1 к Заключению № 11366; Индекс кристалличности = 0.77038; Протонная плотность = 4.63248",
        "structured_metrics": {
          "sample_reference": "Образец № 1 к Заключению № 11366",
          "crystallinity_index": 0.77038,
          "proton_density": 4.63248
        }
      },
      "graph_statistics": {
        "axes": {
          "y_axis": {
            "label": "А/П, усл. ед.",
            "visible_min": null,
            "visible_max": null,
            "step_interval": null
          },
          "x_axis": {
            "label": "Время, мкс",
            "visible_min": 0,
            "visible_max": 175,
            "step_interval": null
          }
        },
        "y_metrics_max": {
          "red": null,
          "blue": null,
          "green": null
        },
        "visible_tabs": []
      },
      "log_panel_data": {
        "timestamp": "",
        "raw_lines": [
          "Дата исследования - 24.06.2023",
          "Время релаксации короткой компоненты = 132.98402 мкс",
          "Время релаксации длинной компоненты = 1346.5957 мкс",
          "Амплитуда короткой компоненты = 8.97456 а.у.",
          "Амплитуда длинной компоненты = 3.95456 а.у.",
          "Индекс кристалличности - 0.77038",
          "Протонная плотность - 4.63248"
        ],
        "structured_log_metrics": {
          "research_date": "24.06.2023",
          "relaxation_time_short_component_mks": 132.98402,
          "relaxation_time_long_component_mks": 1346.5957,
          "amplitude_short_component_au": 8.97456,
          "amplitude_long_component_au": 3.95456,
          "calculated_crystallinity_index": 0.77038,
          "calculated_proton_density": 4.63248
        }
      },
      "status_bar_data": {
        "urtb": "3%",
        "adc": "",
        "base_offset": "100% 100%",
        "operation": "Чтение буфера A",
        "numeric_values": "135.0 782.3 2032 2094"
      },
      "caption_data": {
        "illustration_number": "17",
        "full_text": "Иллюстрация №17. Изображение одного из ЯМР участков исследуемых штрихов рукописной подписи от имени Тисленко Т.Б. в предоставленном на исследование Объекте №4 при первом проколе.",
        "structured_details": {
          "object_type": "ЯМР участок",
          "source_item": "рукописная подпись от имени Тисленко Т.Б.",
          "investigation_object": "Объект №4",
          "condition": "первый прокол"
        }
      }
    }
  ],
  "model": "gpt-4o-2024-08-06",
  "usage": {
    "prompt_tokens": 2025,
    "completion_tokens": 1494,
    "total_tokens": 3519,
    "prompt_tokens_details": {
      "cached_tokens": 0,
      "audio_tokens": 0
    },
    "completion_tokens_details": {
      "reasoning_tokens": 0,
      "audio_tokens": 0,
      "accepted_prediction_tokens": 0,
      "rejected_prediction_tokens": 0
    }
  }
}