{
  "page": 30,
  "content": "```json\n[\n  {\n    \"page_context\": {\n      \"title\": \"Приложение №6. Изображения графиков ЯМР участков…\"\n    },\n    \"graph_id\": 1,\n    \"header_data\": {\n      \"full_text\": \"Образец N 1 к Заключению № 11366; Индекс кристалличности = 0.81262; Протонная плотность = 4.45701\",\n      \"structured_metrics\": {\n        \"sample_reference\": \"Образец N 1 к Заключению № 11366\",\n        \"crystallinity_index\": 0.81262,\n        \"proton_density\": 4.45701\n      }\n    },\n    \"graph_statistics\": {\n      \"axes\": {\n        \"y_axis\": {\n          \"label\": \"Интенсивность, % а.е.\",\n          \"visible_min\": -5.0,\n          \"visible_max\": 50.0,\n          \"step_interval\": null\n        },\n        \"x_axis\": {\n          \"label\": \"Время, мкс\",\n          \"visible_min\": 0.0,\n          \"visible_max\": 400.0,\n          \"step_interval\": null\n        }\n      },\n      \"y_metrics_max\": {\n        \"red\": null,\n        \"blue\": null,\n        \"green\": null\n      },\n      \"visible_tabs\": [\"NMR Signal\", \"Results Graph\", \"Code\"]\n    },\n    \"log_panel_data\": {\n      \"timestamp\": \"11:24:28\",\n      \"raw_lines\": [\n        \"Дата исследования - 24.06.2023\",\n        \"Время релаксации короткой компоненты - 82.47929 мкс\",\n        \"Время релаксации длинной компоненты - 193.2651 мкс\",\n        \"Амплитуда короткой компоненты - 1.1973 а.е.\",\n        \"Амплитуда длинной компоненты - 2.9571 а.е.\",\n        \"Индекс кристалличности - 0.7634\",\n        \"Протонная плотность - 4.45701\"\n      ],\n      \"structured_log_metrics\": {\n        \"research_date\": \"24.06.2023\",\n        \"relaxation_time_short_component_mks\": 82.47929,\n        \"relaxation_time_long_component_mks\": 193.2651,\n        \"amplitude_short_component_au\": 1.1973,\n        \"amplitude_long_component_au\": 2.9571,\n        \"calculated_crystallinity_index\": 0.7634,\n        \"calculated_proton_density\": 4.45701\n      }\n    },\n    \"status_bar_data\": {\n      \"urtb\": \"3%\",\n      \"adc\": \"0%\",\n      \"base_offset\": \"100% 100%\",\n      \"operation\": \"Чтение буфера A\",\n      \"numeric_values\": \"135.0 7823 2094\"\n    },\n    \"caption_data\": {\n      \"illustration_number\": \"№58\",\n      \"full_text\": \"Иллюстрация №58. Изображение одного из ЯМР участков исследуемых штрихов отпечатка круглой мастичной печати ООО «Агро-Индустриальная Корпорация «Волго-Дон» в предоставленном на исследование Объекте №2 при первом проколе.\",\n      \"structured_details\": {\n        \"object_type\": \"штрих\",\n        \"source_item\": \"ООО «Агро-Индустриальная Корпорация «Волго-Дон»\",\n        \"investigation_object\": \"Объект №2\",\n        \"condition\": \"первый прокол\"\n      }\n    }\n  },\n  {\n    \"graph_id\": 2,\n    \"header_data\": {\n      \"full_text\": \"Образец N 1 к Заключению № 11366; Индекс кристалличности = 0.80761; Протонная плотность = 4.45095\",\n      \"structured_metrics\": {\n        \"sample_reference\": \"Образец N 1 к Заключению № 11366\",\n        \"crystallinity_index\": 0.80761,\n        \"proton_density\": 4.45095\n      }\n    },\n    \"graph_statistics\": {\n      \"axes\": {\n        \"y_axis\": {\n          \"label\": \"Интенсивность, % а.е.\",\n          \"visible_min\": -5.0,\n          \"visible_max\": 40.0,\n          \"step_interval\": null\n        },\n        \"x_axis\": {\n          \"label\": \"Время, мкс\",\n          \"visible_min\": 0.0,\n          \"visible_max\": 400.0,\n          \"step_interval\": null\n        }\n      },\n      \"y_metrics_max\": {\n        \"red\": null,\n        \"blue\": null,\n        \"green\": null\n      },\n      \"visible_tabs\": [\"NMR Signal\", \"Results Graph\", \"Code\"]\n    },\n    \"log_panel_data\": {\n      \"timestamp\": \"11:28:27\",\n      \"raw_lines\": [\n        \"Дата исследования - 24.06.2023\",\n        \"Время релаксации короткой компоненты - 153.66975 мкс\",\n        \"Время релаксации длинной компоненты - 296.9485 мкс\",\n        \"Амплитуда короткой компоненты - 3.2954 а.е.\",\n        \"Амплитуда длинной компоненты - 8.221 а.е.\",\n        \"Индекс кристалличности - 0.7486\",\n        \"Протонная плотность - 4.45095\"\n      ],\n      \"structured_log_metrics\": {\n        \"research_date\": \"24.06.2023\",\n        \"relaxation_time_short_component_mks\": 153.66975,\n        \"relaxation_time_long_component_mks\": 296.9485,\n        \"amplitude_short_component_au\": 3.2954,\n        \"amplitude_long_component_au\": 8.221,\n        \"calculated_crystallinity_index\": 0.7486,\n        \"calculated_proton_density\": 4.45095\n      }\n    },\n    \"status_bar_data\": {\n      \"urtb\": \"3%\",\n      \"adc\": \"0%\",\n      \"base_offset\": \"100% 100%\",\n      \"operation\": \"Чтение буфера A\",\n      \"numeric_values\": \"135.0 7823 2094\"\n    },\n    \"caption_data\": {\n      \"illustration_number\": \"№59\",\n      \"full_text\": \"Иллюстрация №59. Изображение одного из ЯМР участков исследуемых штрихов отпечатка круглой мастичной печати ПАО «Московский Индустриальный банк» в предоставленном на исследование Объекте №3 при первом проколе.\",\n      \"structured_details\": {\n        \"object_type\": \"штрих\",\n        \"source_item\": \"ПАО «Московский Индустриальный банк»\",\n        \"investigation_object\": \"Объект №3\",\n        \"condition\": \"первый прокол\"\n      }\n    }\n  }\n]\n```",
  "graphs": [
    {
      "page_context": {
        "title": "Приложение №6. Изображения графиков ЯМР участков…"
      },
      "graph_id": 1,
      "header_data": {
        "full_text": "Образец N 1 к Заключению № 11366; Индекс кристалличности = 0.81262; Протонная плотность = 4.45701",
        "structured_metrics": {
          "sample_reference": "Образец N 1 к Заключению № 11366",
          "crystallinity_index": 0.81262,
          "proton_density": 4.45701
        }
      },
      "graph_statistics": {
        "axes": {
          "y_axis": {
            "label": "Интенсивность, % а.е.",
            "visible_min": -5.0,
            "visible_max": 50.0,
            "step_interval": null
          },
          "x_axis": {
            "label": "Время, мкс",
            "visible_min": 0.0,
            "visible_max": 400.0,
            "step_interval": null
          }
        },
        "y_metrics_max": {
          "red": null,
          "blue": null,
          "green": null
        },
        "visible_tabs": [
          "NMR Signal",
          "Results Graph",
          "Code"
        ]
      },
      "log_panel_data": {
        "timestamp": "11:24:28",
        "raw_lines": [
          "Дата исследования - 24.06.2023",
          "Время релаксации короткой компоненты - 82.47929 мкс",
          "Время релаксации длинной компоненты - 193.2651 мкс",
          "Амплитуда короткой компоненты - 1.1973 а.е.",
          "Амплитуда длинной компоненты - 2.9571 а.е.",
          "Индекс кристалличности - 0.7634",
          "Протонная плотность - 4.45701"
        ],
        "structured_log_metrics": {
          "research_date": "24.06.2023",
          "relaxation_time_short_component_mks": 82.47929,
          "relaxation_time_long_component_mks": 193.2651,
          "amplitude_short_component_au": 1.1973,
          "amplitude_long_component_au": 2.9571,
          "calculated_crystallinity_index": 0.7634,
          "calculated_proton_density": 4.45701
        }
      },
      "status_bar_data": {
        "urtb": "3%",
        "adc": "0%",
        "base_offset": "100% 100%",
        "operation": "Чтение буфера A",
        "numeric_values": "135.0 7823 2094"
      },
      "caption_data": {
        "illustration_number": "№58",
        "full_text": "Иллюстрация №58. Изображение одного из ЯМР участков исследуемых штрихов отпечатка круглой мастичной печати ООО «Агро-Индустриальная Корпорация «Волго-Дон» в предоставленном на исследование Объекте №2 при первом проколе.",
        "structured_details": {
          "object_type": "штрих",
          "source_item": "ООО «Агро-Индустриальная Корпорация «Волго-Дон»",
          "investigation_object": "Объект №2",
          "condition": "первый прокол"
        }
      }
    },
    {
      "graph_id": 2,
      "header_data": {
        "full_text": "Образец N 1 к Заключению № 11366; Индекс кристалличности = 0.80761; Протонная плотность = 4.45095",
        "structured_metrics": {
          "sample_reference": "Образец N 1 к Заключению № 11366",
          "crystallinity_index": 0.80761,
          "proton_density": 4.45095
        }
      },
      "graph_statistics": {
        "axes": {
          "y_axis": {
            "label": "Интенсивность, % а.е.",
            "visible_min": -5.0,
            "visible_max": 40.0,
            "step_interval": null
          },
          "x_axis": {
            "label": "Время, мкс",
            "visible_min": 0.0,
            "visible_max": 400.0,
            "step_interval": null
          }
        },
        "y_metrics_max": {
          "red": null,
          "blue": null,
          "green": null
        },
        "visible_tabs": [
          "NMR Signal",
          "Results Graph",
          "Code"
        ]
      },
      "log_panel_data": {
        "timestamp": "11:28:27",
        "raw_lines": [
          "Дата исследования - 24.06.2023",
          "Время релаксации короткой компоненты - 153.66975 мкс",
          "Время релаксации длинной компоненты - 296.9485 мкс",
          "Амплитуда короткой компоненты - 3.2954 а.е.",
          "Амплитуда длинной компоненты - 8.221 а.е.",
          "Индекс кристалличности - 0.7486",
          "Протонная плотность - 4.45095"
        ],
        "structured_log_metrics": {
          "research_date": "24.06.2023",
          "relaxation_time_short_component_mks": 153.66975,
          "relaxation_time_long_component_mks": 296.9485,
          "amplitude_short_component_au": 3.2954,
          "amplitude_long_component_au": 8.221,
          "calculated_crystallinity_index": 0.7486,
          "calculated_proton_density": 4.45095
        }
      },
      "status_bar_data": {
        "urtb": "3%",
        "adc": "0%",
        "base_offset": "100% 100%",
        "operation": "Чтение буфера A",
        "numeric_values": "135.0 7823 2094"
      },
      "caption_data": {
        "illustration_number": "№59",
        "full_text": "Иллюстрация №59. Изображение одного из ЯМР участков исследуемых штрихов отпечатка круглой мастичной печати ПАО «Московский Индустриальный банк» в предоставленном на исследование Объекте №3 при первом проколе.",
        "structured_details": {
          "object_type": "штрих",
          "source_item": "ПАО «Московский Индустриальный банк»",
          "investigation_object": "Объект №3",
          "condition": "первый прокол"
        }
      }
    }
  ],
  "model": "gpt-4o-2024-08-06",
  "usage": {
    "prompt_tokens": 2025,
    "completion_tokens": 1555,
    "total_tokens": 3580,
    "prompt_tokens_details": {
      "cached_tokens": 0,
      "audio_tokens": 0
    },
    "completion_tokens_details": {
      "reasoning_tokens": 0,
      "audio_tokens": 0,
      "accepted_prediction_tokens": 0,
      "rejected_prediction_tokens": 0
    }
  }
}