{
  "page": 36,
  "content": "```json\n[\n  {\n    \"page_context\": {\n      \"title\": \"Приложение №6. Изображения графиков ЯМР участков\"\n    },\n    \"graph_id\": 1,\n    \"header_data\": {\n      \"full_text\": \"Образец № 1 к Заключению № 11366; Индекс кристалличности = 0.83288; Протонная плотность = 3.40336\",\n      \"structured_metrics\": {\n        \"sample_reference\": \"Образец № 1 к Заключению № 11366\",\n        \"crystallinity_index\": 0.83288,\n        \"proton_density\": 3.40336\n      }\n    },\n    \"graph_statistics\": {\n      \"axes\": {\n        \"y_axis\": {\n          \"label\": \"Интенсивность, a.u.\",\n          \"visible_min\": null,\n          \"visible_max\": 60,\n          \"step_interval\": null\n        },\n        \"x_axis\": {\n          \"label\": \"Время, мкс\",\n          \"visible_min\": null,\n          \"visible_max\": 250,\n          \"step_interval\": null\n        }\n      },\n      \"y_metrics_max\": {\n        \"red\": null,\n        \"blue\": null,\n        \"green\": null\n      },\n      \"visible_tabs\": []\n    },\n    \"log_panel_data\": {\n      \"timestamp\": \"12:11:04\",\n      \"raw_lines\": [\n        \"12:11:04 Дата исследования = 24.06.2025\",\n        \"12:11:04 Время релаксации короткой компоненты = 190.26569 мкс\",\n        \"12:11:04 Время релаксации длинной компоненты = 1233.5213 мкс\",\n        \"12:11:05 Амплитуда короткой компоненты = 2.35768 a.u.\",\n        \"12:11:05 Амплитуда длинной компоненты = 3.23558 a.u.\",\n        \"12:11:05 Индекс кристалличности = 0.83288\",\n        \"12:11:05 Протонная плотность = 3.40336\"\n      ],\n      \"structured_log_metrics\": {\n        \"research_date\": \"24.06.2025\",\n        \"relaxation_time_short_component_mks\": 190.26569,\n        \"relaxation_time_long_component_mks\": 1233.5213,\n        \"amplitude_short_component_au\": 2.35768,\n        \"amplitude_long_component_au\": 3.23558,\n        \"calculated_crystallinity_index\": 0.83288,\n        \"calculated_proton_density\": 3.40336\n      }\n    },\n    \"status_bar_data\": {\n      \"urtb\": \"3%\",\n      \"adc\": \"\",\n      \"base_offset\": \"100% 100%\",\n      \"operation\": \"Чтение буфера A\",\n      \"numeric_values\": \"135.0 0.7823 2032 2094\"\n    },\n    \"caption_data\": {\n      \"illustration_number\": \"№70\",\n      \"full_text\": \"Иллюстрация №70. Изображение одного из ЯМР участков исследуемых штрихов отпечатка круглой мастичной печати ООО «Рословская нива» в предоставленном на исследование Объекте №8 при первом проколе.\",\n      \"structured_details\": {\n        \"object_type\": \"ЯМР участок\",\n        \"source_item\": \"ООО «Рословская нива»\",\n        \"investigation_object\": \"Объект №8\",\n        \"condition\": \"первый прокол\"\n      }\n    }\n  },\n  {\n    \"graph_id\": 2,\n    \"header_data\": {\n      \"full_text\": \"Образец № 1 к Заключению № 11366; Индекс кристалличности = 0.82408; Протонная плотность = 3.90727\",\n      \"structured_metrics\": {\n        \"sample_reference\": \"Образец № 1 к Заключению № 11366\",\n        \"crystallinity_index\": 0.82408,\n        \"proton_density\": 3.90727\n      }\n    },\n    \"graph_statistics\": {\n      \"axes\": {\n        \"y_axis\": {\n          \"label\": \"Интенсивность, a.u.\",\n          \"visible_min\": null,\n          \"visible_max\": 60,\n          \"step_interval\": null\n        },\n        \"x_axis\": {\n          \"label\": \"Время, мкс\",\n          \"visible_min\": null,\n          \"visible_max\": 250,\n          \"step_interval\": null\n        }\n      },\n      \"y_metrics_max\": {\n        \"red\": null,\n        \"blue\": null,\n        \"green\": null\n      },\n      \"visible_tabs\": []\n    },\n    \"log_panel_data\": {\n      \"timestamp\": \"12:11:05\",\n      \"raw_lines\": [\n        \"12:11:05 Дата исследования = 24.06.2025\",\n        \"12:11:05 Время релаксации короткой компоненты = 190.24385 мкс\",\n        \"12:11:05 Время релаксации длинной компоненты = 1277.6775 мкс\",\n        \"12:11:05 Амплитуда короткой компоненты = 3.17317 a.u.\",\n        \"12:11:05 Амплитуда длинной компоненты = 3.16539 a.u.\",\n        \"12:11:05 Индекс кристалличности = 0.82408\",\n        \"12:11:05 Протонная плотность = 3.90727\"\n      ],\n      \"structured_log_metrics\": {\n        \"research_date\": \"24.06.2025\",\n        \"relaxation_time_short_component_mks\": 190.24385,\n        \"relaxation_time_long_component_mks\": 1277.6775,\n        \"amplitude_short_component_au\": 3.17317,\n        \"amplitude_long_component_au\": 3.16539,\n        \"calculated_crystallinity_index\": 0.82408,\n        \"calculated_proton_density\": 3.90727\n      }\n    },\n    \"status_bar_data\": {\n      \"urtb\": \"3%\",\n      \"adc\": \"\",\n      \"base_offset\": \"100% 100%\",\n      \"operation\": \"Чтение буфера A\",\n      \"numeric_values\": \"135.0 0.7823 2032 2094\"\n    },\n    \"caption_data\": {\n      \"illustration_number\": \"№71\",\n      \"full_text\": \"Иллюстрация №71. Изображение одного из ЯМР участков исследуемых штрихов отпечатка круглой мастичной печати ПАО «Московский Индустриальный банк» в предоставленном на исследование Объекте №9 при первом проколе.\",\n      \"structured_details\": {\n        \"object_type\": \"ЯМР участок\",\n        \"source_item\": \"ПАО «Московский Индустриальный банк»\",\n        \"investigation_object\": \"Объект №9\",\n        \"condition\": \"первый прокол\"\n      }\n    }\n  }\n]\n```",
  "graphs": [
    {
      "page_context": {
        "title": "Приложение №6. Изображения графиков ЯМР участков"
      },
      "graph_id": 1,
      "header_data": {
        "full_text": "Образец № 1 к Заключению № 11366; Индекс кристалличности = 0.83288; Протонная плотность = 3.40336",
        "structured_metrics": {
          "sample_reference": "Образец № 1 к Заключению № 11366",
          "crystallinity_index": 0.83288,
          "proton_density": 3.40336
        }
      },
      "graph_statistics": {
        "axes": {
          "y_axis": {
            "label": "Интенсивность, a.u.",
            "visible_min": null,
            "visible_max": 60,
            "step_interval": null
          },
          "x_axis": {
            "label": "Время, мкс",
            "visible_min": null,
            "visible_max": 250,
            "step_interval": null
          }
        },
        "y_metrics_max": {
          "red": null,
          "blue": null,
          "green": null
        },
        "visible_tabs": []
      },
      "log_panel_data": {
        "timestamp": "12:11:04",
        "raw_lines": [
          "12:11:04 Дата исследования = 24.06.2025",
          "12:11:04 Время релаксации короткой компоненты = 190.26569 мкс",
          "12:11:04 Время релаксации длинной компоненты = 1233.5213 мкс",
          "12:11:05 Амплитуда короткой компоненты = 2.35768 a.u.",
          "12:11:05 Амплитуда длинной компоненты = 3.23558 a.u.",
          "12:11:05 Индекс кристалличности = 0.83288",
          "12:11:05 Протонная плотность = 3.40336"
        ],
        "structured_log_metrics": {
          "research_date": "24.06.2025",
          "relaxation_time_short_component_mks": 190.26569,
          "relaxation_time_long_component_mks": 1233.5213,
          "amplitude_short_component_au": 2.35768,
          "amplitude_long_component_au": 3.23558,
          "calculated_crystallinity_index": 0.83288,
          "calculated_proton_density": 3.40336
        }
      },
      "status_bar_data": {
        "urtb": "3%",
        "adc": "",
        "base_offset": "100% 100%",
        "operation": "Чтение буфера A",
        "numeric_values": "135.0 0.7823 2032 2094"
      },
      "caption_data": {
        "illustration_number": "№70",
        "full_text": "Иллюстрация №70. Изображение одного из ЯМР участков исследуемых штрихов отпечатка круглой мастичной печати ООО «Рословская нива» в предоставленном на исследование Объекте №8 при первом проколе.",
        "structured_details": {
          "object_type": "ЯМР участок",
          "source_item": "ООО «Рословская нива»",
          "investigation_object": "Объект №8",
          "condition": "первый прокол"
        }
      }
    },
    {
      "graph_id": 2,
      "header_data": {
        "full_text": "Образец № 1 к Заключению № 11366; Индекс кристалличности = 0.82408; Протонная плотность = 3.90727",
        "structured_metrics": {
          "sample_reference": "Образец № 1 к Заключению № 11366",
          "crystallinity_index": 0.82408,
          "proton_density": 3.90727
        }
      },
      "graph_statistics": {
        "axes": {
          "y_axis": {
            "label": "Интенсивность, a.u.",
            "visible_min": null,
            "visible_max": 60,
            "step_interval": null
          },
          "x_axis": {
            "label": "Время, мкс",
            "visible_min": null,
            "visible_max": 250,
            "step_interval": null
          }
        },
        "y_metrics_max": {
          "red": null,
          "blue": null,
          "green": null
        },
        "visible_tabs": []
      },
      "log_panel_data": {
        "timestamp": "12:11:05",
        "raw_lines": [
          "12:11:05 Дата исследования = 24.06.2025",
          "12:11:05 Время релаксации короткой компоненты = 190.24385 мкс",
          "12:11:05 Время релаксации длинной компоненты = 1277.6775 мкс",
          "12:11:05 Амплитуда короткой компоненты = 3.17317 a.u.",
          "12:11:05 Амплитуда длинной компоненты = 3.16539 a.u.",
          "12:11:05 Индекс кристалличности = 0.82408",
          "12:11:05 Протонная плотность = 3.90727"
        ],
        "structured_log_metrics": {
          "research_date": "24.06.2025",
          "relaxation_time_short_component_mks": 190.24385,
          "relaxation_time_long_component_mks": 1277.6775,
          "amplitude_short_component_au": 3.17317,
          "amplitude_long_component_au": 3.16539,
          "calculated_crystallinity_index": 0.82408,
          "calculated_proton_density": 3.90727
        }
      },
      "status_bar_data": {
        "urtb": "3%",
        "adc": "",
        "base_offset": "100% 100%",
        "operation": "Чтение буфера A",
        "numeric_values": "135.0 0.7823 2032 2094"
      },
      "caption_data": {
        "illustration_number": "№71",
        "full_text": "Иллюстрация №71. Изображение одного из ЯМР участков исследуемых штрихов отпечатка круглой мастичной печати ПАО «Московский Индустриальный банк» в предоставленном на исследование Объекте №9 при первом проколе.",
        "structured_details": {
          "object_type": "ЯМР участок",
          "source_item": "ПАО «Московский Индустриальный банк»",
          "investigation_object": "Объект №9",
          "condition": "первый прокол"
        }
      }
    }
  ],
  "model": "gpt-4o-2024-08-06",
  "usage": {
    "prompt_tokens": 2025,
    "completion_tokens": 1576,
    "total_tokens": 3601,
    "prompt_tokens_details": {
      "cached_tokens": 0,
      "audio_tokens": 0
    },
    "completion_tokens_details": {
      "reasoning_tokens": 0,
      "audio_tokens": 0,
      "accepted_prediction_tokens": 0,
      "rejected_prediction_tokens": 0
    }
  }
}