{
  "page": 38,
  "content": "```json\n[\n  {\n    \"graph_id\": 1,\n    \"header_data\": {\n      \"full_text\": \"Образец № 1 к Заключению № 11366; Индекс кристалличности = 0.84582; Протонная плотность = 0.15838\",\n      \"structured_metrics\": {\n        \"sample_reference\": \"Образец № 1 к Заключению № 11366\",\n        \"crystallinity_index\": 0.84582,\n        \"proton_density\": 0.15838\n      }\n    },\n    \"graph_statistics\": {\n      \"axes\": {\n        \"y_axis\": {\n          \"label\": \"Интенсивность, %\",\n          \"visible_min\": 0,\n          \"visible_max\": 25,\n          \"step_interval\": 5\n        },\n        \"x_axis\": {\n          \"label\": \"Время, мкс\",\n          \"visible_min\": 0,\n          \"visible_max\": 65,\n          \"step_interval\": 10\n        }\n      },\n      \"y_metrics_max\": {\n        \"red\": 20,\n        \"blue\": 15,\n        \"green\": 18\n      },\n      \"visible_tabs\": [\"NMR Signal\", \"Results Graph\", \"Code\"]\n    },\n    \"caption_data\": {\n      \"illustration_number\": \"№75\",\n      \"full_text\": \"Иллюстрация №75. Изображение одного из ЯМР участков исследуемых штрихов оттиска круглой мастичной печати ПАО «Московский Индустриальный банк» в предоставленном на исследование Объекте №11 при первом проколе.\",\n      \"structured_details\": {\n        \"object_type\": \"ЯМР участок исследуемых штрихов\",\n        \"source_item\": \"оттиск круглой мастичной печати ПАО «Московский Индустриальный банк»\",\n        \"investigation_object\": \"Объект №11\",\n        \"condition\": \"при первом проколе\"\n      }\n    }\n  },\n  {\n    \"graph_id\": 2,\n    \"header_data\": {\n      \"full_text\": \"Образец № 1 к Заключению № 11366; Индекс кристалличности = 0.81858; Протонная плотность = 0.28760\",\n      \"structured_metrics\": {\n        \"sample_reference\": \"Образец № 1 к Заключению № 11366\",\n        \"crystallinity_index\": 0.81858,\n        \"proton_density\": 0.28760\n      }\n    },\n    \"graph_statistics\": {\n      \"axes\": {\n        \"y_axis\": {\n          \"label\": \"Интенсивность, %\",\n          \"visible_min\": -75,\n          \"visible_max\": 45,\n          \"step_interval\": 15\n        },\n        \"x_axis\": {\n          \"label\": \"Время, мкс\",\n          \"visible_min\": 0,\n          \"visible_max\": 115,\n          \"step_interval\": 5\n        }\n      },\n      \"y_metrics_max\": {\n        \"red\": 40,\n        \"blue\": 35,\n        \"green\": 45\n      },\n      \"visible_tabs\": [\"NMR Signal\", \"Results Graph\", \"Code\"]\n    },\n    \"caption_data\": {\n      \"illustration_number\": \"№76\",\n      \"full_text\": \"Иллюстрация №76. Изображение одного из ЯМР участков исследуемых штрихов оттиска круглой мастичной печати ООО «Агро-Индустриальная Корпорация «Волго-Дон» в предоставленном на исследование Объекте №11 при первом проколе.\",\n      \"structured_details\": {\n        \"object_type\": \"ЯМР участок исследуемых штрихов\",\n        \"source_item\": \"оттиск круглой мастичной печати ООО «Агро-Индустриальная Корпорация «Волго-Дон»\",\n        \"investigation_object\": \"Объект №11\",\n        \"condition\": \"при первом проколе\"\n      }\n    }\n  }\n]\n```",
  "graphs": [
    {
      "graph_id": 1,
      "header_data": {
        "full_text": "Образец № 1 к Заключению № 11366; Индекс кристалличности = 0.84582; Протонная плотность = 0.15838",
        "structured_metrics": {
          "sample_reference": "Образец № 1 к Заключению № 11366",
          "crystallinity_index": 0.84582,
          "proton_density": 0.15838
        }
      },
      "graph_statistics": {
        "axes": {
          "y_axis": {
            "label": "Интенсивность, %",
            "visible_min": 0,
            "visible_max": 25,
            "step_interval": 5
          },
          "x_axis": {
            "label": "Время, мкс",
            "visible_min": 0,
            "visible_max": 65,
            "step_interval": 10
          }
        },
        "y_metrics_max": {
          "red": 20,
          "blue": 15,
          "green": 18
        },
        "visible_tabs": [
          "NMR Signal",
          "Results Graph",
          "Code"
        ]
      },
      "caption_data": {
        "illustration_number": "№75",
        "full_text": "Иллюстрация №75. Изображение одного из ЯМР участков исследуемых штрихов оттиска круглой мастичной печати ПАО «Московский Индустриальный банк» в предоставленном на исследование Объекте №11 при первом проколе.",
        "structured_details": {
          "object_type": "ЯМР участок исследуемых штрихов",
          "source_item": "оттиск круглой мастичной печати ПАО «Московский Индустриальный банк»",
          "investigation_object": "Объект №11",
          "condition": "при первом проколе"
        }
      }
    },
    {
      "graph_id": 2,
      "header_data": {
        "full_text": "Образец № 1 к Заключению № 11366; Индекс кристалличности = 0.81858; Протонная плотность = 0.28760",
        "structured_metrics": {
          "sample_reference": "Образец № 1 к Заключению № 11366",
          "crystallinity_index": 0.81858,
          "proton_density": 0.2876
        }
      },
      "graph_statistics": {
        "axes": {
          "y_axis": {
            "label": "Интенсивность, %",
            "visible_min": -75,
            "visible_max": 45,
            "step_interval": 15
          },
          "x_axis": {
            "label": "Время, мкс",
            "visible_min": 0,
            "visible_max": 115,
            "step_interval": 5
          }
        },
        "y_metrics_max": {
          "red": 40,
          "blue": 35,
          "green": 45
        },
        "visible_tabs": [
          "NMR Signal",
          "Results Graph",
          "Code"
        ]
      },
      "caption_data": {
        "illustration_number": "№76",
        "full_text": "Иллюстрация №76. Изображение одного из ЯМР участков исследуемых штрихов оттиска круглой мастичной печати ООО «Агро-Индустриальная Корпорация «Волго-Дон» в предоставленном на исследование Объекте №11 при первом проколе.",
        "structured_details": {
          "object_type": "ЯМР участок исследуемых штрихов",
          "source_item": "оттиск круглой мастичной печати ООО «Агро-Индустриальная Корпорация «Волго-Дон»",
          "investigation_object": "Объект №11",
          "condition": "при первом проколе"
        }
      }
    }
  ],
  "model": "gpt-4o-2024-08-06",
  "usage": {
    "prompt_tokens": 2055,
    "completion_tokens": 884,
    "total_tokens": 2939,
    "prompt_tokens_details": {
      "cached_tokens": 0,
      "audio_tokens": 0
    },
    "completion_tokens_details": {
      "reasoning_tokens": 0,
      "audio_tokens": 0,
      "accepted_prediction_tokens": 0,
      "rejected_prediction_tokens": 0
    }
  }
}