{
  "page": 60,
  "content": "```json\n[\n  {\n    \"graph_id\": 1,\n    \"header_data\": {\n      \"full_text\": \"Образец № 3 к Заключению № 11366; Индекс кристалличности = 0.77281; Протонная плотность = 0.44177\",\n      \"structured_metrics\": {\n        \"sample_reference\": \"Образец № 3 к Заключению № 11366\",\n        \"crystallinity_index\": 0.77281,\n        \"proton_density\": 0.44177\n      }\n    },\n    \"graph_statistics\": {\n      \"axes\": {\n        \"y_axis\": {\n          \"label\": \"Интенсивность, %\",\n          \"visible_min\": 0,\n          \"visible_max\": 44,\n          \"step_interval\": null\n        },\n        \"x_axis\": {\n          \"label\": \"Время, мкс\",\n          \"visible_min\": 0,\n          \"visible_max\": 165,\n          \"step_interval\": 15\n        }\n      },\n      \"y_metrics_max\": {\n        \"red\": 40,\n        \"blue\": 42,\n        \"green\": 36\n      },\n      \"visible_tabs\": [\"NMR Signal\", \"Results Graph\", \"Code\"]\n    },\n    \"caption_data\": {\n      \"illustration_number\": \"№119\",\n      \"full_text\": \"Иллюстрация №119. Изображение одного из ЯМР участков исследуемых штрихов рукописной подписи нераспознанного лица №2 в предоставленном на исследование Объекте №9 при третьем проколе.\",\n      \"structured_details\": {\n        \"object_type\": \"ЯМР участок исследуемых штрихов\",\n        \"source_item\": \"\",\n        \"investigation_object\": \"Объект №9\",\n        \"condition\": \"при третьем проколе\"\n      }\n    }\n  },\n  {\n    \"graph_id\": 2,\n    \"header_data\": {\n      \"full_text\": \"Образец № 3 к Заключению № 11366; Индекс кристалличности = 0.71987; Протонная плотность = 0.53140\",\n      \"structured_metrics\": {\n        \"sample_reference\": \"Образец № 3 к Заключению № 11366\",\n        \"crystallinity_index\": 0.71987,\n        \"proton_density\": 0.53140\n      }\n    },\n    \"graph_statistics\": {\n      \"axes\": {\n        \"y_axis\": {\n          \"label\": \"Интенсивность, %\",\n          \"visible_min\": -15,\n          \"visible_max\": 25,\n          \"step_interval\": null\n        },\n        \"x_axis\": {\n          \"label\": \"Время, мкс\",\n          \"visible_min\": 0,\n          \"visible_max\": 300,\n          \"step_interval\": 30\n        }\n      },\n      \"y_metrics_max\": {\n        \"red\": 24,\n        \"blue\": 25,\n        \"green\": 23\n      },\n      \"visible_tabs\": [\"NMR Signal\", \"Results Graph\", \"Code\"]\n    },\n    \"caption_data\": {\n      \"illustration_number\": \"№120\",\n      \"full_text\": \"Иллюстрация №120. Изображение одного из ЯМР участков исследуемых штрихов рукописной подписи нераспознанного лица №3 в предоставленном на исследование Объекте №9 при третьем проколе.\",\n      \"structured_details\": {\n        \"object_type\": \"ЯМР участок исследуемых штрихов\",\n        \"source_item\": \"\",\n        \"investigation_object\": \"Объект №9\",\n        \"condition\": \"при третьем проколе\"\n      }\n    }\n  }\n]\n```",
  "graphs": [
    {
      "graph_id": 1,
      "header_data": {
        "full_text": "Образец № 3 к Заключению № 11366; Индекс кристалличности = 0.77281; Протонная плотность = 0.44177",
        "structured_metrics": {
          "sample_reference": "Образец № 3 к Заключению № 11366",
          "crystallinity_index": 0.77281,
          "proton_density": 0.44177
        }
      },
      "graph_statistics": {
        "axes": {
          "y_axis": {
            "label": "Интенсивность, %",
            "visible_min": 0,
            "visible_max": 44,
            "step_interval": null
          },
          "x_axis": {
            "label": "Время, мкс",
            "visible_min": 0,
            "visible_max": 165,
            "step_interval": 15
          }
        },
        "y_metrics_max": {
          "red": 40,
          "blue": 42,
          "green": 36
        },
        "visible_tabs": [
          "NMR Signal",
          "Results Graph",
          "Code"
        ]
      },
      "caption_data": {
        "illustration_number": "№119",
        "full_text": "Иллюстрация №119. Изображение одного из ЯМР участков исследуемых штрихов рукописной подписи нераспознанного лица №2 в предоставленном на исследование Объекте №9 при третьем проколе.",
        "structured_details": {
          "object_type": "ЯМР участок исследуемых штрихов",
          "source_item": "",
          "investigation_object": "Объект №9",
          "condition": "при третьем проколе"
        }
      }
    },
    {
      "graph_id": 2,
      "header_data": {
        "full_text": "Образец № 3 к Заключению № 11366; Индекс кристалличности = 0.71987; Протонная плотность = 0.53140",
        "structured_metrics": {
          "sample_reference": "Образец № 3 к Заключению № 11366",
          "crystallinity_index": 0.71987,
          "proton_density": 0.5314
        }
      },
      "graph_statistics": {
        "axes": {
          "y_axis": {
            "label": "Интенсивность, %",
            "visible_min": -15,
            "visible_max": 25,
            "step_interval": null
          },
          "x_axis": {
            "label": "Время, мкс",
            "visible_min": 0,
            "visible_max": 300,
            "step_interval": 30
          }
        },
        "y_metrics_max": {
          "red": 24,
          "blue": 25,
          "green": 23
        },
        "visible_tabs": [
          "NMR Signal",
          "Results Graph",
          "Code"
        ]
      },
      "caption_data": {
        "illustration_number": "№120",
        "full_text": "Иллюстрация №120. Изображение одного из ЯМР участков исследуемых штрихов рукописной подписи нераспознанного лица №3 в предоставленном на исследование Объекте №9 при третьем проколе.",
        "structured_details": {
          "object_type": "ЯМР участок исследуемых штрихов",
          "source_item": "",
          "investigation_object": "Объект №9",
          "condition": "при третьем проколе"
        }
      }
    }
  ],
  "model": "gpt-4o-2024-08-06",
  "usage": {
    "prompt_tokens": 2055,
    "completion_tokens": 814,
    "total_tokens": 2869,
    "prompt_tokens_details": {
      "cached_tokens": 0,
      "audio_tokens": 0
    },
    "completion_tokens_details": {
      "reasoning_tokens": 0,
      "audio_tokens": 0,
      "accepted_prediction_tokens": 0,
      "rejected_prediction_tokens": 0
    }
  }
}