{
  "page": 32,
  "content": "```json\n[\n  {\n    \"graph_id\": 1,\n    \"header_data\": {\n      \"full_text\": \"Образец № 1 к Заключению № 11366; Индекс кристалличности = 0.81025; Протонная плотность = 0.41718\",\n      \"structured_metrics\": {\n        \"sample_reference\": \"Образец № 1 к Заключению № 11366\",\n        \"crystallinity_index\": 0.81025,\n        \"proton_density\": 0.41718\n      }\n    },\n    \"graph_statistics\": {\n      \"axes\": {\n        \"y_axis\": {\n          \"label\": \"Интенсивность, %\",\n          \"visible_min\": -50,\n          \"visible_max\": 100,\n          \"step_interval\": 10\n        },\n        \"x_axis\": {\n          \"label\": \"Время, мкс\",\n          \"visible_min\": 0,\n          \"visible_max\": 115,\n          \"step_interval\": 5\n        }\n      },\n      \"y_metrics_max\": {\n        \"red\": 60,\n        \"blue\": 40,\n        \"green\": 100\n      },\n      \"visible_tabs\": [\"NMR Signal\", \"Results Graph\", \"Code\"]\n    },\n    \"caption_data\": {\n      \"illustration_number\": \"№63\",\n      \"full_text\": \"Иллюстрация №63. Изображение одного из ЯМР участков исследуемых штрихов оттиска круглой мастичной печати ПАО «Московский Индустриальный банк» в предоставленном на исследование Объекте №5 при первом проколе.\",\n      \"structured_details\": {\n        \"object_type\": \"ЯМР участок исследуемых штрихов\",\n        \"source_item\": \"оттиск круглой мастичной печати ПАО «Московский Индустриальный банк»\",\n        \"investigation_object\": \"Объект №5\",\n        \"condition\": \"при первом проколе\"\n      }\n    }\n  },\n  {\n    \"graph_id\": 2,\n    \"header_data\": {\n      \"full_text\": \"Образец № 1 к Заключению № 11366; Индекс кристалличности = 0.79896; Протонная плотность = 0.30698\",\n      \"structured_metrics\": {\n        \"sample_reference\": \"Образец № 1 к Заключению № 11366\",\n        \"crystallinity_index\": 0.79896,\n        \"proton_density\": 0.30698\n      }\n    },\n    \"graph_statistics\": {\n      \"axes\": {\n        \"y_axis\": {\n          \"label\": \"Интенсивность, %\",\n          \"visible_min\": -50,\n          \"visible_max\": 100,\n          \"step_interval\": 10\n        },\n        \"x_axis\": {\n          \"label\": \"Время, мкс\",\n          \"visible_min\": 0,\n          \"visible_max\": 300,\n          \"step_interval\": 30\n        }\n      },\n      \"y_metrics_max\": {\n        \"red\": 60,\n        \"blue\": 40,\n        \"green\": 100\n      },\n      \"visible_tabs\": [\"NMR Signal\", \"Results Graph\", \"Code\"]\n    },\n    \"caption_data\": {\n      \"illustration_number\": \"№64\",\n      \"full_text\": \"Иллюстрация №64. Изображение одного из ЯМР участков исследуемых штрихов оттиска круглой мастичной печати ООО «Агро-Индустриальная Корпорация «Волго-Дон» в предоставленном на исследование Объекте №5 при первом проколе.\",\n      \"structured_details\": {\n        \"object_type\": \"ЯМР участок исследуемых штрихов\",\n        \"source_item\": \"оттиск круглой мастичной печати ООО «Агро-Индустриальная Корпорация «Волго-Дон»\",\n        \"investigation_object\": \"Объект №5\",\n        \"condition\": \"при первом проколе\"\n      }\n    }\n  }\n]\n```",
  "graphs": [
    {
      "graph_id": 1,
      "header_data": {
        "full_text": "Образец № 1 к Заключению № 11366; Индекс кристалличности = 0.81025; Протонная плотность = 0.41718",
        "structured_metrics": {
          "sample_reference": "Образец № 1 к Заключению № 11366",
          "crystallinity_index": 0.81025,
          "proton_density": 0.41718
        }
      },
      "graph_statistics": {
        "axes": {
          "y_axis": {
            "label": "Интенсивность, %",
            "visible_min": -50,
            "visible_max": 100,
            "step_interval": 10
          },
          "x_axis": {
            "label": "Время, мкс",
            "visible_min": 0,
            "visible_max": 115,
            "step_interval": 5
          }
        },
        "y_metrics_max": {
          "red": 60,
          "blue": 40,
          "green": 100
        },
        "visible_tabs": [
          "NMR Signal",
          "Results Graph",
          "Code"
        ]
      },
      "caption_data": {
        "illustration_number": "№63",
        "full_text": "Иллюстрация №63. Изображение одного из ЯМР участков исследуемых штрихов оттиска круглой мастичной печати ПАО «Московский Индустриальный банк» в предоставленном на исследование Объекте №5 при первом проколе.",
        "structured_details": {
          "object_type": "ЯМР участок исследуемых штрихов",
          "source_item": "оттиск круглой мастичной печати ПАО «Московский Индустриальный банк»",
          "investigation_object": "Объект №5",
          "condition": "при первом проколе"
        }
      }
    },
    {
      "graph_id": 2,
      "header_data": {
        "full_text": "Образец № 1 к Заключению № 11366; Индекс кристалличности = 0.79896; Протонная плотность = 0.30698",
        "structured_metrics": {
          "sample_reference": "Образец № 1 к Заключению № 11366",
          "crystallinity_index": 0.79896,
          "proton_density": 0.30698
        }
      },
      "graph_statistics": {
        "axes": {
          "y_axis": {
            "label": "Интенсивность, %",
            "visible_min": -50,
            "visible_max": 100,
            "step_interval": 10
          },
          "x_axis": {
            "label": "Время, мкс",
            "visible_min": 0,
            "visible_max": 300,
            "step_interval": 30
          }
        },
        "y_metrics_max": {
          "red": 60,
          "blue": 40,
          "green": 100
        },
        "visible_tabs": [
          "NMR Signal",
          "Results Graph",
          "Code"
        ]
      },
      "caption_data": {
        "illustration_number": "№64",
        "full_text": "Иллюстрация №64. Изображение одного из ЯМР участков исследуемых штрихов оттиска круглой мастичной печати ООО «Агро-Индустриальная Корпорация «Волго-Дон» в предоставленном на исследование Объекте №5 при первом проколе.",
        "structured_details": {
          "object_type": "ЯМР участок исследуемых штрихов",
          "source_item": "оттиск круглой мастичной печати ООО «Агро-Индустриальная Корпорация «Волго-Дон»",
          "investigation_object": "Объект №5",
          "condition": "при первом проколе"
        }
      }
    }
  ],
  "model": "gpt-4o-2024-08-06",
  "usage": {
    "prompt_tokens": 2055,
    "completion_tokens": 884,
    "total_tokens": 2939,
    "prompt_tokens_details": {
      "cached_tokens": 0,
      "audio_tokens": 0
    },
    "completion_tokens_details": {
      "reasoning_tokens": 0,
      "audio_tokens": 0,
      "accepted_prediction_tokens": 0,
      "rejected_prediction_tokens": 0
    }
  }
}