{
  "page": 24,
  "content": "```json\n[\n  {\n    \"graph_id\": 1,\n    \"header_data\": {\n      \"full_text\": \"Образец № 1 к Заключению № 11366; Индекс кристалличности = 0.83857; Протонная плотность = 0.72428\",\n      \"structured_metrics\": {\n        \"sample_reference\": \"Образец № 1 к Заключению № 11366\",\n        \"crystallinity_index\": 0.83857,\n        \"proton_density\": 0.72428\n      }\n    },\n    \"graph_statistics\": {\n      \"axes\": {\n        \"y_axis\": {\n          \"label\": \"Интенсивность, %\",\n          \"visible_min\": -60,\n          \"visible_max\": 60,\n          \"step_interval\": 20\n        },\n        \"x_axis\": {\n          \"label\": \"Время, мкс\",\n          \"visible_min\": 0,\n          \"visible_max\": 110,\n          \"step_interval\": 10\n        }\n      },\n      \"y_metrics_max\": {\n        \"red\": 30,\n        \"blue\": 50,\n        \"green\": 40\n      },\n      \"visible_tabs\": [\n        \"Log\",\n        \"NMRI Signal\",\n        \"Results Graph\",\n        \"Code\"\n      ]\n    },\n    \"caption_data\": {\n      \"illustration_number\": \"№47\",\n      \"full_text\": \"Иллюстрация №47. Изображение одного из ЯМР участков исследуемых штрихов рукописной подписи от имени Губашева С.С. в предоставленном на исследование Объекте №11 при первом проколе.\",\n      \"structured_details\": {\n        \"object_type\": \"ЯМР участок исследуемых штрихов\",\n        \"source_item\": \"рукописной подписи от имени Губашева С.С.\",\n        \"investigation_object\": \"Объект №11\",\n        \"condition\": \"при первом проколе\"\n      }\n    }\n  },\n  {\n    \"graph_id\": 2,\n    \"header_data\": {\n      \"full_text\": \"Образец № 1 к Заключению № 11366; Индекс кристалличности = 0.84031; Протонная плотность = 0.24021\",\n      \"structured_metrics\": {\n        \"sample_reference\": \"Образец № 1 к Заключению № 11366\",\n        \"crystallinity_index\": 0.84031,\n        \"proton_density\": 0.24021\n      }\n    },\n    \"graph_statistics\": {\n      \"axes\": {\n        \"y_axis\": {\n          \"label\": \"Интенсивность, %\",\n          \"visible_min\": -60,\n          \"visible_max\": 60,\n          \"step_interval\": 20\n        },\n        \"x_axis\": {\n          \"label\": \"Время, мкс\",\n          \"visible_min\": 0,\n          \"visible_max\": 110,\n          \"step_interval\": 10\n        }\n      },\n      \"y_metrics_max\": {\n        \"red\": 35,\n        \"blue\": 55,\n        \"green\": 55\n      },\n      \"visible_tabs\": [\n        \"Log\",\n        \"NMRI Signal\",\n        \"Results Graph\",\n        \"Code\"\n      ]\n    },\n    \"caption_data\": {\n      \"illustration_number\": \"№48\",\n      \"full_text\": \"Иллюстрация №48. Изображение одного из ЯМР участков исследуемых штрихов рукописной подписи от имени Тисленко Т.Б. в предоставленном на исследование Объекте №11 при первом проколе.\",\n      \"structured_details\": {\n        \"object_type\": \"ЯМР участок исследуемых штрихов\",\n        \"source_item\": \"рукописной подписи от имени Тисленко Т.Б.\",\n        \"investigation_object\": \"Объект №11\",\n        \"condition\": \"при первом проколе\"\n      }\n    }\n  }\n]\n```",
  "graphs": [
    {
      "graph_id": 1,
      "header_data": {
        "full_text": "Образец № 1 к Заключению № 11366; Индекс кристалличности = 0.83857; Протонная плотность = 0.72428",
        "structured_metrics": {
          "sample_reference": "Образец № 1 к Заключению № 11366",
          "crystallinity_index": 0.83857,
          "proton_density": 0.72428
        }
      },
      "graph_statistics": {
        "axes": {
          "y_axis": {
            "label": "Интенсивность, %",
            "visible_min": -60,
            "visible_max": 60,
            "step_interval": 20
          },
          "x_axis": {
            "label": "Время, мкс",
            "visible_min": 0,
            "visible_max": 110,
            "step_interval": 10
          }
        },
        "y_metrics_max": {
          "red": 30,
          "blue": 50,
          "green": 40
        },
        "visible_tabs": [
          "Log",
          "NMRI Signal",
          "Results Graph",
          "Code"
        ]
      },
      "caption_data": {
        "illustration_number": "№47",
        "full_text": "Иллюстрация №47. Изображение одного из ЯМР участков исследуемых штрихов рукописной подписи от имени Губашева С.С. в предоставленном на исследование Объекте №11 при первом проколе.",
        "structured_details": {
          "object_type": "ЯМР участок исследуемых штрихов",
          "source_item": "рукописной подписи от имени Губашева С.С.",
          "investigation_object": "Объект №11",
          "condition": "при первом проколе"
        }
      }
    },
    {
      "graph_id": 2,
      "header_data": {
        "full_text": "Образец № 1 к Заключению № 11366; Индекс кристалличности = 0.84031; Протонная плотность = 0.24021",
        "structured_metrics": {
          "sample_reference": "Образец № 1 к Заключению № 11366",
          "crystallinity_index": 0.84031,
          "proton_density": 0.24021
        }
      },
      "graph_statistics": {
        "axes": {
          "y_axis": {
            "label": "Интенсивность, %",
            "visible_min": -60,
            "visible_max": 60,
            "step_interval": 20
          },
          "x_axis": {
            "label": "Время, мкс",
            "visible_min": 0,
            "visible_max": 110,
            "step_interval": 10
          }
        },
        "y_metrics_max": {
          "red": 35,
          "blue": 55,
          "green": 55
        },
        "visible_tabs": [
          "Log",
          "NMRI Signal",
          "Results Graph",
          "Code"
        ]
      },
      "caption_data": {
        "illustration_number": "№48",
        "full_text": "Иллюстрация №48. Изображение одного из ЯМР участков исследуемых штрихов рукописной подписи от имени Тисленко Т.Б. в предоставленном на исследование Объекте №11 при первом проколе.",
        "structured_details": {
          "object_type": "ЯМР участок исследуемых штрихов",
          "source_item": "рукописной подписи от имени Тисленко Т.Б.",
          "investigation_object": "Объект №11",
          "condition": "при первом проколе"
        }
      }
    }
  ],
  "model": "gpt-4o-2024-08-06",
  "usage": {
    "prompt_tokens": 2055,
    "completion_tokens": 862,
    "total_tokens": 2917,
    "prompt_tokens_details": {
      "cached_tokens": 0,
      "audio_tokens": 0
    },
    "completion_tokens_details": {
      "reasoning_tokens": 0,
      "audio_tokens": 0,
      "accepted_prediction_tokens": 0,
      "rejected_prediction_tokens": 0
    }
  }
}