{
  "page": 54,
  "content": "```json\n[\n  {\n    \"graph_id\": 1,\n    \"header_data\": {\n      \"full_text\": \"Образец № 3 к Заключению № 11366; Индекс кристалличности = 0.72577; Протонная плотность = 0.18596\",\n      \"structured_metrics\": {\n        \"sample_reference\": \"Образец № 3 к Заключению № 11366\",\n        \"crystallinity_index\": 0.72577,\n        \"proton_density\": 0.18596\n      }\n    },\n    \"graph_statistics\": {\n      \"axes\": {\n        \"y_axis\": {\n          \"label\": \"Интенсивность, %\",\n          \"visible_min\": -16,\n          \"visible_max\": 20,\n          \"step_interval\": 4\n        },\n        \"x_axis\": {\n          \"label\": \"Время, мкс\",\n          \"visible_min\": 0,\n          \"visible_max\": 240,\n          \"step_interval\": 15\n        }\n      },\n      \"y_metrics_max\": {\n        \"red\": 20,\n        \"blue\": 10,\n        \"green\": 15\n      },\n      \"visible_tabs\": [\"NMR Signal\", \"Results Graph\", \"Code\"]\n    },\n    \"caption_data\": {\n      \"illustration_number\": \"№107\",\n      \"full_text\": \"Иллюстрация №107. Изображение одного из ЯМР участков исследуемых штрихов рукописной подписи от имени Тисленко Т.Б. в предоставленном на исследование Объекте №7 при третьем проколе.\",\n      \"structured_details\": {\n        \"object_type\": \"ЯМР участок исследуемых штрихов\",\n        \"source_item\": \"рукописной подписи от имени Тисленко Т.Б.\",\n        \"investigation_object\": \"Объект №7\",\n        \"condition\": \"при третьем проколе\"\n      }\n    }\n  },\n  {\n    \"graph_id\": 2,\n    \"header_data\": {\n      \"full_text\": \"Образец № 3 к Заключению № 11366; Индекс кристалличности = 0.68997; Протонная плотность = 0.03268\",\n      \"structured_metrics\": {\n        \"sample_reference\": \"Образец № 3 к Заключению № 11366\",\n        \"crystallinity_index\": 0.68997,\n        \"proton_density\": 0.03268\n      }\n    },\n    \"graph_statistics\": {\n      \"axes\": {\n        \"y_axis\": {\n          \"label\": \"Интенсивность, %\",\n          \"visible_min\": -48,\n          \"visible_max\": 32,\n          \"step_interval\": 8\n        },\n        \"x_axis\": {\n          \"label\": \"Время, мкс\",\n          \"visible_min\": 0,\n          \"visible_max\": 115,\n          \"step_interval\": 5\n        }\n      },\n      \"y_metrics_max\": {\n        \"red\": 22,\n        \"blue\": 25,\n        \"green\": 30\n      },\n      \"visible_tabs\": [\"NMR Signal\", \"Results Graph\", \"Code\"]\n    },\n    \"caption_data\": {\n      \"illustration_number\": \"№108\",\n      \"full_text\": \"Иллюстрация №108. Изображение одного из ЯМР участков исследуемых штрихов рукописной подписи от имени Филипенко И.Н. в предоставленном на исследование Объекте №7 при третьем проколе.\",\n      \"structured_details\": {\n        \"object_type\": \"ЯМР участок исследуемых штрихов\",\n        \"source_item\": \"рукописной подписи от имени Филипенко И.Н.\",\n        \"investigation_object\": \"Объект №7\",\n        \"condition\": \"при третьем проколе\"\n      }\n    }\n  }\n]\n```",
  "graphs": [
    {
      "graph_id": 1,
      "header_data": {
        "full_text": "Образец № 3 к Заключению № 11366; Индекс кристалличности = 0.72577; Протонная плотность = 0.18596",
        "structured_metrics": {
          "sample_reference": "Образец № 3 к Заключению № 11366",
          "crystallinity_index": 0.72577,
          "proton_density": 0.18596
        }
      },
      "graph_statistics": {
        "axes": {
          "y_axis": {
            "label": "Интенсивность, %",
            "visible_min": -16,
            "visible_max": 20,
            "step_interval": 4
          },
          "x_axis": {
            "label": "Время, мкс",
            "visible_min": 0,
            "visible_max": 240,
            "step_interval": 15
          }
        },
        "y_metrics_max": {
          "red": 20,
          "blue": 10,
          "green": 15
        },
        "visible_tabs": [
          "NMR Signal",
          "Results Graph",
          "Code"
        ]
      },
      "caption_data": {
        "illustration_number": "№107",
        "full_text": "Иллюстрация №107. Изображение одного из ЯМР участков исследуемых штрихов рукописной подписи от имени Тисленко Т.Б. в предоставленном на исследование Объекте №7 при третьем проколе.",
        "structured_details": {
          "object_type": "ЯМР участок исследуемых штрихов",
          "source_item": "рукописной подписи от имени Тисленко Т.Б.",
          "investigation_object": "Объект №7",
          "condition": "при третьем проколе"
        }
      }
    },
    {
      "graph_id": 2,
      "header_data": {
        "full_text": "Образец № 3 к Заключению № 11366; Индекс кристалличности = 0.68997; Протонная плотность = 0.03268",
        "structured_metrics": {
          "sample_reference": "Образец № 3 к Заключению № 11366",
          "crystallinity_index": 0.68997,
          "proton_density": 0.03268
        }
      },
      "graph_statistics": {
        "axes": {
          "y_axis": {
            "label": "Интенсивность, %",
            "visible_min": -48,
            "visible_max": 32,
            "step_interval": 8
          },
          "x_axis": {
            "label": "Время, мкс",
            "visible_min": 0,
            "visible_max": 115,
            "step_interval": 5
          }
        },
        "y_metrics_max": {
          "red": 22,
          "blue": 25,
          "green": 30
        },
        "visible_tabs": [
          "NMR Signal",
          "Results Graph",
          "Code"
        ]
      },
      "caption_data": {
        "illustration_number": "№108",
        "full_text": "Иллюстрация №108. Изображение одного из ЯМР участков исследуемых штрихов рукописной подписи от имени Филипенко И.Н. в предоставленном на исследование Объекте №7 при третьем проколе.",
        "structured_details": {
          "object_type": "ЯМР участок исследуемых штрихов",
          "source_item": "рукописной подписи от имени Филипенко И.Н.",
          "investigation_object": "Объект №7",
          "condition": "при третьем проколе"
        }
      }
    }
  ],
  "model": "gpt-4o-2024-08-06",
  "usage": {
    "prompt_tokens": 2055,
    "completion_tokens": 846,
    "total_tokens": 2901,
    "prompt_tokens_details": {
      "cached_tokens": 0,
      "audio_tokens": 0
    },
    "completion_tokens_details": {
      "reasoning_tokens": 0,
      "audio_tokens": 0,
      "accepted_prediction_tokens": 0,
      "rejected_prediction_tokens": 0
    }
  }
}