{
  "page": 12,
  "content": "```json\n[\n  {\n    \"graph_id\": 1,\n    \"header_data\": {\n      \"full_text\": \"Образец № 1 к Заключению № 11366; Индекс кристалличности = 0.81263; Протонная плотность = 0.35133\",\n      \"structured_metrics\": {\n        \"sample_reference\": \"Образец № 1 к Заключению № 11366\",\n        \"crystallinity_index\": 0.81263,\n        \"proton_density\": 0.35133\n      }\n    },\n    \"graph_statistics\": {\n      \"axes\": {\n        \"y_axis\": {\n          \"label\": \"Интенсивность, %\",\n          \"visible_min\": -50,\n          \"visible_max\": 50,\n          \"step_interval\": null\n        },\n        \"x_axis\": {\n          \"label\": \"Время, мкс\",\n          \"visible_min\": 0,\n          \"visible_max\": 405,\n          \"step_interval\": 25\n        }\n      },\n      \"y_metrics_max\": {\n        \"red\": 25,\n        \"blue\": 45,\n        \"green\": 15\n      },\n      \"visible_tabs\": [\n        \"NMR Signal\",\n        \"Results Graph\",\n        \"Code\"\n      ]\n    },\n    \"caption_data\": {\n      \"illustration_number\": \"№23\",\n      \"full_text\": \"Иллюстрация №23. Изображение одного из ЯМР участков исследуемых штрихов рукописной подписи от имени Шмульт Т.А. в предоставленном на исследование Объекте №5 при первом проколе.\",\n      \"structured_details\": {\n        \"object_type\": \"ЯМР участок исследуемых штрихов\",\n        \"source_item\": \"рукописной подписи от имени Шмульт Т.А.\",\n        \"investigation_object\": \"Объекте №5\",\n        \"condition\": \"при первом проколе\"\n      }\n    }\n  },\n  {\n    \"graph_id\": 2,\n    \"header_data\": {\n      \"full_text\": \"Образец № 1 к Заключению № 11366; Индекс кристалличности = 0.81436; Протонная плотность = 0.30238\",\n      \"structured_metrics\": {\n        \"sample_reference\": \"Образец № 1 к Заключению № 11366\",\n        \"crystallinity_index\": 0.81436,\n        \"proton_density\": 0.30238\n      }\n    },\n    \"graph_statistics\": {\n      \"axes\": {\n        \"y_axis\": {\n          \"label\": \"Интенсивность, %\",\n          \"visible_min\": -50,\n          \"visible_max\": 50,\n          \"step_interval\": null\n        },\n        \"x_axis\": {\n          \"label\": \"Время, мкс\",\n          \"visible_min\": 0,\n          \"visible_max\": 290,\n          \"step_interval\": 25\n        }\n      },\n      \"y_metrics_max\": {\n        \"red\": 20,\n        \"blue\": 30,\n        \"green\": 10\n      },\n      \"visible_tabs\": [\n        \"NMR Signal\",\n        \"Results Graph\",\n        \"Code\"\n      ]\n    },\n    \"caption_data\": {\n      \"illustration_number\": \"№24\",\n      \"full_text\": \"Иллюстрация №24. Изображение одного из ЯМР участков исследуемых штрихов рукописной подписи от имени Губашева С.С. в предоставленном на исследование Объекте №6 при первом проколе.\",\n      \"structured_details\": {\n        \"object_type\": \"ЯМР участок исследуемых штрихов\",\n        \"source_item\": \"рукописной подписи от имени Губашева С.С.\",\n        \"investigation_object\": \"Объекте №6\",\n        \"condition\": \"при первом проколе\"\n      }\n    }\n  }\n]\n```",
  "graphs": [
    {
      "graph_id": 1,
      "header_data": {
        "full_text": "Образец № 1 к Заключению № 11366; Индекс кристалличности = 0.81263; Протонная плотность = 0.35133",
        "structured_metrics": {
          "sample_reference": "Образец № 1 к Заключению № 11366",
          "crystallinity_index": 0.81263,
          "proton_density": 0.35133
        }
      },
      "graph_statistics": {
        "axes": {
          "y_axis": {
            "label": "Интенсивность, %",
            "visible_min": -50,
            "visible_max": 50,
            "step_interval": null
          },
          "x_axis": {
            "label": "Время, мкс",
            "visible_min": 0,
            "visible_max": 405,
            "step_interval": 25
          }
        },
        "y_metrics_max": {
          "red": 25,
          "blue": 45,
          "green": 15
        },
        "visible_tabs": [
          "NMR Signal",
          "Results Graph",
          "Code"
        ]
      },
      "caption_data": {
        "illustration_number": "№23",
        "full_text": "Иллюстрация №23. Изображение одного из ЯМР участков исследуемых штрихов рукописной подписи от имени Шмульт Т.А. в предоставленном на исследование Объекте №5 при первом проколе.",
        "structured_details": {
          "object_type": "ЯМР участок исследуемых штрихов",
          "source_item": "рукописной подписи от имени Шмульт Т.А.",
          "investigation_object": "Объекте №5",
          "condition": "при первом проколе"
        }
      }
    },
    {
      "graph_id": 2,
      "header_data": {
        "full_text": "Образец № 1 к Заключению № 11366; Индекс кристалличности = 0.81436; Протонная плотность = 0.30238",
        "structured_metrics": {
          "sample_reference": "Образец № 1 к Заключению № 11366",
          "crystallinity_index": 0.81436,
          "proton_density": 0.30238
        }
      },
      "graph_statistics": {
        "axes": {
          "y_axis": {
            "label": "Интенсивность, %",
            "visible_min": -50,
            "visible_max": 50,
            "step_interval": null
          },
          "x_axis": {
            "label": "Время, мкс",
            "visible_min": 0,
            "visible_max": 290,
            "step_interval": 25
          }
        },
        "y_metrics_max": {
          "red": 20,
          "blue": 30,
          "green": 10
        },
        "visible_tabs": [
          "NMR Signal",
          "Results Graph",
          "Code"
        ]
      },
      "caption_data": {
        "illustration_number": "№24",
        "full_text": "Иллюстрация №24. Изображение одного из ЯМР участков исследуемых штрихов рукописной подписи от имени Губашева С.С. в предоставленном на исследование Объекте №6 при первом проколе.",
        "structured_details": {
          "object_type": "ЯМР участок исследуемых штрихов",
          "source_item": "рукописной подписи от имени Губашева С.С.",
          "investigation_object": "Объекте №6",
          "condition": "при первом проколе"
        }
      }
    }
  ],
  "model": "gpt-4o-2024-08-06",
  "usage": {
    "prompt_tokens": 2055,
    "completion_tokens": 850,
    "total_tokens": 2905,
    "prompt_tokens_details": {
      "cached_tokens": 0,
      "audio_tokens": 0
    },
    "completion_tokens_details": {
      "reasoning_tokens": 0,
      "audio_tokens": 0,
      "accepted_prediction_tokens": 0,
      "rejected_prediction_tokens": 0
    }
  }
}