{
  "page": 27,
  "content": "```json\n[\n  {\n    \"graph_id\": 1,\n    \"header_data\": {\n      \"full_text\": \"Образец № 1 к Заключению № 11366; Индекс кристалличности = 0.80599; Протонная плотность = 0.23307\",\n      \"structured_metrics\": {\n        \"sample_reference\": \"Образец № 1 к Заключению № 11366\",\n        \"crystallinity_index\": 0.80599,\n        \"proton_density\": 0.23307\n      }\n    },\n    \"graph_statistics\": {\n      \"axes\": {\n        \"y_axis\": {\n          \"label\": \"Интенсивность, %\",\n          \"visible_min\": -24,\n          \"visible_max\": 24,\n          \"step_interval\": 6\n        },\n        \"x_axis\": {\n          \"label\": \"Время, мкс\",\n          \"visible_min\": 0,\n          \"visible_max\": 115,\n          \"step_interval\": 10\n        }\n      },\n      \"y_metrics_max\": {\n        \"red\": 4,\n        \"blue\": 6,\n        \"green\": 2\n      },\n      \"visible_tabs\": [\"NMR Signal\", \"Results Graph\", \"Code\"]\n    },\n    \"caption_data\": {\n      \"illustration_number\": \"№53\",\n      \"full_text\": \"Иллюстрация №53. Изображение одного из ЯМР участков исследуемых штрихов рукописной подписи от имени Филиппенко И.Н. в предоставленном на исследование Объекте №12 при первом проколе.\",\n      \"structured_details\": {\n        \"object_type\": \"ЯМР участок исследуемых штрихов\",\n        \"source_item\": \"рукописной подписи от имени Филиппенко И.Н.\",\n        \"investigation_object\": \"Объекте №12\",\n        \"condition\": \"при первом проколе\"\n      }\n    }\n  },\n  {\n    \"graph_id\": 2,\n    \"header_data\": {\n      \"full_text\": \"Образец № 1 к Заключению № 11366; Индекс кристалличности = 0.78367; Протонная плотность = 0.46562\",\n      \"structured_metrics\": {\n        \"sample_reference\": \"Образец № 1 к Заключению № 11366\",\n        \"crystallinity_index\": 0.78367,\n        \"proton_density\": 0.46562\n      }\n    },\n    \"graph_statistics\": {\n      \"axes\": {\n        \"y_axis\": {\n          \"label\": \"Интенсивность, %\",\n          \"visible_min\": -30,\n          \"visible_max\": 24,\n          \"step_interval\": 6\n        },\n        \"x_axis\": {\n          \"label\": \"Время, мкс\",\n          \"visible_min\": 0,\n          \"visible_max\": 325,\n          \"step_interval\": 25\n        }\n      },\n      \"y_metrics_max\": {\n        \"red\": 20,\n        \"blue\": 4,\n        \"green\": 16\n      },\n      \"visible_tabs\": [\"NMR Signal\", \"Results Graph\", \"Code\"]\n    },\n    \"caption_data\": {\n      \"illustration_number\": \"№54\",\n      \"full_text\": \"Иллюстрация №54. Изображение одного из ЯМР участков исследуемых штрихов рукописной подписи от имени Шмульт Т.А. в предоставленном на исследование Объекте №12 при первом проколе.\",\n      \"structured_details\": {\n        \"object_type\": \"ЯМР участок исследуемых штрихов\",\n        \"source_item\": \"рукописной подписи от имени Шмульт Т.А.\",\n        \"investigation_object\": \"Объекте №12\",\n        \"condition\": \"при первом проколе\"\n      }\n    }\n  }\n]\n```",
  "graphs": [
    {
      "graph_id": 1,
      "header_data": {
        "full_text": "Образец № 1 к Заключению № 11366; Индекс кристалличности = 0.80599; Протонная плотность = 0.23307",
        "structured_metrics": {
          "sample_reference": "Образец № 1 к Заключению № 11366",
          "crystallinity_index": 0.80599,
          "proton_density": 0.23307
        }
      },
      "graph_statistics": {
        "axes": {
          "y_axis": {
            "label": "Интенсивность, %",
            "visible_min": -24,
            "visible_max": 24,
            "step_interval": 6
          },
          "x_axis": {
            "label": "Время, мкс",
            "visible_min": 0,
            "visible_max": 115,
            "step_interval": 10
          }
        },
        "y_metrics_max": {
          "red": 4,
          "blue": 6,
          "green": 2
        },
        "visible_tabs": [
          "NMR Signal",
          "Results Graph",
          "Code"
        ]
      },
      "caption_data": {
        "illustration_number": "№53",
        "full_text": "Иллюстрация №53. Изображение одного из ЯМР участков исследуемых штрихов рукописной подписи от имени Филиппенко И.Н. в предоставленном на исследование Объекте №12 при первом проколе.",
        "structured_details": {
          "object_type": "ЯМР участок исследуемых штрихов",
          "source_item": "рукописной подписи от имени Филиппенко И.Н.",
          "investigation_object": "Объекте №12",
          "condition": "при первом проколе"
        }
      }
    },
    {
      "graph_id": 2,
      "header_data": {
        "full_text": "Образец № 1 к Заключению № 11366; Индекс кристалличности = 0.78367; Протонная плотность = 0.46562",
        "structured_metrics": {
          "sample_reference": "Образец № 1 к Заключению № 11366",
          "crystallinity_index": 0.78367,
          "proton_density": 0.46562
        }
      },
      "graph_statistics": {
        "axes": {
          "y_axis": {
            "label": "Интенсивность, %",
            "visible_min": -30,
            "visible_max": 24,
            "step_interval": 6
          },
          "x_axis": {
            "label": "Время, мкс",
            "visible_min": 0,
            "visible_max": 325,
            "step_interval": 25
          }
        },
        "y_metrics_max": {
          "red": 20,
          "blue": 4,
          "green": 16
        },
        "visible_tabs": [
          "NMR Signal",
          "Results Graph",
          "Code"
        ]
      },
      "caption_data": {
        "illustration_number": "№54",
        "full_text": "Иллюстрация №54. Изображение одного из ЯМР участков исследуемых штрихов рукописной подписи от имени Шмульт Т.А. в предоставленном на исследование Объекте №12 при первом проколе.",
        "structured_details": {
          "object_type": "ЯМР участок исследуемых штрихов",
          "source_item": "рукописной подписи от имени Шмульт Т.А.",
          "investigation_object": "Объекте №12",
          "condition": "при первом проколе"
        }
      }
    }
  ],
  "model": "gpt-4o-2024-08-06",
  "usage": {
    "prompt_tokens": 2055,
    "completion_tokens": 840,
    "total_tokens": 2895,
    "prompt_tokens_details": {
      "cached_tokens": 0,
      "audio_tokens": 0
    },
    "completion_tokens_details": {
      "reasoning_tokens": 0,
      "audio_tokens": 0,
      "accepted_prediction_tokens": 0,
      "rejected_prediction_tokens": 0
    }
  }
}