{
  "page": 78,
  "content": "```json\n[\n  {\n    \"graph_id\": 1,\n    \"header_data\": {\n      \"full_text\": \"Образец № 3 к Заключению № 11366; Индекс кристалличности = 0.73297; Протонная плотность = 0.25920\",\n      \"structured_metrics\": {\n        \"sample_reference\": \"Образец № 3 к Заключению № 11366\",\n        \"crystallinity_index\": 0.73297,\n        \"proton_density\": 0.25920\n      }\n    },\n    \"graph_statistics\": {\n      \"axes\": {\n        \"y_axis\": {\n          \"label\": \"Интенсивность, %\",\n          \"visible_min\": -10,\n          \"visible_max\": 40,\n          \"step_interval\": 10\n        },\n        \"x_axis\": {\n          \"label\": \"Время, мкс\",\n          \"visible_min\": 0,\n          \"visible_max\": 405,\n          \"step_interval\": 25\n        }\n      },\n      \"y_metrics_max\": {\n        \"red\": 33,\n        \"blue\": 30,\n        \"green\": 35\n      },\n      \"visible_tabs\": [\"NMR Signal\", \"Results Graph\", \"Code\"]\n    },\n    \"caption_data\": {\n      \"illustration_number\": \"№155\",\n      \"full_text\": \"Иллюстрация №155. Изображение одного из ЯМР участков исследуемых штрихов оттиска круглой мастичной печати ПАО «Московский Индустриальный банк» в предоставленном на исследование Объекте №12 при третьем проколе.\",\n      \"structured_details\": {\n        \"object_type\": \"ЯМР участок исследуемых штрихов\",\n        \"source_item\": \"оттиск круглой мастичной печати ПАО «Московский Индустриальный банк»\",\n        \"investigation_object\": \"Объект №12\",\n        \"condition\": \"при третьем проколе\"\n      }\n    }\n  },\n  {\n    \"graph_id\": 2,\n    \"header_data\": {\n      \"full_text\": \"Образец № 3 к Заключению № 11366; Индекс кристалличности = 0.69276; Протонная плотность = 0.38404\",\n      \"structured_metrics\": {\n        \"sample_reference\": \"Образец № 3 к Заключению № 11366\",\n        \"crystallinity_index\": 0.69276,\n        \"proton_density\": 0.38404\n      }\n    },\n    \"graph_statistics\": {\n      \"axes\": {\n        \"y_axis\": {\n          \"label\": \"Интенсивность, %\",\n          \"visible_min\": -60,\n          \"visible_max\": 80,\n          \"step_interval\": 20\n        },\n        \"x_axis\": {\n          \"label\": \"Время, мкс\",\n          \"visible_min\": 0,\n          \"visible_max\": 175,\n          \"step_interval\": 25\n        }\n      },\n      \"y_metrics_max\": {\n        \"red\": 70,\n        \"blue\": 65,\n        \"green\": 75\n      },\n      \"visible_tabs\": [\"NMR Signal\", \"Results Graph\", \"Code\"]\n    },\n    \"caption_data\": {\n      \"illustration_number\": \"№156\",\n      \"full_text\": \"Иллюстрация №156. Изображение одного из ЯМР участков исследуемых штрихов оттиска круглой мастичной печати ООО «Ростовская нива» в предоставленном на исследование Объекте №12 при третьем проколе.\",\n      \"structured_details\": {\n        \"object_type\": \"ЯМР участок исследуемых штрихов\",\n        \"source_item\": \"оттиск круглой мастичной печати ООО «Ростовская нива»\",\n        \"investigation_object\": \"Объект №12\",\n        \"condition\": \"при третьем проколе\"\n      }\n    }\n  }\n]\n```",
  "graphs": [
    {
      "graph_id": 1,
      "header_data": {
        "full_text": "Образец № 3 к Заключению № 11366; Индекс кристалличности = 0.73297; Протонная плотность = 0.25920",
        "structured_metrics": {
          "sample_reference": "Образец № 3 к Заключению № 11366",
          "crystallinity_index": 0.73297,
          "proton_density": 0.2592
        }
      },
      "graph_statistics": {
        "axes": {
          "y_axis": {
            "label": "Интенсивность, %",
            "visible_min": -10,
            "visible_max": 40,
            "step_interval": 10
          },
          "x_axis": {
            "label": "Время, мкс",
            "visible_min": 0,
            "visible_max": 405,
            "step_interval": 25
          }
        },
        "y_metrics_max": {
          "red": 33,
          "blue": 30,
          "green": 35
        },
        "visible_tabs": [
          "NMR Signal",
          "Results Graph",
          "Code"
        ]
      },
      "caption_data": {
        "illustration_number": "№155",
        "full_text": "Иллюстрация №155. Изображение одного из ЯМР участков исследуемых штрихов оттиска круглой мастичной печати ПАО «Московский Индустриальный банк» в предоставленном на исследование Объекте №12 при третьем проколе.",
        "structured_details": {
          "object_type": "ЯМР участок исследуемых штрихов",
          "source_item": "оттиск круглой мастичной печати ПАО «Московский Индустриальный банк»",
          "investigation_object": "Объект №12",
          "condition": "при третьем проколе"
        }
      }
    },
    {
      "graph_id": 2,
      "header_data": {
        "full_text": "Образец № 3 к Заключению № 11366; Индекс кристалличности = 0.69276; Протонная плотность = 0.38404",
        "structured_metrics": {
          "sample_reference": "Образец № 3 к Заключению № 11366",
          "crystallinity_index": 0.69276,
          "proton_density": 0.38404
        }
      },
      "graph_statistics": {
        "axes": {
          "y_axis": {
            "label": "Интенсивность, %",
            "visible_min": -60,
            "visible_max": 80,
            "step_interval": 20
          },
          "x_axis": {
            "label": "Время, мкс",
            "visible_min": 0,
            "visible_max": 175,
            "step_interval": 25
          }
        },
        "y_metrics_max": {
          "red": 70,
          "blue": 65,
          "green": 75
        },
        "visible_tabs": [
          "NMR Signal",
          "Results Graph",
          "Code"
        ]
      },
      "caption_data": {
        "illustration_number": "№156",
        "full_text": "Иллюстрация №156. Изображение одного из ЯМР участков исследуемых штрихов оттиска круглой мастичной печати ООО «Ростовская нива» в предоставленном на исследование Объекте №12 при третьем проколе.",
        "structured_details": {
          "object_type": "ЯМР участок исследуемых штрихов",
          "source_item": "оттиск круглой мастичной печати ООО «Ростовская нива»",
          "investigation_object": "Объект №12",
          "condition": "при третьем проколе"
        }
      }
    }
  ],
  "model": "gpt-4o-2024-08-06",
  "usage": {
    "prompt_tokens": 2055,
    "completion_tokens": 864,
    "total_tokens": 2919,
    "prompt_tokens_details": {
      "cached_tokens": 0,
      "audio_tokens": 0
    },
    "completion_tokens_details": {
      "reasoning_tokens": 0,
      "audio_tokens": 0,
      "accepted_prediction_tokens": 0,
      "rejected_prediction_tokens": 0
    }
  }
}