{
  "page": 50,
  "content": "```json\n[\n  {\n    \"graph_id\": 1,\n    \"header_data\": {\n      \"full_text\": \"Образец № 3 к Заключению № 11366; Индекс кристалличности = 0.70318; Протонная плотность = 0.47087\",\n      \"structured_metrics\": {\n        \"sample_reference\": \"Образец № 3 к Заключению № 11366\",\n        \"crystallinity_index\": 0.70318,\n        \"proton_density\": 0.47087\n      }\n    },\n    \"graph_statistics\": {\n      \"axes\": {\n        \"y_axis\": {\n          \"label\": \"Интенсивность, %\",\n          \"visible_min\": -50,\n          \"visible_max\": 50,\n          \"step_interval\": null\n        },\n        \"x_axis\": {\n          \"label\": \"Время, мкс\",\n          \"visible_min\": 0,\n          \"visible_max\": 250,\n          \"step_interval\": null\n        }\n      },\n      \"y_metrics_max\": {\n        \"red\": 12,\n        \"blue\": 24,\n        \"green\": 28\n      },\n      \"visible_tabs\": [\"NMR Signal\", \"Results Graph\"]\n    },\n    \"caption_data\": {\n      \"illustration_number\": \"№99\",\n      \"full_text\": \"Иллюстрация №99. Изображение одного из ЯМР участков исследуемых штрихов рукописной подписи от имени Тисленко Т.Б. в предоставленном на исследование Объекте №5 при третьем проколе.\",\n      \"structured_details\": {\n        \"object_type\": \"ЯМР участок исследуемых штрихов\",\n        \"source_item\": \"рукописной подписи от имени Тисленко Т.Б.\",\n        \"investigation_object\": \"Объект №5\",\n        \"condition\": \"при третьем проколе\"\n      }\n    }\n  },\n  {\n    \"graph_id\": 2,\n    \"header_data\": {\n      \"full_text\": \"Образец № 3 к Заключению № 11366; Индекс кристалличности = 0.72422; Протонная плотность = 0.40709\",\n      \"structured_metrics\": {\n        \"sample_reference\": \"Образец № 3 к Заключению № 11366\",\n        \"crystallinity_index\": 0.72422,\n        \"proton_density\": 0.40709\n      }\n    },\n    \"graph_statistics\": {\n      \"axes\": {\n        \"y_axis\": {\n          \"label\": \"Интенсивность, %\",\n          \"visible_min\": -50,\n          \"visible_max\": 50,\n          \"step_interval\": null\n        },\n        \"x_axis\": {\n          \"label\": \"Время, мкс\",\n          \"visible_min\": 0,\n          \"visible_max\": 350,\n          \"step_interval\": null\n        }\n      },\n      \"y_metrics_max\": {\n        \"red\": 0,\n        \"blue\": 24,\n        \"green\": 40\n      },\n      \"visible_tabs\": [\"NMR Signal\", \"Results Graph\"]\n    },\n    \"caption_data\": {\n      \"illustration_number\": \"№100\",\n      \"full_text\": \"Иллюстрация №100. Изображение одного из ЯМР участков исследуемых штрихов рукописной подписи от имени Филипенко И.Н. в предоставленном на исследование Объекте №5 при третьем проколе.\",\n      \"structured_details\": {\n        \"object_type\": \"ЯМР участок исследуемых штрихов\",\n        \"source_item\": \"рукописной подписи от имени Филипенко И.Н.\",\n        \"investigation_object\": \"Объект №5\",\n        \"condition\": \"при третьем проколе\"\n      }\n    }\n  }\n]\n```",
  "graphs": [
    {
      "graph_id": 1,
      "header_data": {
        "full_text": "Образец № 3 к Заключению № 11366; Индекс кристалличности = 0.70318; Протонная плотность = 0.47087",
        "structured_metrics": {
          "sample_reference": "Образец № 3 к Заключению № 11366",
          "crystallinity_index": 0.70318,
          "proton_density": 0.47087
        }
      },
      "graph_statistics": {
        "axes": {
          "y_axis": {
            "label": "Интенсивность, %",
            "visible_min": -50,
            "visible_max": 50,
            "step_interval": null
          },
          "x_axis": {
            "label": "Время, мкс",
            "visible_min": 0,
            "visible_max": 250,
            "step_interval": null
          }
        },
        "y_metrics_max": {
          "red": 12,
          "blue": 24,
          "green": 28
        },
        "visible_tabs": [
          "NMR Signal",
          "Results Graph"
        ]
      },
      "caption_data": {
        "illustration_number": "№99",
        "full_text": "Иллюстрация №99. Изображение одного из ЯМР участков исследуемых штрихов рукописной подписи от имени Тисленко Т.Б. в предоставленном на исследование Объекте №5 при третьем проколе.",
        "structured_details": {
          "object_type": "ЯМР участок исследуемых штрихов",
          "source_item": "рукописной подписи от имени Тисленко Т.Б.",
          "investigation_object": "Объект №5",
          "condition": "при третьем проколе"
        }
      }
    },
    {
      "graph_id": 2,
      "header_data": {
        "full_text": "Образец № 3 к Заключению № 11366; Индекс кристалличности = 0.72422; Протонная плотность = 0.40709",
        "structured_metrics": {
          "sample_reference": "Образец № 3 к Заключению № 11366",
          "crystallinity_index": 0.72422,
          "proton_density": 0.40709
        }
      },
      "graph_statistics": {
        "axes": {
          "y_axis": {
            "label": "Интенсивность, %",
            "visible_min": -50,
            "visible_max": 50,
            "step_interval": null
          },
          "x_axis": {
            "label": "Время, мкс",
            "visible_min": 0,
            "visible_max": 350,
            "step_interval": null
          }
        },
        "y_metrics_max": {
          "red": 0,
          "blue": 24,
          "green": 40
        },
        "visible_tabs": [
          "NMR Signal",
          "Results Graph"
        ]
      },
      "caption_data": {
        "illustration_number": "№100",
        "full_text": "Иллюстрация №100. Изображение одного из ЯМР участков исследуемых штрихов рукописной подписи от имени Филипенко И.Н. в предоставленном на исследование Объекте №5 при третьем проколе.",
        "structured_details": {
          "object_type": "ЯМР участок исследуемых штрихов",
          "source_item": "рукописной подписи от имени Филипенко И.Н.",
          "investigation_object": "Объект №5",
          "condition": "при третьем проколе"
        }
      }
    }
  ],
  "model": "gpt-4o-2024-08-06",
  "usage": {
    "prompt_tokens": 2055,
    "completion_tokens": 836,
    "total_tokens": 2891,
    "prompt_tokens_details": {
      "cached_tokens": 0,
      "audio_tokens": 0
    },
    "completion_tokens_details": {
      "reasoning_tokens": 0,
      "audio_tokens": 0,
      "accepted_prediction_tokens": 0,
      "rejected_prediction_tokens": 0
    }
  }
}