{
  "page": 70,
  "content": "```json\n[\n  {\n    \"graph_id\": 1,\n    \"header_data\": {\n      \"full_text\": \"Образец № 3 к Заключению № 11366; Индекс кристалличности = 0.72990; Протонная плотность = 0.48950\",\n      \"structured_metrics\": {\n        \"sample_reference\": \"Образец № 3 к Заключению № 11366\",\n        \"crystallinity_index\": 0.72990,\n        \"proton_density\": 0.48950\n      }\n    },\n    \"graph_statistics\": {\n      \"axes\": {\n        \"y_axis\": {\n          \"label\": \"Интенсивность, %\",\n          \"visible_min\": -30,\n          \"visible_max\": 60,\n          \"step_interval\": 10\n        },\n        \"x_axis\": {\n          \"label\": \"Время, мкс\",\n          \"visible_min\": 0,\n          \"visible_max\": 250,\n          \"step_interval\": 25\n        }\n      },\n      \"y_metrics_max\": {\n        \"red\": 32,\n        \"blue\": 48,\n        \"green\": 22\n      },\n      \"visible_tabs\": [\"NMR Signal\", \"Results Graph\", \"Code\"]\n    },\n    \"caption_data\": {\n      \"illustration_number\": \"№139\",\n      \"full_text\": \"Иллюстрация №139. Изображение одного из ЯМР участков исследуемых штрихов оттиска круглой мастичной печати ПАО «Московский Индустриальный банк» в предоставленном на исследование Объекте №4 при третьем проколе.\",\n      \"structured_details\": {\n        \"object_type\": \"ЯМР участок исследуемых штрихов\",\n        \"source_item\": \"оттиск круглой мастичной печати ПАО «Московский Индустриальный банк»\",\n        \"investigation_object\": \"Объект №4\",\n        \"condition\": \"при третьем проколе\"\n      }\n    }\n  },\n  {\n    \"graph_id\": 2,\n    \"header_data\": {\n      \"full_text\": \"Образец № 3 к Заключению № 11366; Индекс кристалличности = 0.73402; Протонная плотность = 0.24103\",\n      \"structured_metrics\": {\n        \"sample_reference\": \"Образец № 3 к Заключению № 11366\",\n        \"crystallinity_index\": 0.73402,\n        \"proton_density\": 0.24103\n      }\n    },\n    \"graph_statistics\": {\n      \"axes\": {\n        \"y_axis\": {\n          \"label\": \"Интенсивность, %\",\n          \"visible_min\": -30,\n          \"visible_max\": 60,\n          \"step_interval\": 10\n        },\n        \"x_axis\": {\n          \"label\": \"Время, мкс\",\n          \"visible_min\": 0,\n          \"visible_max\": 165,\n          \"step_interval\": 15\n        }\n      },\n      \"y_metrics_max\": {\n        \"red\": 32,\n        \"blue\": 48,\n        \"green\": 22\n      },\n      \"visible_tabs\": [\"NMR Signal\", \"Results Graph\", \"Code\"]\n    },\n    \"caption_data\": {\n      \"illustration_number\": \"№140\",\n      \"full_text\": \"Иллюстрация №140. Изображение одного из ЯМР участков исследуемых штрихов оттиска круглой мастичной печати ООО «Ростовская нива» в предоставленном на исследование Объекте №4 при третьем проколе.\",\n      \"structured_details\": {\n        \"object_type\": \"ЯМР участок исследуемых штрихов\",\n        \"source_item\": \"оттиск круглой мастичной печати ООО «Ростовская нива»\",\n        \"investigation_object\": \"Объект №4\",\n        \"condition\": \"при третьем проколе\"\n      }\n    }\n  }\n]\n```",
  "graphs": [
    {
      "graph_id": 1,
      "header_data": {
        "full_text": "Образец № 3 к Заключению № 11366; Индекс кристалличности = 0.72990; Протонная плотность = 0.48950",
        "structured_metrics": {
          "sample_reference": "Образец № 3 к Заключению № 11366",
          "crystallinity_index": 0.7299,
          "proton_density": 0.4895
        }
      },
      "graph_statistics": {
        "axes": {
          "y_axis": {
            "label": "Интенсивность, %",
            "visible_min": -30,
            "visible_max": 60,
            "step_interval": 10
          },
          "x_axis": {
            "label": "Время, мкс",
            "visible_min": 0,
            "visible_max": 250,
            "step_interval": 25
          }
        },
        "y_metrics_max": {
          "red": 32,
          "blue": 48,
          "green": 22
        },
        "visible_tabs": [
          "NMR Signal",
          "Results Graph",
          "Code"
        ]
      },
      "caption_data": {
        "illustration_number": "№139",
        "full_text": "Иллюстрация №139. Изображение одного из ЯМР участков исследуемых штрихов оттиска круглой мастичной печати ПАО «Московский Индустриальный банк» в предоставленном на исследование Объекте №4 при третьем проколе.",
        "structured_details": {
          "object_type": "ЯМР участок исследуемых штрихов",
          "source_item": "оттиск круглой мастичной печати ПАО «Московский Индустриальный банк»",
          "investigation_object": "Объект №4",
          "condition": "при третьем проколе"
        }
      }
    },
    {
      "graph_id": 2,
      "header_data": {
        "full_text": "Образец № 3 к Заключению № 11366; Индекс кристалличности = 0.73402; Протонная плотность = 0.24103",
        "structured_metrics": {
          "sample_reference": "Образец № 3 к Заключению № 11366",
          "crystallinity_index": 0.73402,
          "proton_density": 0.24103
        }
      },
      "graph_statistics": {
        "axes": {
          "y_axis": {
            "label": "Интенсивность, %",
            "visible_min": -30,
            "visible_max": 60,
            "step_interval": 10
          },
          "x_axis": {
            "label": "Время, мкс",
            "visible_min": 0,
            "visible_max": 165,
            "step_interval": 15
          }
        },
        "y_metrics_max": {
          "red": 32,
          "blue": 48,
          "green": 22
        },
        "visible_tabs": [
          "NMR Signal",
          "Results Graph",
          "Code"
        ]
      },
      "caption_data": {
        "illustration_number": "№140",
        "full_text": "Иллюстрация №140. Изображение одного из ЯМР участков исследуемых штрихов оттиска круглой мастичной печати ООО «Ростовская нива» в предоставленном на исследование Объекте №4 при третьем проколе.",
        "structured_details": {
          "object_type": "ЯМР участок исследуемых штрихов",
          "source_item": "оттиск круглой мастичной печати ООО «Ростовская нива»",
          "investigation_object": "Объект №4",
          "condition": "при третьем проколе"
        }
      }
    }
  ],
  "model": "gpt-4o-2024-08-06",
  "usage": {
    "prompt_tokens": 2055,
    "completion_tokens": 864,
    "total_tokens": 2919,
    "prompt_tokens_details": {
      "cached_tokens": 0,
      "audio_tokens": 0
    },
    "completion_tokens_details": {
      "reasoning_tokens": 0,
      "audio_tokens": 0,
      "accepted_prediction_tokens": 0,
      "rejected_prediction_tokens": 0
    }
  }
}