{
  "page": 1,
  "content": "```json\n[\n  {\n    \"graph_id\": 1,\n    \"header_data\": {\n      \"full_text\": \"Образец № 1 к Заключению № 11366; Индекс кристалличности = 0.8029%; Протонная плотность = 0.35677\",\n      \"structured_metrics\": {\n        \"sample_reference\": \"Образец № 1 к Заключению № 11366\",\n        \"crystallinity_index\": 0.8029,\n        \"proton_density\": 0.35677\n      }\n    },\n    \"graph_statistics\": {\n      \"axes\": {\n        \"y_axis\": {\n          \"label\": \"Интенсивность, %\",\n          \"visible_min\": -5,\n          \"visible_max\": 45,\n          \"step_interval\": 5\n        },\n        \"x_axis\": {\n          \"label\": \"Время, мкс\",\n          \"visible_min\": 0,\n          \"visible_max\": 175,\n          \"step_interval\": 25\n        }\n      },\n      \"y_metrics_max\": {\n        \"red\": 40,\n        \"blue\": 24,\n        \"green\": 40\n      },\n      \"visible_tabs\": [\"NMR Signal\", \"Results Graph\", \"Code\"]\n    },\n    \"caption_data\": {\n      \"illustration_number\": \"№1\",\n      \"full_text\": \"Иллюстрация №1. Изображение одного из ЯМР участков исследуемых штрихов рукописной подписи от имени Губаева С.С. в предоставленном на исследование Объекте №1 при первом проколе.\",\n      \"structured_details\": {\n        \"object_type\": \"ЯМР участок исследуемых штрихов\",\n        \"source_item\": \"рукописной подписи от имени Губаева С.С.\",\n        \"investigation_object\": \"Объект №1\",\n        \"condition\": \"при первом проколе\"\n      }\n    }\n  },\n  {\n    \"graph_id\": 2,\n    \"header_data\": {\n      \"full_text\": \"Образец № 1 к Заключению № 11366; Индекс кристалличности = 0.81836; Протонная плотность = 0.06842\",\n      \"structured_metrics\": {\n        \"sample_reference\": \"Образец № 1 к Заключению № 11366\",\n        \"crystallinity_index\": 0.81836,\n        \"proton_density\": 0.06842\n      }\n    },\n    \"graph_statistics\": {\n      \"axes\": {\n        \"y_axis\": {\n          \"label\": \"Интенсивность, %\",\n          \"visible_min\": -5,\n          \"visible_max\": 45,\n          \"step_interval\": 5\n        },\n        \"x_axis\": {\n          \"label\": \"Время, мкс\",\n          \"visible_min\": 0,\n          \"visible_max\": 250,\n          \"step_interval\": 50\n        }\n      },\n      \"y_metrics_max\": {\n        \"red\": 40,\n        \"blue\": 38,\n        \"green\": 30\n      },\n      \"visible_tabs\": [\"NMR Signal\", \"Results Graph\", \"Code\"]\n    },\n    \"caption_data\": {\n      \"illustration_number\": \"№2\",\n      \"full_text\": \"Иллюстрация №2. Изображение одного из ЯМР участков исследуемых штрихов рукописной подписи от имени Тисленко Т.Б. в предоставленном на исследование Объекте №1 при первом проколе.\",\n      \"structured_details\": {\n        \"object_type\": \"ЯМР участок исследуемых штрихов\",\n        \"source_item\": \"рукописной подписи от имени Тисленко Т.Б.\",\n        \"investigation_object\": \"Объект №1\",\n        \"condition\": \"при первом проколе\"\n      }\n    }\n  }\n]\n```",
  "graphs": [
    {
      "graph_id": 1,
      "header_data": {
        "full_text": "Образец № 1 к Заключению № 11366; Индекс кристалличности = 0.8029%; Протонная плотность = 0.35677",
        "structured_metrics": {
          "sample_reference": "Образец № 1 к Заключению № 11366",
          "crystallinity_index": 0.8029,
          "proton_density": 0.35677
        }
      },
      "graph_statistics": {
        "axes": {
          "y_axis": {
            "label": "Интенсивность, %",
            "visible_min": -5,
            "visible_max": 45,
            "step_interval": 5
          },
          "x_axis": {
            "label": "Время, мкс",
            "visible_min": 0,
            "visible_max": 175,
            "step_interval": 25
          }
        },
        "y_metrics_max": {
          "red": 40,
          "blue": 24,
          "green": 40
        },
        "visible_tabs": [
          "NMR Signal",
          "Results Graph",
          "Code"
        ]
      },
      "caption_data": {
        "illustration_number": "№1",
        "full_text": "Иллюстрация №1. Изображение одного из ЯМР участков исследуемых штрихов рукописной подписи от имени Губаева С.С. в предоставленном на исследование Объекте №1 при первом проколе.",
        "structured_details": {
          "object_type": "ЯМР участок исследуемых штрихов",
          "source_item": "рукописной подписи от имени Губаева С.С.",
          "investigation_object": "Объект №1",
          "condition": "при первом проколе"
        }
      }
    },
    {
      "graph_id": 2,
      "header_data": {
        "full_text": "Образец № 1 к Заключению № 11366; Индекс кристалличности = 0.81836; Протонная плотность = 0.06842",
        "structured_metrics": {
          "sample_reference": "Образец № 1 к Заключению № 11366",
          "crystallinity_index": 0.81836,
          "proton_density": 0.06842
        }
      },
      "graph_statistics": {
        "axes": {
          "y_axis": {
            "label": "Интенсивность, %",
            "visible_min": -5,
            "visible_max": 45,
            "step_interval": 5
          },
          "x_axis": {
            "label": "Время, мкс",
            "visible_min": 0,
            "visible_max": 250,
            "step_interval": 50
          }
        },
        "y_metrics_max": {
          "red": 40,
          "blue": 38,
          "green": 30
        },
        "visible_tabs": [
          "NMR Signal",
          "Results Graph",
          "Code"
        ]
      },
      "caption_data": {
        "illustration_number": "№2",
        "full_text": "Иллюстрация №2. Изображение одного из ЯМР участков исследуемых штрихов рукописной подписи от имени Тисленко Т.Б. в предоставленном на исследование Объекте №1 при первом проколе.",
        "structured_details": {
          "object_type": "ЯМР участок исследуемых штрихов",
          "source_item": "рукописной подписи от имени Тисленко Т.Б.",
          "investigation_object": "Объект №1",
          "condition": "при первом проколе"
        }
      }
    }
  ],
  "model": "gpt-4o-2024-08-06",
  "usage": {
    "prompt_tokens": 2055,
    "completion_tokens": 842,
    "total_tokens": 2897,
    "prompt_tokens_details": {
      "cached_tokens": 0,
      "audio_tokens": 0
    },
    "completion_tokens_details": {
      "reasoning_tokens": 0,
      "audio_tokens": 0,
      "accepted_prediction_tokens": 0,
      "rejected_prediction_tokens": 0
    }
  }
}