{
  "page": 19,
  "content": "```json\n[\n  {\n    \"graph_id\": 1,\n    \"header_data\": {\n      \"full_text\": \"Образец № 1 к Заключению № 11366; Индекс кристалличности = 0.80857; Протонная плотность = 0.69806\",\n      \"structured_metrics\": {\n        \"sample_reference\": \"Образец № 1 к Заключению № 11366\",\n        \"crystallinity_index\": 0.80857,\n        \"proton_density\": 0.69806\n      }\n    },\n    \"graph_statistics\": {\n      \"axes\": {\n        \"y_axis\": {\n          \"label\": \"Интенсивность, %\",\n          \"visible_min\": -8,\n          \"visible_max\": 44,\n          \"step_interval\": 8\n        },\n        \"x_axis\": {\n          \"label\": \"Время, мкс\",\n          \"visible_min\": 0,\n          \"visible_max\": 165,\n          \"step_interval\": 15\n        }\n      },\n      \"y_metrics_max\": {\n        \"red\": 40,\n        \"blue\": 32,\n        \"green\": 30\n      },\n      \"visible_tabs\": [\"NMR Signal\", \"Results Graph\", \"Code\"]\n    },\n    \"caption_data\": {\n      \"illustration_number\": \"№37\",\n      \"full_text\": \"Иллюстрация №37. Изображение одного из ЯМР участков исследуемых штрихов рукописной подписи от имени Тисленко Т.Б. в предоставленном на исследование Объекте №9 при первом проколе.\",\n      \"structured_details\": {\n        \"object_type\": \"ЯМР участок исследуемых штрихов\",\n        \"source_item\": \"рукописная подпись от имени Тисленко Т.Б.\",\n        \"investigation_object\": \"Объект №9\",\n        \"condition\": \"при первом проколе\"\n      }\n    }\n  },\n  {\n    \"graph_id\": 2,\n    \"header_data\": {\n      \"full_text\": \"Образец № 1 к Заключению № 11366; Индекс кристалличности = 0.80863; Протонная плотность = 0.10674\",\n      \"structured_metrics\": {\n        \"sample_reference\": \"Образец № 1 к Заключению № 11366\",\n        \"crystallinity_index\": 0.80863,\n        \"proton_density\": 0.10674\n      }\n    },\n    \"graph_statistics\": {\n      \"axes\": {\n        \"y_axis\": {\n          \"label\": \"Интенсивность, %\",\n          \"visible_min\": -40,\n          \"visible_max\": 24,\n          \"step_interval\": 8\n        },\n        \"x_axis\": {\n          \"label\": \"Время, мкс\",\n          \"visible_min\": 0,\n          \"visible_max\": 405,\n          \"step_interval\": 45\n        }\n      },\n      \"y_metrics_max\": {\n        \"red\": 16,\n        \"blue\": 0,\n        \"green\": 8\n      },\n      \"visible_tabs\": [\"NMR Signal\", \"Results Graph\", \"Code\"]\n    },\n    \"caption_data\": {\n      \"illustration_number\": \"№38\",\n      \"full_text\": \"Иллюстрация №38. Изображение одного из ЯМР участков исследуемых штрихов рукописной подписи от имени Филиппенко И.Н. в предоставленном на исследование Объекте №9 при первом проколе.\",\n      \"structured_details\": {\n        \"object_type\": \"ЯМР участок исследуемых штрихов\",\n        \"source_item\": \"рукописная подпись от имени Филиппенко И.Н.\",\n        \"investigation_object\": \"Объект №9\",\n        \"condition\": \"при первом проколе\"\n      }\n    }\n  }\n]\n```",
  "graphs": [
    {
      "graph_id": 1,
      "header_data": {
        "full_text": "Образец № 1 к Заключению № 11366; Индекс кристалличности = 0.80857; Протонная плотность = 0.69806",
        "structured_metrics": {
          "sample_reference": "Образец № 1 к Заключению № 11366",
          "crystallinity_index": 0.80857,
          "proton_density": 0.69806
        }
      },
      "graph_statistics": {
        "axes": {
          "y_axis": {
            "label": "Интенсивность, %",
            "visible_min": -8,
            "visible_max": 44,
            "step_interval": 8
          },
          "x_axis": {
            "label": "Время, мкс",
            "visible_min": 0,
            "visible_max": 165,
            "step_interval": 15
          }
        },
        "y_metrics_max": {
          "red": 40,
          "blue": 32,
          "green": 30
        },
        "visible_tabs": [
          "NMR Signal",
          "Results Graph",
          "Code"
        ]
      },
      "caption_data": {
        "illustration_number": "№37",
        "full_text": "Иллюстрация №37. Изображение одного из ЯМР участков исследуемых штрихов рукописной подписи от имени Тисленко Т.Б. в предоставленном на исследование Объекте №9 при первом проколе.",
        "structured_details": {
          "object_type": "ЯМР участок исследуемых штрихов",
          "source_item": "рукописная подпись от имени Тисленко Т.Б.",
          "investigation_object": "Объект №9",
          "condition": "при первом проколе"
        }
      }
    },
    {
      "graph_id": 2,
      "header_data": {
        "full_text": "Образец № 1 к Заключению № 11366; Индекс кристалличности = 0.80863; Протонная плотность = 0.10674",
        "structured_metrics": {
          "sample_reference": "Образец № 1 к Заключению № 11366",
          "crystallinity_index": 0.80863,
          "proton_density": 0.10674
        }
      },
      "graph_statistics": {
        "axes": {
          "y_axis": {
            "label": "Интенсивность, %",
            "visible_min": -40,
            "visible_max": 24,
            "step_interval": 8
          },
          "x_axis": {
            "label": "Время, мкс",
            "visible_min": 0,
            "visible_max": 405,
            "step_interval": 45
          }
        },
        "y_metrics_max": {
          "red": 16,
          "blue": 0,
          "green": 8
        },
        "visible_tabs": [
          "NMR Signal",
          "Results Graph",
          "Code"
        ]
      },
      "caption_data": {
        "illustration_number": "№38",
        "full_text": "Иллюстрация №38. Изображение одного из ЯМР участков исследуемых штрихов рукописной подписи от имени Филиппенко И.Н. в предоставленном на исследование Объекте №9 при первом проколе.",
        "structured_details": {
          "object_type": "ЯМР участок исследуемых штрихов",
          "source_item": "рукописная подпись от имени Филиппенко И.Н.",
          "investigation_object": "Объект №9",
          "condition": "при первом проколе"
        }
      }
    }
  ],
  "model": "gpt-4o-2024-08-06",
  "usage": {
    "prompt_tokens": 2055,
    "completion_tokens": 842,
    "total_tokens": 2897,
    "prompt_tokens_details": {
      "cached_tokens": 0,
      "audio_tokens": 0
    },
    "completion_tokens_details": {
      "reasoning_tokens": 0,
      "audio_tokens": 0,
      "accepted_prediction_tokens": 0,
      "rejected_prediction_tokens": 0
    }
  }
}