{
  "page": 26,
  "content": "```json\n[\n  {\n    \"graph_id\": 1,\n    \"header_data\": {\n      \"full_text\": \"Образец № 1 к Заключению № 11366; Индекс кристалличности = 0.78864; Протонная плотность = 0.56207\",\n      \"structured_metrics\": {\n        \"sample_reference\": \"Образец № 1 к Заключению № 11366\",\n        \"crystallinity_index\": 0.78864,\n        \"proton_density\": 0.56207\n      }\n    },\n    \"graph_statistics\": {\n      \"axes\": {\n        \"y_axis\": {\n          \"label\": \"Интенсивность, %\",\n          \"visible_min\": -20,\n          \"visible_max\": 20,\n          \"step_interval\": 4\n        },\n        \"x_axis\": {\n          \"label\": \"Время, мкс\",\n          \"visible_min\": 0,\n          \"visible_max\": 170,\n          \"step_interval\": 10\n        }\n      },\n      \"y_metrics_max\": {\n        \"red\": 20,\n        \"blue\": 14,\n        \"green\": null\n      },\n      \"visible_tabs\": [\"NMR Signal\", \"Results Graph\", \"Code\"]\n    },\n    \"caption_data\": {\n      \"illustration_number\": \"№51\",\n      \"full_text\": \"Иллюстрация №51. Изображение одного из ЯМР участков исследуемых штрихов рукописной подписи от имени Волобько И.А. в предоставленном на исследование Объекте №12 при первом проколе.\",\n      \"structured_details\": {\n        \"object_type\": \"ЯМР участок исследуемых штрихов\",\n        \"source_item\": \"рукописной подписи от имени Волобько И.А.\",\n        \"investigation_object\": \"Объект №12\",\n        \"condition\": \"при первом проколе\"\n      }\n    }\n  },\n  {\n    \"graph_id\": 2,\n    \"header_data\": {\n      \"full_text\": \"Образец № 1 к Заключению № 11366; Индекс кристалличности = 0.84622; Протонная плотность = 0.21450\",\n      \"structured_metrics\": {\n        \"sample_reference\": \"Образец № 1 к Заключению № 11366\",\n        \"crystallinity_index\": 0.84622,\n        \"proton_density\": 0.21450\n      }\n    },\n    \"graph_statistics\": {\n      \"axes\": {\n        \"y_axis\": {\n          \"label\": \"Интенсивность, %\",\n          \"visible_min\": -20,\n          \"visible_max\": 20,\n          \"step_interval\": 4\n        },\n        \"x_axis\": {\n          \"label\": \"Время, мкс\",\n          \"visible_min\": 0,\n          \"visible_max\": 115,\n          \"step_interval\": 5\n        }\n      },\n      \"y_metrics_max\": {\n        \"red\": 16,\n        \"blue\": null,\n        \"green\": 12\n      },\n      \"visible_tabs\": [\"NMR Signal\", \"Code\"]\n    },\n    \"caption_data\": {\n      \"illustration_number\": \"№52\",\n      \"full_text\": \"Иллюстрация №52. Изображение одного из ЯМР участков исследуемых штрихов рукописной подписи от имени Тисленко Т.Б. в предоставленном на исследование Объекте №12 при первом проколе.\",\n      \"structured_details\": {\n        \"object_type\": \"ЯМР участок исследуемых штрихов\",\n        \"source_item\": \"рукописной подписи от имени Тисленко Т.Б.\",\n        \"investigation_object\": \"Объект №12\",\n        \"condition\": \"при первом проколе\"\n      }\n    }\n  }\n]\n```",
  "graphs": [
    {
      "graph_id": 1,
      "header_data": {
        "full_text": "Образец № 1 к Заключению № 11366; Индекс кристалличности = 0.78864; Протонная плотность = 0.56207",
        "structured_metrics": {
          "sample_reference": "Образец № 1 к Заключению № 11366",
          "crystallinity_index": 0.78864,
          "proton_density": 0.56207
        }
      },
      "graph_statistics": {
        "axes": {
          "y_axis": {
            "label": "Интенсивность, %",
            "visible_min": -20,
            "visible_max": 20,
            "step_interval": 4
          },
          "x_axis": {
            "label": "Время, мкс",
            "visible_min": 0,
            "visible_max": 170,
            "step_interval": 10
          }
        },
        "y_metrics_max": {
          "red": 20,
          "blue": 14,
          "green": null
        },
        "visible_tabs": [
          "NMR Signal",
          "Results Graph",
          "Code"
        ]
      },
      "caption_data": {
        "illustration_number": "№51",
        "full_text": "Иллюстрация №51. Изображение одного из ЯМР участков исследуемых штрихов рукописной подписи от имени Волобько И.А. в предоставленном на исследование Объекте №12 при первом проколе.",
        "structured_details": {
          "object_type": "ЯМР участок исследуемых штрихов",
          "source_item": "рукописной подписи от имени Волобько И.А.",
          "investigation_object": "Объект №12",
          "condition": "при первом проколе"
        }
      }
    },
    {
      "graph_id": 2,
      "header_data": {
        "full_text": "Образец № 1 к Заключению № 11366; Индекс кристалличности = 0.84622; Протонная плотность = 0.21450",
        "structured_metrics": {
          "sample_reference": "Образец № 1 к Заключению № 11366",
          "crystallinity_index": 0.84622,
          "proton_density": 0.2145
        }
      },
      "graph_statistics": {
        "axes": {
          "y_axis": {
            "label": "Интенсивность, %",
            "visible_min": -20,
            "visible_max": 20,
            "step_interval": 4
          },
          "x_axis": {
            "label": "Время, мкс",
            "visible_min": 0,
            "visible_max": 115,
            "step_interval": 5
          }
        },
        "y_metrics_max": {
          "red": 16,
          "blue": null,
          "green": 12
        },
        "visible_tabs": [
          "NMR Signal",
          "Code"
        ]
      },
      "caption_data": {
        "illustration_number": "№52",
        "full_text": "Иллюстрация №52. Изображение одного из ЯМР участков исследуемых штрихов рукописной подписи от имени Тисленко Т.Б. в предоставленном на исследование Объекте №12 при первом проколе.",
        "structured_details": {
          "object_type": "ЯМР участок исследуемых штрихов",
          "source_item": "рукописной подписи от имени Тисленко Т.Б.",
          "investigation_object": "Объект №12",
          "condition": "при первом проколе"
        }
      }
    }
  ],
  "model": "gpt-4o-2024-08-06",
  "usage": {
    "prompt_tokens": 2055,
    "completion_tokens": 836,
    "total_tokens": 2891,
    "prompt_tokens_details": {
      "cached_tokens": 0,
      "audio_tokens": 0
    },
    "completion_tokens_details": {
      "reasoning_tokens": 0,
      "audio_tokens": 0,
      "accepted_prediction_tokens": 0,
      "rejected_prediction_tokens": 0
    }
  }
}