{
  "page": 42,
  "content": "```json\n[\n  {\n    \"graph_id\": 1,\n    \"header_data\": {\n      \"full_text\": \"Образец № 3 к Заключению № 11366; Индекс кристалличности = 0.70949; Протонная плотность = 0.05827\",\n      \"structured_metrics\": {\n        \"sample_reference\": \"Образец № 3 к Заключению № 11366\",\n        \"crystallinity_index\": 0.70949,\n        \"proton_density\": 0.05827\n      }\n    },\n    \"graph_statistics\": {\n      \"axes\": {\n        \"y_axis\": {\n          \"label\": \"Интенсивность, %,\",\n          \"visible_min\": -20,\n          \"visible_max\": 90,\n          \"step_interval\": 10\n        },\n        \"x_axis\": {\n          \"label\": \"Время, мкс\",\n          \"visible_min\": 0,\n          \"visible_max\": 400,\n          \"step_interval\": 40\n        }\n      },\n      \"y_metrics_max\": {\n        \"red\": 48,\n        \"blue\": 67,\n        \"green\": 66\n      },\n      \"visible_tabs\": [\"NMR Signal\", \"Results Graph\", \"Code\"]\n    },\n    \"caption_data\": {\n      \"illustration_number\": \"№83\",\n      \"full_text\": \"Иллюстрация №83. Изображение одного из ЯМР участков исследуемых штрихов рукописной подписи от имени Губашева С.С. в предоставленном на исследование Объекте №2 при третьем проколе.\",\n      \"structured_details\": {\n        \"object_type\": \"ЯМР участок исследуемых штрихов\",\n        \"source_item\": \"рукописной подписи от имени Губашева С.С.\",\n        \"investigation_object\": \"Объекте №2\",\n        \"condition\": \"при третьем проколе\"\n      }\n    }\n  },\n  {\n    \"graph_id\": 2,\n    \"header_data\": {\n      \"full_text\": \"Образец № 3 к Заключению № 11366; Индекс кристалличности = 0.70227; Протонная плотность = 0.32139\",\n      \"structured_metrics\": {\n        \"sample_reference\": \"Образец № 3 к Заключению № 11366\",\n        \"crystallinity_index\": 0.70227,\n        \"proton_density\": 0.32139\n      }\n    },\n    \"graph_statistics\": {\n      \"axes\": {\n        \"y_axis\": {\n          \"label\": \"Интенсивность, %\",\n          \"visible_min\": -50,\n          \"visible_max\": 54,\n          \"step_interval\": 10\n        },\n        \"x_axis\": {\n          \"label\": \"Время, мкс\",\n          \"visible_min\": 0,\n          \"visible_max\": 115,\n          \"step_interval\": 10\n        }\n      },\n      \"y_metrics_max\": {\n        \"red\": 47,\n        \"blue\": 48,\n        \"green\": 47\n      },\n      \"visible_tabs\": [\"NMR Signal\", \"Results Graph\", \"Code\"]\n    },\n    \"caption_data\": {\n      \"illustration_number\": \"№84\",\n      \"full_text\": \"Иллюстрация №84. Изображение одного из ЯМР участков исследуемых штрихов рукописной подписи от имени Тисленко Т.Б. в предоставленном на исследование Объекте №2 при третьем проколе.\",\n      \"structured_details\": {\n        \"object_type\": \"ЯМР участок исследуемых штрихов\",\n        \"source_item\": \"рукописной подписи от имени Тисленко Т.Б.\",\n        \"investigation_object\": \"Объекте №2\",\n        \"condition\": \"при третьем проколе\"\n      }\n    }\n  }\n]\n```",
  "graphs": [
    {
      "graph_id": 1,
      "header_data": {
        "full_text": "Образец № 3 к Заключению № 11366; Индекс кристалличности = 0.70949; Протонная плотность = 0.05827",
        "structured_metrics": {
          "sample_reference": "Образец № 3 к Заключению № 11366",
          "crystallinity_index": 0.70949,
          "proton_density": 0.05827
        }
      },
      "graph_statistics": {
        "axes": {
          "y_axis": {
            "label": "Интенсивность, %,",
            "visible_min": -20,
            "visible_max": 90,
            "step_interval": 10
          },
          "x_axis": {
            "label": "Время, мкс",
            "visible_min": 0,
            "visible_max": 400,
            "step_interval": 40
          }
        },
        "y_metrics_max": {
          "red": 48,
          "blue": 67,
          "green": 66
        },
        "visible_tabs": [
          "NMR Signal",
          "Results Graph",
          "Code"
        ]
      },
      "caption_data": {
        "illustration_number": "№83",
        "full_text": "Иллюстрация №83. Изображение одного из ЯМР участков исследуемых штрихов рукописной подписи от имени Губашева С.С. в предоставленном на исследование Объекте №2 при третьем проколе.",
        "structured_details": {
          "object_type": "ЯМР участок исследуемых штрихов",
          "source_item": "рукописной подписи от имени Губашева С.С.",
          "investigation_object": "Объекте №2",
          "condition": "при третьем проколе"
        }
      }
    },
    {
      "graph_id": 2,
      "header_data": {
        "full_text": "Образец № 3 к Заключению № 11366; Индекс кристалличности = 0.70227; Протонная плотность = 0.32139",
        "structured_metrics": {
          "sample_reference": "Образец № 3 к Заключению № 11366",
          "crystallinity_index": 0.70227,
          "proton_density": 0.32139
        }
      },
      "graph_statistics": {
        "axes": {
          "y_axis": {
            "label": "Интенсивность, %",
            "visible_min": -50,
            "visible_max": 54,
            "step_interval": 10
          },
          "x_axis": {
            "label": "Время, мкс",
            "visible_min": 0,
            "visible_max": 115,
            "step_interval": 10
          }
        },
        "y_metrics_max": {
          "red": 47,
          "blue": 48,
          "green": 47
        },
        "visible_tabs": [
          "NMR Signal",
          "Results Graph",
          "Code"
        ]
      },
      "caption_data": {
        "illustration_number": "№84",
        "full_text": "Иллюстрация №84. Изображение одного из ЯМР участков исследуемых штрихов рукописной подписи от имени Тисленко Т.Б. в предоставленном на исследование Объекте №2 при третьем проколе.",
        "structured_details": {
          "object_type": "ЯМР участок исследуемых штрихов",
          "source_item": "рукописной подписи от имени Тисленко Т.Б.",
          "investigation_object": "Объекте №2",
          "condition": "при третьем проколе"
        }
      }
    }
  ],
  "model": "gpt-4o-2024-08-06",
  "usage": {
    "prompt_tokens": 2055,
    "completion_tokens": 848,
    "total_tokens": 2903,
    "prompt_tokens_details": {
      "cached_tokens": 0,
      "audio_tokens": 0
    },
    "completion_tokens_details": {
      "reasoning_tokens": 0,
      "audio_tokens": 0,
      "accepted_prediction_tokens": 0,
      "rejected_prediction_tokens": 0
    }
  }
}